Workbook

Sheet Change Overview
A1: SMTinel | YOKOTEN | DEVIATION + ECO CONTROL
A4: Fuente de importacion | B4: Deviation.csv + EngineeringChangeOrder.csv
A5: Fecha de evaluacion | B5: 46311
A7: INDICADORES DEL MAESTRO
A9: Desviaciones en registro | B9: =COUNTIF('Change Register'!B2:B5000,"DEVIATION") -> 487
A10: Registros CSV originales | B10: =COUNTA('Deviation Raw'!A2:A5000) -> 1890
A11: Combinaciones unicas CTAN + BU + PN | B11: =COUNTA('Deviation Items'!A2:A4000) -> 1786
A12: Reglas PCBA candidatas (DEV + ECO) | B12: =COUNTA('Change Applicability'!A2:A5000) -> 903
A13: Desviaciones con fecha fin abierta | B13: =COUNTIF('Deviation Radar'!L2:L3000,"END DATE NOT PASSED") -> 102
A14: Desviaciones con conflictos en status/alcance | B14: =COUNTIF('Deviation Radar'!K2:K3000,"?*") -> 10
A15: Alertas certificadas listas para SMTinel | B15: =COUNTIFS('Change Applicability'!Z2:Z5000,"Verified",'Change Applicability'!AA2:AA5000,"Y") -> 0
A16: Part Numbers excluidos de FJZ | B16: =COUNTIF('Deviation Items'!O2:O4000,"EXCLUDED - FJZ RULE") -> 2
A19: CRITERIOS DE PUBLICACION Y CONTROL
A21: • Fuentes: Deviation.csv y EngineeringChangeOrder.csv. Son exportables de seguimiento, NO documentos customer firmados ni permiso de sustitución.
A22: • Fecha fin abierta NO equivale a desviacion aprobada ni activa. El estado CCB, FAI Status o Implementation se muestra como fuente sin convertirlo a Approved.
A23: • Register: 487 DEV + 728 ECO de fuente. Applicability: PN 73- exacto; ECO usa REV NUEVA literal y guarda REV VIEJA como antecedente. Todas Pending Review / Active=N.
A24: • Deviation Items relaciona todos los numeros de parte (incluyendo CPN, chassis, PCB y ensambles) sin asumir que son un PCBA o material anterior/nuevo.
A25: • Deviation Raw preserva las 1,890 filas originales y evidencia de origen. Deviation Radar resume estados y candidatos para curacion.
A26: • Desviaciones sin revisión explícita quedan candidatas por PN (rev por validar), no coincidencias por revisión. No heredar automáticamente A0/B0/C0.
A27: • No aplicar automaticamente PN 73-19152-02 o 17-15768-01 en FJZ. Buscar caso explicito en documento y Common DB antes de reconsiderar.
A28: • Para alertas operativas: verificar aprobacion oficial, revision, BOM/AVL, WO, fecha de corrida, sitio y orden de cambio. Luego marcar Verified + Active=Y.
A29: • ECO ya incorporados; el Agile ECN asociado NO crea automáticamente un documento ECN separado. Los documentos ECO sin PN 73-, BU o REV confiables requieren revisión de alcance.
A32: ORDEN RECOMENDADO: SKU → REVISION → PCBA PN → DOCUMENTO → COMPONENTE → VIGENCIA → EVIDENCIA.
A34: Detalle: ECO Radar / ECO Items / ECO BOM Ops conservan las revisiones old→new, material, fuente y origen; Deviation Instructions conserva instrucciones de desviaciones.
A36: ECO | RESULTADO DE IMPORTACIÓN
A37: Documentos ECO fuente | B37: =COUNTIF('Change Register'!B2:B5000,"ECO") -> 728
A38: Filas CSV ECO originales | B38: 11011
A39: Filas con ECO # ausente / inválido | B39: 464
A40: Items ECO consolidados | B40: 5522
A41: Operaciones BOM originales deduplicadas | B41: 5765
A42: Reglas ECO PN+Rev exacta | B42: 356
A43: Revisiones simbólicas / no exactas omitidas | B43: 87
A44: ECNs independientes | B44: 0

Sheet Deviation Radar
A1: CTAN Number | B1: Cisco Deviation | C1: BU | D1: Workflow Status (source) | E1: Date Released (source) | F1: Effective To (source) | G1: CSV Rows | H1: Unique Items | I1: PCBA PN Candidates | J1: Known SKU Matches | K1: Source Conflicts | L1: Date Window (screening) | M1: Release Status (screening) | N1: Review Priority | O1: Next Action
A2: CTANJZ04014 | B2: D598638 | C2: SRGBU | D2: Closed | E2: 45514 | F2: 47790 | G2: 1 | H2: 1 | L2: =IF(F2="","REVIEW: DATE CONFLICT/EMPTY",IF(F2<'Change Overview'!$B$5,"END DATE PASSED","END DATE NOT PASSED")) -> END DATE NOT PASSED | M2: =IF(K2<>"","REVIEW SOURCE CONFLICT",IF(OR(ISNUMBER(SEARCH("CCB",D2)),ISNUMBER(SEARCH("Pending",D2))),"CCB/PENDING",IF(OR(ISNUMBER(SEARCH("Expired",D2)),ISNUMBER(SEARCH("Closed",D2))),"CLOSED/EXPIRED",IF(E2="","NO RELEASE DATE","REVIEW APPROVAL")))) -> CLOSED/EXPIRED | N2: =IF(K2<>"","HIGH: SOURCE CONFLICT",IF(AND(L2="END DATE NOT PASSED",M2="REVIEW APPROVAL"),"HIGH: VERIFY",IF(L2="END DATE NOT PASSED","MEDIUM: CHECK STATUS","LOW: HISTORICAL"))) -> MEDIUM: CHECK STATUS | O2: Validar documento firmado, revision/WO/sitio, material afectado y evidencia antes de activar alerta automatica.
A3: CTANJZ04427 | B3: D601187 | C3: STBU | D3: Expired | E3: 45713 | F3: 45775 | G3: 3 | H3: 3 | I3: 73-20249-05 | L3: =IF(F3="","REVIEW: DATE CONFLICT/EMPTY",IF(F3<'Change Overview'!$B$5,"END DATE PASSED","END DATE NOT PASSED")) -> END DATE PASSED | M3: =IF(K3<>"","REVIEW SOURCE CONFLICT",IF(OR(ISNUMBER(SEARCH("CCB",D3)),ISNUMBER(SEARCH("Pending",D3))),"CCB/PENDING",IF(OR(ISNUMBER(SEARCH("Expired",D3)),ISNUMBER(SEARCH("Closed",D3))),"CLOSED/EXPIRED",IF(E3="","NO RELEASE DATE","REVIEW APPROVAL")))) -> CLOSED/EXPIRED | N3: =IF(K3<>"","HIGH: SOURCE CONFLICT",IF(AND(L3="END DATE NOT PASSED",M3="REVIEW APPROVAL"),"HIGH: VERIFY",IF(L3="END DATE NOT PASSED","MEDIUM: CHECK STATUS","LOW: HISTORICAL"))) -> LOW: HISTORICAL | O3: Validar documento firmado, revision/WO/sitio, material afectado y evidencia antes de activar alerta automatica.
A4: CTANJZ04430 | B4: D601838 | C4: STBU | D4: Expired | E4: 45709 | F4: 45783 | G4: 1 | H4: 1 | L4: =IF(F4="","REVIEW: DATE CONFLICT/EMPTY",IF(F4<'Change Overview'!$B$5,"END DATE PASSED","END DATE NOT PASSED")) -> END DATE PASSED | M4: =IF(K4<>"","REVIEW SOURCE CONFLICT",IF(OR(ISNUMBER(SEARCH("CCB",D4)),ISNUMBER(SEARCH("Pending",D4))),"CCB/PENDING",IF(OR(ISNUMBER(SEARCH("Expired",D4)),ISNUMBER(SEARCH("Closed",D4))),"CLOSED/EXPIRED",IF(E4="","NO RELEASE DATE","REVIEW APPROVAL")))) -> CLOSED/EXPIRED | N4: =IF(K4<>"","HIGH: SOURCE CONFLICT",IF(AND(L4="END DATE NOT PASSED",M4="REVIEW APPROVAL"),"HIGH: VERIFY",IF(L4="END DATE NOT PASSED","MEDIUM: CHECK STATUS","LOW: HISTORICAL"))) -> LOW: HISTORICAL | O4: Validar documento firmado, revision/WO/sitio, material afectado y evidencia antes de activar alerta automatica.
A5: CTANJZ04431 | B5: D601949 | C5: STBU | D5: Expired | E5: 45713 | F5: 45783 | G5: 5 | H5: 5 | I5: 73-20247-05, 73-20249-05 | L5: =IF(F5="","REVIEW: DATE CONFLICT/EMPTY",IF(F5<'Change Overview'!$B$5,"END DATE PASSED","END DATE NOT PASSED")) -> END DATE PASSED | M5: =IF(K5<>"","REVIEW SOURCE CONFLICT",IF(OR(ISNUMBER(SEARCH("CCB",D5)),ISNUMBER(SEARCH("Pending",D5))),"CCB/PENDING",IF(OR(ISNUMBER(SEARCH("Expired",D5)),ISNUMBER(SEARCH("Closed",D5))),"CLOSED/EXPIRED",IF(E5="","NO RELEASE DATE","REVIEW APPROVAL")))) -> CLOSED/EXPIRED | N5: =IF(K5<>"","HIGH: SOURCE CONFLICT",IF(AND(L5="END DATE NOT PASSED",M5="REVIEW APPROVAL"),"HIGH: VERIFY",IF(L5="END DATE NOT PASSED","MEDIUM: CHECK STATUS","LOW: HISTORICAL"))) -> LOW: HISTORICAL | O5: Validar documento firmado, revision/WO/sitio, material afectado y evidencia antes de activar alerta automatica.
A6: CTANJZ04432 | B6: D601971 | C6: SRGBU | D6: Expired | E6: 45709 | F6: 45783 | G6: 2 | H6: 2 | L6: =IF(F6="","REVIEW: DATE CONFLICT/EMPTY",IF(F6<'Change Overview'!$B$5,"END DATE PASSED","END DATE NOT PASSED")) -> END DATE PASSED | M6: =IF(K6<>"","REVIEW SOURCE CONFLICT",IF(OR(ISNUMBER(SEARCH("CCB",D6)),ISNUMBER(SEARCH("Pending",D6))),"CCB/PENDING",IF(OR(ISNUMBER(SEARCH("Expired",D6)),ISNUMBER(SEARCH("Closed",D6))),"CLOSED/EXPIRED",IF(E6="","NO RELEASE DATE","REVIEW APPROVAL")))) -> CLOSED/EXPIRED | N6: =IF(K6<>"","HIGH: SOURCE CONFLICT",IF(AND(L6="END DATE NOT PASSED",M6="REVIEW APPROVAL"),"HIGH: VERIFY",IF(L6="END DATE NOT PASSED","MEDIUM: CHECK STATUS","LOW: HISTORICAL"))) -> LOW: HISTORICAL | O6: Validar documento firmado, revision/WO/sitio, material afectado y evidencia antes de activar alerta automatica.
A7: CTANJZ04435 | B7: D596346 | C7: STBU | D7: Expired | E7: 45709 | F7: 45783 | G7: 1 | H7: 1 | L7: =IF(F7="","REVIEW: DATE CONFLICT/EMPTY",IF(F7<'Change Overview'!$B$5,"END DATE PASSED","END DATE NOT PASSED")) -> END DATE PASSED | M7: =IF(K7<>"","REVIEW SOURCE CONFLICT",IF(OR(ISNUMBER(SEARCH("CCB",D7)),ISNUMBER(SEARCH("Pending",D7))),"CCB/PENDING",IF(OR(ISNUMBER(SEARCH("Expired",D7)),ISNUMBER(SEARCH("Closed",D7))),"CLOSED/EXPIRED",IF(E7="","NO RELEASE DATE","REVIEW APPROVAL")))) -> CLOSED/EXPIRED | N7: =IF(K7<>"","HIGH: SOURCE CONFLICT",IF(AND(L7="END DATE NOT PASSED",M7="REVIEW APPROVAL"),"HIGH: VERIFY",IF(L7="END DATE NOT PASSED","MEDIUM: CHECK STATUS","LOW: HISTORICAL"))) -> LOW: HISTORICAL | O7: Validar documento firmado, revision/WO/sitio, material afectado y evidencia antes de activar alerta automatica.
A8: CTANJZ04441 | B8: D601899 | C8: SRGBU | D8: Expired | E8: 45713 | F8: 45788 | G8: 3 | H8: 3 | L8: =IF(F8="","REVIEW: DATE CONFLICT/EMPTY",IF(F8<'Change Overview'!$B$5,"END DATE PASSED","END DATE NOT PASSED")) -> END DATE PASSED | M8: =IF(K8<>"","REVIEW SOURCE CONFLICT",IF(OR(ISNUMBER(SEARCH("CCB",D8)),ISNUMBER(SEARCH("Pending",D8))),"CCB/PENDING",IF(OR(ISNUMBER(SEARCH("Expired",D8)),ISNUMBER(SEARCH("Closed",D8))),"CLOSED/EXPIRED",IF(E8="","NO RELEASE DATE","REVIEW APPROVAL")))) -> CLOSED/EXPIRED | N8: =IF(K8<>"","HIGH: SOURCE CONFLICT",IF(AND(L8="END DATE NOT PASSED",M8="REVIEW APPROVAL"),"HIGH: VERIFY",IF(L8="END DATE NOT PASSED","MEDIUM: CHECK STATUS","LOW: HISTORICAL"))) -> LOW: HISTORICAL | O8: Validar documento firmado, revision/WO/sitio, material afectado y evidencia antes de activar alerta automatica.
A9: CTANJZ04443 | B9: D601883 | C9: STBU | D9: Expired | E9: 45709 | F9: 45788 | G9: 2 | H9: 2 | L9: =IF(F9="","REVIEW: DATE CONFLICT/EMPTY",IF(F9<'Change Overview'!$B$5,"END DATE PASSED","END DATE NOT PASSED")) -> END DATE PASSED | M9: =IF(K9<>"","REVIEW SOURCE CONFLICT",IF(OR(ISNUMBER(SEARCH("CCB",D9)),ISNUMBER(SEARCH("Pending",D9))),"CCB/PENDING",IF(OR(ISNUMBER(SEARCH("Expired",D9)),ISNUMBER(SEARCH("Closed",D9))),"CLOSED/EXPIRED",IF(E9="","NO RELEASE DATE","REVIEW APPROVAL")))) -> CLOSED/EXPIRED | N9: =IF(K9<>"","HIGH: SOURCE CONFLICT",IF(AND(L9="END DATE NOT PASSED",M9="REVIEW APPROVAL"),"HIGH: VERIFY",IF(L9="END DATE NOT PASSED","MEDIUM: CHECK STATUS","LOW: HISTORICAL"))) -> LOW: HISTORICAL | O9: Validar documento firmado, revision/WO/sitio, material afectado y evidencia antes de activar alerta automatica.
A10: CTANJZ04449 | B10: D602143 | C10: STBU | D10: Expired | E10: 45709 | F10: 45789 | G10: 9 | H10: 9 | I10: 73-17567-12, 73-17568-12, 73-17569-10, 73-17570-10 | L10: =IF(F10="","REVIEW: DATE CONFLICT/EMPTY",IF(F10<'Change Overview'!$B$5,"END DATE PASSED","END DATE NOT PASSED")) -> END DATE PASSED | M10: =IF(K10<>"","REVIEW SOURCE CONFLICT",IF(OR(ISNUMBER(SEARCH("CCB",D10)),ISNUMBER(SEARCH("Pending",D10))),"CCB/PENDING",IF(OR(ISNUMBER(SEARCH("Expired",D10)),ISNUMBER(SEARCH("Closed",D10))),"CLOSED/EXPIRED",IF(E10="","NO RELEASE DATE","REVIEW APPROVAL")))) -> CLOSED/EXPIRED | N10: =IF(K10<>"","HIGH: SOURCE CONFLICT",IF(AND(L10="END DATE NOT PASSED",M10="REVIEW APPROVAL"),"HIGH: VERIFY",IF(L10="END DATE NOT PASSED","MEDIUM: CHECK STATUS","LOW: HISTORICAL"))) -> LOW: HISTORICAL | O10: Validar documento firmado, revision/WO/sitio, material afectado y evidencia antes de activar alerta automatica.
A11: CTANJZ04450 | B11: D602145 | C11: STBU | D11: Expired | E11: 45713 | F11: 45789 | G11: 7 | H11: 7 | L11: =IF(F11="","REVIEW: DATE CONFLICT/EMPTY",IF(F11<'Change Overview'!$B$5,"END DATE PASSED","END DATE NOT PASSED")) -> END DATE PASSED | M11: =IF(K11<>"","REVIEW SOURCE CONFLICT",IF(OR(ISNUMBER(SEARCH("CCB",D11)),ISNUMBER(SEARCH("Pending",D11))),"CCB/PENDING",IF(OR(ISNUMBER(SEARCH("Expired",D11)),ISNUMBER(SEARCH("Closed",D11))),"CLOSED/EXPIRED",IF(E11="","NO RELEASE DATE","REVIEW APPROVAL")))) -> CLOSED/EXPIRED | N11: =IF(K11<>"","HIGH: SOURCE CONFLICT",IF(AND(L11="END DATE NOT PASSED",M11="REVIEW APPROVAL"),"HIGH: VERIFY",IF(L11="END DATE NOT PASSED","MEDIUM: CHECK STATUS","LOW: HISTORICAL"))) -> LOW: HISTORICAL | O11: Validar documento firmado, revision/WO/sitio, material afectado y evidencia antes de activar alerta automatica.
A12: CTANJZ04453 | B12: D601097 | C12: STBU | D12: Expired | E12: 45709 | F12: 45790 | G12: 3 | H12: 3 | I12: 73-17499-07 | L12: =IF(F12="","REVIEW: DATE CONFLICT/EMPTY",IF(F12<'Change Overview'!$B$5,"END DATE PASSED","END DATE NOT PASSED")) -> END DATE PASSED | M12: =IF(K12<>"","REVIEW SOURCE CONFLICT",IF(OR(ISNUMBER(SEARCH("CCB",D12)),ISNUMBER(SEARCH("Pending",D12))),"CCB/PENDING",IF(OR(ISNUMBER(SEARCH("Expired",D12)),ISNUMBER(SEARCH("Closed",D12))),"CLOSED/EXPIRED",IF(E12="","NO RELEASE DATE","REVIEW APPROVAL")))) -> CLOSED/EXPIRED | N12: =IF(K12<>"","HIGH: SOURCE CONFLICT",IF(AND(L12="END DATE NOT PASSED",M12="REVIEW APPROVAL"),"HIGH: VERIFY",IF(L12="END DATE NOT PASSED","MEDIUM: CHECK STATUS","LOW: HISTORICAL"))) -> LOW: HISTORICAL | O12: Validar documento firmado, revision/WO/sitio, material afectado y evidencia antes de activar alerta automatica.
A13: CTANJZ04465 | B13: D602184 | C13: SRGBU | D13: Expired | E13: 45713 | F13: 45796 | G13: 3 | H13: 3 | L13: =IF(F13="","REVIEW: DATE CONFLICT/EMPTY",IF(F13<'Change Overview'!$B$5,"END DATE PASSED","END DATE NOT PASSED")) -> END DATE PASSED | M13: =IF(K13<>"","REVIEW SOURCE CONFLICT",IF(OR(ISNUMBER(SEARCH("CCB",D13)),ISNUMBER(SEARCH("Pending",D13))),"CCB/PENDING",IF(OR(ISNUMBER(SEARCH("Expired",D13)),ISNUMBER(SEARCH("Closed",D13))),"CLOSED/EXPIRED",IF(E13="","NO RELEASE DATE","REVIEW APPROVAL")))) -> CLOSED/EXPIRED | N13: =IF(K13<>"","HIGH: SOURCE CONFLICT",IF(AND(L13="END DATE NOT PASSED",M13="REVIEW APPROVAL"),"HIGH: VERIFY",IF(L13="END DATE NOT PASSED","MEDIUM: CHECK STATUS","LOW: HISTORICAL"))) -> LOW: HISTORICAL | O13: Validar documento firmado, revision/WO/sitio, material afectado y evidencia antes de activar alerta automatica.
A14: CTANJZ04466 | B14: D602196 | C14: STBU | D14: Expired | E14: 45716 | F14: 45796 | G14: 5 | H14: 5 | I14: 73-17497-04, 73-17499-07, 73-20247-06, 73-20249-06 | J14: TUFNELL PARK | L14: =IF(F14="","REVIEW: DATE CONFLICT/EMPTY",IF(F14<'Change Overview'!$B$5,"END DATE PASSED","END DATE NOT PASSED")) -> END DATE PASSED | M14: =IF(K14<>"","REVIEW SOURCE CONFLICT",IF(OR(ISNUMBER(SEARCH("CCB",D14)),ISNUMBER(SEARCH("Pending",D14))),"CCB/PENDING",IF(OR(ISNUMBER(SEARCH("Expired",D14)),ISNUMBER(SEARCH("Closed",D14))),"CLOSED/EXPIRED",IF(E14="","NO RELEASE DATE","REVIEW APPROVAL")))) -> CLOSED/EXPIRED | N14: =IF(K14<>"","HIGH: SOURCE CONFLICT",IF(AND(L14="END DATE NOT PASSED",M14="REVIEW APPROVAL"),"HIGH: VERIFY",IF(L14="END DATE NOT PASSED","MEDIUM: CHECK STATUS","LOW: HISTORICAL"))) -> LOW: HISTORICAL | O14: Validar documento firmado, revision/WO/sitio, material afectado y evidencia antes de activar alerta automatica.
A15: CTANJZ04473 | B15: D602345 | C15: STBU | D15: Expired | E15: 45720 | F15: 45799 | G15: 5 | H15: 5 | L15: =IF(F15="","REVIEW: DATE CONFLICT/EMPTY",IF(F15<'Change Overview'!$B$5,"END DATE PASSED","END DATE NOT PASSED")) -> END DATE PASSED | M15: =IF(K15<>"","REVIEW SOURCE CONFLICT",IF(OR(ISNUMBER(SEARCH("CCB",D15)),ISNUMBER(SEARCH("Pending",D15))),"CCB/PENDING",IF(OR(ISNUMBER(SEARCH("Expired",D15)),ISNUMBER(SEARCH("Closed",D15))),"CLOSED/EXPIRED",IF(E15="","NO RELEASE DATE","REVIEW APPROVAL")))) -> CLOSED/EXPIRED | N15: =IF(K15<>"","HIGH: SOURCE CONFLICT",IF(AND(L15="END DATE NOT PASSED",M15="REVIEW APPROVAL"),"HIGH: VERIFY",IF(L15="END DATE NOT PASSED","MEDIUM: CHECK STATUS","LOW: HISTORICAL"))) -> LOW: HISTORICAL | O15: Validar documento firmado, revision/WO/sitio, material afectado y evidencia antes de activar alerta automatica.
A16: CTANJZ04475 | B16: D602181 | C16: SRGBU | D16: Expired | E16: 45720 | F16: 45799 | G16: 17 | H16: 17 | I16: 73-14503-08, 73-14504-09, 73-14505-09, 73-14506-08, 73-15195-05, 73-15196-05, 73-15197-05, 73-16084-04, 73-16524-03, 73-19107-04 | L16: =IF(F16="","REVIEW: DATE CONFLICT/EMPTY",IF(F16<'Change Overview'!$B$5,"END DATE PASSED","END DATE NOT PASSED")) -> END DATE PASSED | M16: =IF(K16<>"","REVIEW SOURCE CONFLICT",IF(OR(ISNUMBER(SEARCH("CCB",D16)),ISNUMBER(SEARCH("Pending",D16))),"CCB/PENDING",IF(OR(ISNUMBER(SEARCH("Expired",D16)),ISNUMBER(SEARCH("Closed",D16))),"CLOSED/EXPIRED",IF(E16="","NO RELEASE DATE","REVIEW APPROVAL")))) -> CLOSED/EXPIRED | N16: =IF(K16<>"","HIGH: SOURCE CONFLICT",IF(AND(L16="END DATE NOT PASSED",M16="REVIEW APPROVAL"),"HIGH: VERIFY",IF(L16="END DATE NOT PASSED","MEDIUM: CHECK STATUS","LOW: HISTORICAL"))) -> LOW: HISTORICAL | O16: Validar documento firmado, revision/WO/sitio, material afectado y evidencia antes de activar alerta automatica.
A17: CTANJZ04478 | B17: DP524571 | C17: IOTBU | D17: Expired | E17: 45723 | F17: 45775 | G17: 5 | H17: 5 | I17: 73-103150-03 | L17: =IF(F17="","REVIEW: DATE CONFLICT/EMPTY",IF(F17<'Change Overview'!$B$5,"END DATE PASSED","END DATE NOT PASSED")) -> END DATE PASSED | M17: =IF(K17<>"","REVIEW SOURCE CONFLICT",IF(OR(ISNUMBER(SEARCH("CCB",D17)),ISNUMBER(SEARCH("Pending",D17))),"CCB/PENDING",IF(OR(ISNUMBER(SEARCH("Expired",D17)),ISNUMBER(SEARCH("Closed",D17))),"CLOSED/EXPIRED",IF(E17="","NO RELEASE DATE","REVIEW APPROVAL")))) -> CLOSED/EXPIRED | N17: =IF(K17<>"","HIGH: SOURCE CONFLICT",IF(AND(L17="END DATE NOT PASSED",M17="REVIEW APPROVAL"),"HIGH: VERIFY",IF(L17="END DATE NOT PASSED","MEDIUM: CHECK STATUS","LOW: HISTORICAL"))) -> LOW: HISTORICAL | O17: Validar documento firmado, revision/WO/sitio, material afectado y evidencia antes de activar alerta automatica.
A18: CTANJZ04481 | B18: D600361 | C18: STBU | D18: Expired | E18: 45736 | F18: 45809 | G18: 3 | H18: 3 | I18: 73-19332-01 | L18: =IF(F18="","REVIEW: DATE CONFLICT/EMPTY",IF(F18<'Change Overview'!$B$5,"END DATE PASSED","END DATE NOT PASSED")) -> END DATE PASSED | M18: =IF(K18<>"","REVIEW SOURCE CONFLICT",IF(OR(ISNUMBER(SEARCH("CCB",D18)),ISNUMBER(SEARCH("Pending",D18))),"CCB/PENDING",IF(OR(ISNUMBER(SEARCH("Expired",D18)),ISNUMBER(SEARCH("Closed",D18))),"CLOSED/EXPIRED",IF(E18="","NO RELEASE DATE","REVIEW APPROVAL")))) -> CLOSED/EXPIRED | N18: =IF(K18<>"","HIGH: SOURCE CONFLICT",IF(AND(L18="END DATE NOT PASSED",M18="REVIEW APPROVAL"),"HIGH: VERIFY",IF(L18="END DATE NOT PASSED","MEDIUM: CHECK STATUS","LOW: HISTORICAL"))) -> LOW: HISTORICAL | O18: Validar documento firmado, revision/WO/sitio, material afectado y evidencia antes de activar alerta automatica.
A19: CTANJZ04487 | B19: D602439 | C19: SRGBU | D19: Expired | E19: 45732 | F19: 45810 | G19: 1 | H19: 1 | L19: =IF(F19="","REVIEW: DATE CONFLICT/EMPTY",IF(F19<'Change Overview'!$B$5,"END DATE PASSED","END DATE NOT PASSED")) -> END DATE PASSED | M19: =IF(K19<>"","REVIEW SOURCE CONFLICT",IF(OR(ISNUMBER(SEARCH("CCB",D19)),ISNUMBER(SEARCH("Pending",D19))),"CCB/PENDING",IF(OR(ISNUMBER(SEARCH("Expired",D19)),ISNUMBER(SEARCH("Closed",D19))),"CLOSED/EXPIRED",IF(E19="","NO RELEASE DATE","REVIEW APPROVAL")))) -> CLOSED/EXPIRED | N19: =IF(K19<>"","HIGH: SOURCE CONFLICT",IF(AND(L19="END DATE NOT PASSED",M19="REVIEW APPROVAL"),"HIGH: VERIFY",IF(L19="END DATE NOT PASSED","MEDIUM: CHECK STATUS","LOW: HISTORICAL"))) -> LOW: HISTORICAL | O19: Validar documento firmado, revision/WO/sitio, material afectado y evidencia antes de activar alerta automatica.
A20: CTANJZ04493 | B20: D602616 | C20: STBU | D20: Expired | E20: 45742 | F20: 45817 | G20: 6 | H20: 6 | L20: =IF(F20="","REVIEW: DATE CONFLICT/EMPTY",IF(F20<'Change Overview'!$B$5,"END DATE PASSED","END DATE NOT PASSED")) -> END DATE PASSED | M20: =IF(K20<>"","REVIEW SOURCE CONFLICT",IF(OR(ISNUMBER(SEARCH("CCB",D20)),ISNUMBER(SEARCH("Pending",D20))),"CCB/PENDING",IF(OR(ISNUMBER(SEARCH("Expired",D20)),ISNUMBER(SEARCH("Closed",D20))),"CLOSED/EXPIRED",IF(E20="","NO RELEASE DATE","REVIEW APPROVAL")))) -> CLOSED/EXPIRED | N20: =IF(K20<>"","HIGH: SOURCE CONFLICT",IF(AND(L20="END DATE NOT PASSED",M20="REVIEW APPROVAL"),"HIGH: VERIFY",IF(L20="END DATE NOT PASSED","MEDIUM: CHECK STATUS","LOW: HISTORICAL"))) -> LOW: HISTORICAL | O20: Validar documento firmado, revision/WO/sitio, material afectado y evidencia antes de activar alerta automatica.
A21: CTANJZ04503 | B21: D602312 | C21: STBU | D21: Expired | E21: 45748 | F21: 45824 | G21: 3 | H21: 3 | I21: 73-18489-07 | L21: =IF(F21="","REVIEW: DATE CONFLICT/EMPTY",IF(F21<'Change Overview'!$B$5,"END DATE PASSED","END DATE NOT PASSED")) -> END DATE PASSED | M21: =IF(K21<>"","REVIEW SOURCE CONFLICT",IF(OR(ISNUMBER(SEARCH("CCB",D21)),ISNUMBER(SEARCH("Pending",D21))),"CCB/PENDING",IF(OR(ISNUMBER(SEARCH("Expired",D21)),ISNUMBER(SEARCH("Closed",D21))),"CLOSED/EXPIRED",IF(E21="","NO RELEASE DATE","REVIEW APPROVAL")))) -> CLOSED/EXPIRED | N21: =IF(K21<>"","HIGH: SOURCE CONFLICT",IF(AND(L21="END DATE NOT PASSED",M21="REVIEW APPROVAL"),"HIGH: VERIFY",IF(L21="END DATE NOT PASSED","MEDIUM: CHECK STATUS","LOW: HISTORICAL"))) -> LOW: HISTORICAL | O21: Validar documento firmado, revision/WO/sitio, material afectado y evidencia antes de activar alerta automatica.
A22: CTANJZ04504 | B22: D602218 | C22: STBU | D22: Expired | E22: 45748 | F22: 45824 | G22: 3 | H22: 3 | I22: 73-18489-07 | L22: =IF(F22="","REVIEW: DATE CONFLICT/EMPTY",IF(F22<'Change Overview'!$B$5,"END DATE PASSED","END DATE NOT PASSED")) -> END DATE PASSED | M22: =IF(K22<>"","REVIEW SOURCE CONFLICT",IF(OR(ISNUMBER(SEARCH("CCB",D22)),ISNUMBER(SEARCH("Pending",D22))),"CCB/PENDING",IF(OR(ISNUMBER(SEARCH("Expired",D22)),ISNUMBER(SEARCH("Closed",D22))),"CLOSED/EXPIRED",IF(E22="","NO RELEASE DATE","REVIEW APPROVAL")))) -> CLOSED/EXPIRED | N22: =IF(K22<>"","HIGH: SOURCE CONFLICT",IF(AND(L22="END DATE NOT PASSED",M22="REVIEW APPROVAL"),"HIGH: VERIFY",IF(L22="END DATE NOT PASSED","MEDIUM: CHECK STATUS","LOW: HISTORICAL"))) -> LOW: HISTORICAL | O22: Validar documento firmado, revision/WO/sitio, material afectado y evidencia antes de activar alerta automatica.
A23: CTANJZ04506 | B23: D602909 | C23: SRGBU | D23: Expired | E23: 45748 | F23: 45826 | G23: 2 | H23: 2 | L23: =IF(F23="","REVIEW: DATE CONFLICT/EMPTY",IF(F23<'Change Overview'!$B$5,"END DATE PASSED","END DATE NOT PASSED")) -> END DATE PASSED | M23: =IF(K23<>"","REVIEW SOURCE CONFLICT",IF(OR(ISNUMBER(SEARCH("CCB",D23)),ISNUMBER(SEARCH("Pending",D23))),"CCB/PENDING",IF(OR(ISNUMBER(SEARCH("Expired",D23)),ISNUMBER(SEARCH("Closed",D23))),"CLOSED/EXPIRED",IF(E23="","NO RELEASE DATE","REVIEW APPROVAL")))) -> CLOSED/EXPIRED | N23: =IF(K23<>"","HIGH: SOURCE CONFLICT",IF(AND(L23="END DATE NOT PASSED",M23="REVIEW APPROVAL"),"HIGH: VERIFY",IF(L23="END DATE NOT PASSED","MEDIUM: CHECK STATUS","LOW: HISTORICAL"))) -> LOW: HISTORICAL | O23: Validar documento firmado, revision/WO/sitio, material afectado y evidencia antes de activar alerta automatica.
A24: CTANJZ04510 | B24: D601185 | C24: STBU | D24: Expired | E24: 45757 | F24: 45827 | G24: 3 | H24: 3 | I24: 73-20247-05 | L24: =IF(F24="","REVIEW: DATE CONFLICT/EMPTY",IF(F24<'Change Overview'!$B$5,"END DATE PASSED","END DATE NOT PASSED")) -> END DATE PASSED | M24: =IF(K24<>"","REVIEW SOURCE CONFLICT",IF(OR(ISNUMBER(SEARCH("CCB",D24)),ISNUMBER(SEARCH("Pending",D24))),"CCB/PENDING",IF(OR(ISNUMBER(SEARCH("Expired",D24)),ISNUMBER(SEARCH("Closed",D24))),"CLOSED/EXPIRED",IF(E24="","NO RELEASE DATE","REVIEW APPROVAL")))) -> CLOSED/EXPIRED | N24: =IF(K24<>"","HIGH: SOURCE CONFLICT",IF(AND(L24="END DATE NOT PASSED",M24="REVIEW APPROVAL"),"HIGH: VERIFY",IF(L24="END DATE NOT PASSED","MEDIUM: CHECK STATUS","LOW: HISTORICAL"))) -> LOW: HISTORICAL | O24: Validar documento firmado, revision/WO/sitio, material afectado y evidencia antes de activar alerta automatica.
A25: CTANJZ04512 | B25: D602969 | C25: STBU | D25: Expired | E25: 45750 | F25: 45920 | G25: 8 | H25: 8 | I25: 73-20247-05, 73-20249-05 | L25: =IF(F25="","REVIEW: DATE CONFLICT/EMPTY",IF(F25<'Change Overview'!$B$5,"END DATE PASSED","END DATE NOT PASSED")) -> END DATE PASSED | M25: =IF(K25<>"","REVIEW SOURCE CONFLICT",IF(OR(ISNUMBER(SEARCH("CCB",D25)),ISNUMBER(SEARCH("Pending",D25))),"CCB/PENDING",IF(OR(ISNUMBER(SEARCH("Expired",D25)),ISNUMBER(SEARCH("Closed",D25))),"CLOSED/EXPIRED",IF(E25="","NO RELEASE DATE","REVIEW APPROVAL")))) -> CLOSED/EXPIRED | N25: =IF(K25<>"","HIGH: SOURCE CONFLICT",IF(AND(L25="END DATE NOT PASSED",M25="REVIEW APPROVAL"),"HIGH: VERIFY",IF(L25="END DATE NOT PASSED","MEDIUM: CHECK STATUS","LOW: HISTORICAL"))) -> LOW: HISTORICAL | O25: Validar documento firmado, revision/WO/sitio, material afectado y evidencia antes de activar alerta automatica.
A26: CTANJZ04515 | B26: D602888 | C26: STBU | D26: Expired | E26: 45750 | F26: 45830 | G26: 1 | H26: 1 | L26: =IF(F26="","REVIEW: DATE CONFLICT/EMPTY",IF(F26<'Change Overview'!$B$5,"END DATE PASSED","END DATE NOT PASSED")) -> END DATE PASSED | M26: =IF(K26<>"","REVIEW SOURCE CONFLICT",IF(OR(ISNUMBER(SEARCH("CCB",D26)),ISNUMBER(SEARCH("Pending",D26))),"CCB/PENDING",IF(OR(ISNUMBER(SEARCH("Expired",D26)),ISNUMBER(SEARCH("Closed",D26))),"CLOSED/EXPIRED",IF(E26="","NO RELEASE DATE","REVIEW APPROVAL")))) -> CLOSED/EXPIRED | N26: =IF(K26<>"","HIGH: SOURCE CONFLICT",IF(AND(L26="END DATE NOT PASSED",M26="REVIEW APPROVAL"),"HIGH: VERIFY",IF(L26="END DATE NOT PASSED","MEDIUM: CHECK STATUS","LOW: HISTORICAL"))) -> LOW: HISTORICAL | O26: Validar documento firmado, revision/WO/sitio, material afectado y evidencia antes de activar alerta automatica.
A27: CTANJZ04518 | B27: D602944 | C27: CVEBU | D27: Expired | E27: 45751 | F27: 45831 | G27: 1 | H27: 1 | L27: =IF(F27="","REVIEW: DATE CONFLICT/EMPTY",IF(F27<'Change Overview'!$B$5,"END DATE PASSED","END DATE NOT PASSED")) -> END DATE PASSED | M27: =IF(K27<>"","REVIEW SOURCE CONFLICT",IF(OR(ISNUMBER(SEARCH("CCB",D27)),ISNUMBER(SEARCH("Pending",D27))),"CCB/PENDING",IF(OR(ISNUMBER(SEARCH("Expired",D27)),ISNUMBER(SEARCH("Closed",D27))),"CLOSED/EXPIRED",IF(E27="","NO RELEASE DATE","REVIEW APPROVAL")))) -> CLOSED/EXPIRED | N27: =IF(K27<>"","HIGH: SOURCE CONFLICT",IF(AND(L27="END DATE NOT PASSED",M27="REVIEW APPROVAL"),"HIGH: VERIFY",IF(L27="END DATE NOT PASSED","MEDIUM: CHECK STATUS","LOW: HISTORICAL"))) -> LOW: HISTORICAL | O27: Validar documento firmado, revision/WO/sitio, material afectado y evidencia antes de activar alerta automatica.
A28: CTANJZ04523 | B28: DP524680 | C28: IOTBU | D28: Expired | E28: 45751 | F28: 45801 | G28: 2 | H28: 2 | I28: 73-103098-03 | L28: =IF(F28="","REVIEW: DATE CONFLICT/EMPTY",IF(F28<'Change Overview'!$B$5,"END DATE PASSED","END DATE NOT PASSED")) -> END DATE PASSED | M28: =IF(K28<>"","REVIEW SOURCE CONFLICT",IF(OR(ISNUMBER(SEARCH("CCB",D28)),ISNUMBER(SEARCH("Pending",D28))),"CCB/PENDING",IF(OR(ISNUMBER(SEARCH("Expired",D28)),ISNUMBER(SEARCH("Closed",D28))),"CLOSED/EXPIRED",IF(E28="","NO RELEASE DATE","REVIEW APPROVAL")))) -> CLOSED/EXPIRED | N28: =IF(K28<>"","HIGH: SOURCE CONFLICT",IF(AND(L28="END DATE NOT PASSED",M28="REVIEW APPROVAL"),"HIGH: VERIFY",IF(L28="END DATE NOT PASSED","MEDIUM: CHECK STATUS","LOW: HISTORICAL"))) -> LOW: HISTORICAL | O28: Validar documento firmado, revision/WO/sitio, material afectado y evidencia antes de activar alerta automatica.
A29: CTANJZ04524 | B29: D603036 | C29: STBU | D29: Expired | E29: 45751 | F29: 45831 | G29: 2 | H29: 2 | L29: =IF(F29="","REVIEW: DATE CONFLICT/EMPTY",IF(F29<'Change Overview'!$B$5,"END DATE PASSED","END DATE NOT PASSED")) -> END DATE PASSED | M29: =IF(K29<>"","REVIEW SOURCE CONFLICT",IF(OR(ISNUMBER(SEARCH("CCB",D29)),ISNUMBER(SEARCH("Pending",D29))),"CCB/PENDING",IF(OR(ISNUMBER(SEARCH("Expired",D29)),ISNUMBER(SEARCH("Closed",D29))),"CLOSED/EXPIRED",IF(E29="","NO RELEASE DATE","REVIEW APPROVAL")))) -> CLOSED/EXPIRED | N29: =IF(K29<>"","HIGH: SOURCE CONFLICT",IF(AND(L29="END DATE NOT PASSED",M29="REVIEW APPROVAL"),"HIGH: VERIFY",IF(L29="END DATE NOT PASSED","MEDIUM: CHECK STATUS","LOW: HISTORICAL"))) -> LOW: HISTORICAL | O29: Validar documento firmado, revision/WO/sitio, material afectado y evidencia antes de activar alerta automatica.
A30: CTANJZ04526 | B30: D603054 | C30: STBU | D30: Expired | E30: 45752 | F30: 45832 | G30: 4 | H30: 4 | L30: =IF(F30="","REVIEW: DATE CONFLICT/EMPTY",IF(F30<'Change Overview'!$B$5,"END DATE PASSED","END DATE NOT PASSED")) -> END DATE PASSED | M30: =IF(K30<>"","REVIEW SOURCE CONFLICT",IF(OR(ISNUMBER(SEARCH("CCB",D30)),ISNUMBER(SEARCH("Pending",D30))),"CCB/PENDING",IF(OR(ISNUMBER(SEARCH("Expired",D30)),ISNUMBER(SEARCH("Closed",D30))),"CLOSED/EXPIRED",IF(E30="","NO RELEASE DATE","REVIEW APPROVAL")))) -> CLOSED/EXPIRED | N30: =IF(K30<>"","HIGH: SOURCE CONFLICT",IF(AND(L30="END DATE NOT PASSED",M30="REVIEW APPROVAL"),"HIGH: VERIFY",IF(L30="END DATE NOT PASSED","MEDIUM: CHECK STATUS","LOW: HISTORICAL"))) -> LOW: HISTORICAL | O30: Validar documento firmado, revision/WO/sitio, material afectado y evidencia antes de activar alerta automatica.
A31: CTANJZ04532 | B31: DP524725 | C31: STBU | D31: Expired | E31: 45752 | F31: 45804 | G31: 1 | H31: 1 | I31: 73-103558-03 | L31: =IF(F31="","REVIEW: DATE CONFLICT/EMPTY",IF(F31<'Change Overview'!$B$5,"END DATE PASSED","END DATE NOT PASSED")) -> END DATE PASSED | M31: =IF(K31<>"","REVIEW SOURCE CONFLICT",IF(OR(ISNUMBER(SEARCH("CCB",D31)),ISNUMBER(SEARCH("Pending",D31))),"CCB/PENDING",IF(OR(ISNUMBER(SEARCH("Expired",D31)),ISNUMBER(SEARCH("Closed",D31))),"CLOSED/EXPIRED",IF(E31="","NO RELEASE DATE","REVIEW APPROVAL")))) -> CLOSED/EXPIRED | N31: =IF(K31<>"","HIGH: SOURCE CONFLICT",IF(AND(L31="END DATE NOT PASSED",M31="REVIEW APPROVAL"),"HIGH: VERIFY",IF(L31="END DATE NOT PASSED","MEDIUM: CHECK STATUS","LOW: HISTORICAL"))) -> LOW: HISTORICAL | O31: Validar documento firmado, revision/WO/sitio, material afectado y evidencia antes de activar alerta automatica.
A32: CTANJZ04537 | B32: D602319 | C32: STBU | D32: Expired | E32: 45762 | F32: 45837 | G32: 12 | H32: 12 | I32: 73-20247-05, 73-20249-05 | L32: =IF(F32="","REVIEW: DATE CONFLICT/EMPTY",IF(F32<'Change Overview'!$B$5,"END DATE PASSED","END DATE NOT PASSED")) -> END DATE PASSED | M32: =IF(K32<>"","REVIEW SOURCE CONFLICT",IF(OR(ISNUMBER(SEARCH("CCB",D32)),ISNUMBER(SEARCH("Pending",D32))),"CCB/PENDING",IF(OR(ISNUMBER(SEARCH("Expired",D32)),ISNUMBER(SEARCH("Closed",D32))),"CLOSED/EXPIRED",IF(E32="","NO RELEASE DATE","REVIEW APPROVAL")))) -> CLOSED/EXPIRED | N32: =IF(K32<>"","HIGH: SOURCE CONFLICT",IF(AND(L32="END DATE NOT PASSED",M32="REVIEW APPROVAL"),"HIGH: VERIFY",IF(L32="END DATE NOT PASSED","MEDIUM: CHECK STATUS","LOW: HISTORICAL"))) -> LOW: HISTORICAL | O32: Validar documento firmado, revision/WO/sitio, material afectado y evidencia antes de activar alerta automatica.
A33: CTANJZ04545 | B33: D601188 | C33: STBU | D33: Expired | E33: 45769 | F33: 45840 | G33: 3 | H33: 3 | I33: 73-17498-04 | L33: =IF(F33="","REVIEW: DATE CONFLICT/EMPTY",IF(F33<'Change Overview'!$B$5,"END DATE PASSED","END DATE NOT PASSED")) -> END DATE PASSED | M33: =IF(K33<>"","REVIEW SOURCE CONFLICT",IF(OR(ISNUMBER(SEARCH("CCB",D33)),ISNUMBER(SEARCH("Pending",D33))),"CCB/PENDING",IF(OR(ISNUMBER(SEARCH("Expired",D33)),ISNUMBER(SEARCH("Closed",D33))),"CLOSED/EXPIRED",IF(E33="","NO RELEASE DATE","REVIEW APPROVAL")))) -> CLOSED/EXPIRED | N33: =IF(K33<>"","HIGH: SOURCE CONFLICT",IF(AND(L33="END DATE NOT PASSED",M33="REVIEW APPROVAL"),"HIGH: VERIFY",IF(L33="END DATE NOT PASSED","MEDIUM: CHECK STATUS","LOW: HISTORICAL"))) -> LOW: HISTORICAL | O33: Validar documento firmado, revision/WO/sitio, material afectado y evidencia antes de activar alerta automatica.
A34: CTANJZ04552 | B34: D603244 | C34: STBU | D34: Expired | E34: 45771 | F34: 45845 | G34: 9 | H34: 9 | I34: 73-17567-12, 73-17568-12, 73-17569-10, 73-17570-10 | L34: =IF(F34="","REVIEW: DATE CONFLICT/EMPTY",IF(F34<'Change Overview'!$B$5,"END DATE PASSED","END DATE NOT PASSED")) -> END DATE PASSED | M34: =IF(K34<>"","REVIEW SOURCE CONFLICT",IF(OR(ISNUMBER(SEARCH("CCB",D34)),ISNUMBER(SEARCH("Pending",D34))),"CCB/PENDING",IF(OR(ISNUMBER(SEARCH("Expired",D34)),ISNUMBER(SEARCH("Closed",D34))),"CLOSED/EXPIRED",IF(E34="","NO RELEASE DATE","REVIEW APPROVAL")))) -> CLOSED/EXPIRED | N34: =IF(K34<>"","HIGH: SOURCE CONFLICT",IF(AND(L34="END DATE NOT PASSED",M34="REVIEW APPROVAL"),"HIGH: VERIFY",IF(L34="END DATE NOT PASSED","MEDIUM: CHECK STATUS","LOW: HISTORICAL"))) -> LOW: HISTORICAL | O34: Validar documento firmado, revision/WO/sitio, material afectado y evidencia antes de activar alerta automatica.
A35: CTANJZ04555 | B35: D603224 | C35: SRGBU | D35: Expired | E35: 45772 | F35: 45845 | G35: 4 | H35: 4 | L35: =IF(F35="","REVIEW: DATE CONFLICT/EMPTY",IF(F35<'Change Overview'!$B$5,"END DATE PASSED","END DATE NOT PASSED")) -> END DATE PASSED | M35: =IF(K35<>"","REVIEW SOURCE CONFLICT",IF(OR(ISNUMBER(SEARCH("CCB",D35)),ISNUMBER(SEARCH("Pending",D35))),"CCB/PENDING",IF(OR(ISNUMBER(SEARCH("Expired",D35)),ISNUMBER(SEARCH("Closed",D35))),"CLOSED/EXPIRED",IF(E35="","NO RELEASE DATE","REVIEW APPROVAL")))) -> CLOSED/EXPIRED | N35: =IF(K35<>"","HIGH: SOURCE CONFLICT",IF(AND(L35="END DATE NOT PASSED",M35="REVIEW APPROVAL"),"HIGH: VERIFY",IF(L35="END DATE NOT PASSED","MEDIUM: CHECK STATUS","LOW: HISTORICAL"))) -> LOW: HISTORICAL | O35: Validar documento firmado, revision/WO/sitio, material afectado y evidencia antes de activar alerta automatica.
A36: CTANJZ04556 | B36: D603102 | C36: STBU | D36: Expired | E36: 45771 | F36: 45936 | G36: 6 | H36: 6 | I36: 73-20247-05, 73-20249-05 | L36: =IF(F36="","REVIEW: DATE CONFLICT/EMPTY",IF(F36<'Change Overview'!$B$5,"END DATE PASSED","END DATE NOT PASSED")) -> END DATE PASSED | M36: =IF(K36<>"","REVIEW SOURCE CONFLICT",IF(OR(ISNUMBER(SEARCH("CCB",D36)),ISNUMBER(SEARCH("Pending",D36))),"CCB/PENDING",IF(OR(ISNUMBER(SEARCH("Expired",D36)),ISNUMBER(SEARCH("Closed",D36))),"CLOSED/EXPIRED",IF(E36="","NO RELEASE DATE","REVIEW APPROVAL")))) -> CLOSED/EXPIRED | N36: =IF(K36<>"","HIGH: SOURCE CONFLICT",IF(AND(L36="END DATE NOT PASSED",M36="REVIEW APPROVAL"),"HIGH: VERIFY",IF(L36="END DATE NOT PASSED","MEDIUM: CHECK STATUS","LOW: HISTORICAL"))) -> LOW: HISTORICAL | O36: Validar documento firmado, revision/WO/sitio, material afectado y evidencia antes de activar alerta automatica.
A37: CTANJZ04557 | B37: D603243 | C37: STBU | D37: Expired | E37: 45771 | F37: 45847 | G37: 9 | H37: 9 | I37: 73-18488-07, 73-18489-07, 73-18490-09, 73-21007-02 | L37: =IF(F37="","REVIEW: DATE CONFLICT/EMPTY",IF(F37<'Change Overview'!$B$5,"END DATE PASSED","END DATE NOT PASSED")) -> END DATE PASSED | M37: =IF(K37<>"","REVIEW SOURCE CONFLICT",IF(OR(ISNUMBER(SEARCH("CCB",D37)),ISNUMBER(SEARCH("Pending",D37))),"CCB/PENDING",IF(OR(ISNUMBER(SEARCH("Expired",D37)),ISNUMBER(SEARCH("Closed",D37))),"CLOSED/EXPIRED",IF(E37="","NO RELEASE DATE","REVIEW APPROVAL")))) -> CLOSED/EXPIRED | N37: =IF(K37<>"","HIGH: SOURCE CONFLICT",IF(AND(L37="END DATE NOT PASSED",M37="REVIEW APPROVAL"),"HIGH: VERIFY",IF(L37="END DATE NOT PASSED","MEDIUM: CHECK STATUS","LOW: HISTORICAL"))) -> LOW: HISTORICAL | O37: Validar documento firmado, revision/WO/sitio, material afectado y evidencia antes de activar alerta automatica.
A38: CTANJZ04568 | B38: D603037 | C38: STBU | D38: Expired | E38: 45779 | F38: 45853 | G38: 23 | H38: 23 | L38: =IF(F38="","REVIEW: DATE CONFLICT/EMPTY",IF(F38<'Change Overview'!$B$5,"END DATE PASSED","END DATE NOT PASSED")) -> END DATE PASSED | M38: =IF(K38<>"","REVIEW SOURCE CONFLICT",IF(OR(ISNUMBER(SEARCH("CCB",D38)),ISNUMBER(SEARCH("Pending",D38))),"CCB/PENDING",IF(OR(ISNUMBER(SEARCH("Expired",D38)),ISNUMBER(SEARCH("Closed",D38))),"CLOSED/EXPIRED",IF(E38="","NO RELEASE DATE","REVIEW APPROVAL")))) -> CLOSED/EXPIRED | N38: =IF(K38<>"","HIGH: SOURCE CONFLICT",IF(AND(L38="END DATE NOT PASSED",M38="REVIEW APPROVAL"),"HIGH: VERIFY",IF(L38="END DATE NOT PASSED","MEDIUM: CHECK STATUS","LOW: HISTORICAL"))) -> LOW: HISTORICAL | O38: Validar documento firmado, revision/WO/sitio, material afectado y evidencia antes de activar alerta automatica.
A39: CTANJZ04571 | B39: D603340 | C39: IOTBU | D39: Expired | E39: 45773 | F39: 45855 | G39: 1 | H39: 1 | L39: =IF(F39="","REVIEW: DATE CONFLICT/EMPTY",IF(F39<'Change Overview'!$B$5,"END DATE PASSED","END DATE NOT PASSED")) -> END DATE PASSED | M39: =IF(K39<>"","REVIEW SOURCE CONFLICT",IF(OR(ISNUMBER(SEARCH("CCB",D39)),ISNUMBER(SEARCH("Pending",D39))),"CCB/PENDING",IF(OR(ISNUMBER(SEARCH("Expired",D39)),ISNUMBER(SEARCH("Closed",D39))),"CLOSED/EXPIRED",IF(E39="","NO RELEASE DATE","REVIEW APPROVAL")))) -> CLOSED/EXPIRED | N39: =IF(K39<>"","HIGH: SOURCE CONFLICT",IF(AND(L39="END DATE NOT PASSED",M39="REVIEW APPROVAL"),"HIGH: VERIFY",IF(L39="END DATE NOT PASSED","MEDIUM: CHECK STATUS","LOW: HISTORICAL"))) -> LOW: HISTORICAL | O39: Validar documento firmado, revision/WO/sitio, material afectado y evidencia antes de activar alerta automatica.
A40: CTANJZ04573 | B40: D603428 | C40: SRGBU | D40: Expired | E40: 45779 | F40: 45858 | G40: 1 | H40: 1 | L40: =IF(F40="","REVIEW: DATE CONFLICT/EMPTY",IF(F40<'Change Overview'!$B$5,"END DATE PASSED","END DATE NOT PASSED")) -> END DATE PASSED | M40: =IF(K40<>"","REVIEW SOURCE CONFLICT",IF(OR(ISNUMBER(SEARCH("CCB",D40)),ISNUMBER(SEARCH("Pending",D40))),"CCB/PENDING",IF(OR(ISNUMBER(SEARCH("Expired",D40)),ISNUMBER(SEARCH("Closed",D40))),"CLOSED/EXPIRED",IF(E40="","NO RELEASE DATE","REVIEW APPROVAL")))) -> CLOSED/EXPIRED | N40: =IF(K40<>"","HIGH: SOURCE CONFLICT",IF(AND(L40="END DATE NOT PASSED",M40="REVIEW APPROVAL"),"HIGH: VERIFY",IF(L40="END DATE NOT PASSED","MEDIUM: CHECK STATUS","LOW: HISTORICAL"))) -> LOW: HISTORICAL | O40: Validar documento firmado, revision/WO/sitio, material afectado y evidencia antes de activar alerta automatica.
A41: CTANJZ04575 | B41: D603354 | C41: SRGBU | D41: Expired | E41: 45779 | F41: 45858 | G41: 1 | H41: 1 | L41: =IF(F41="","REVIEW: DATE CONFLICT/EMPTY",IF(F41<'Change Overview'!$B$5,"END DATE PASSED","END DATE NOT PASSED")) -> END DATE PASSED | M41: =IF(K41<>"","REVIEW SOURCE CONFLICT",IF(OR(ISNUMBER(SEARCH("CCB",D41)),ISNUMBER(SEARCH("Pending",D41))),"CCB/PENDING",IF(OR(ISNUMBER(SEARCH("Expired",D41)),ISNUMBER(SEARCH("Closed",D41))),"CLOSED/EXPIRED",IF(E41="","NO RELEASE DATE","REVIEW APPROVAL")))) -> CLOSED/EXPIRED | N41: =IF(K41<>"","HIGH: SOURCE CONFLICT",IF(AND(L41="END DATE NOT PASSED",M41="REVIEW APPROVAL"),"HIGH: VERIFY",IF(L41="END DATE NOT PASSED","MEDIUM: CHECK STATUS","LOW: HISTORICAL"))) -> LOW: HISTORICAL | O41: Validar documento firmado, revision/WO/sitio, material afectado y evidencia antes de activar alerta automatica.
A42: CTANJZ04578 | B42: D603342 | C42: STBU | D42: Expired | E42: 45791 | F42: 45860 | G42: 3 | H42: 3 | I42: 73-102435-05 | L42: =IF(F42="","REVIEW: DATE CONFLICT/EMPTY",IF(F42<'Change Overview'!$B$5,"END DATE PASSED","END DATE NOT PASSED")) -> END DATE PASSED | M42: =IF(K42<>"","REVIEW SOURCE CONFLICT",IF(OR(ISNUMBER(SEARCH("CCB",D42)),ISNUMBER(SEARCH("Pending",D42))),"CCB/PENDING",IF(OR(ISNUMBER(SEARCH("Expired",D42)),ISNUMBER(SEARCH("Closed",D42))),"CLOSED/EXPIRED",IF(E42="","NO RELEASE DATE","REVIEW APPROVAL")))) -> CLOSED/EXPIRED | N42: =IF(K42<>"","HIGH: SOURCE CONFLICT",IF(AND(L42="END DATE NOT PASSED",M42="REVIEW APPROVAL"),"HIGH: VERIFY",IF(L42="END DATE NOT PASSED","MEDIUM: CHECK STATUS","LOW: HISTORICAL"))) -> LOW: HISTORICAL | O42: Validar documento firmado, revision/WO/sitio, material afectado y evidencia antes de activar alerta automatica.
A43: CTANJZ04580 | B43: D603575 | C43: SRGBU | D43: Expired | E43: 45791 | F43: 45865 | G43: 1 | H43: 1 | L43: =IF(F43="","REVIEW: DATE CONFLICT/EMPTY",IF(F43<'Change Overview'!$B$5,"END DATE PASSED","END DATE NOT PASSED")) -> END DATE PASSED | M43: =IF(K43<>"","REVIEW SOURCE CONFLICT",IF(OR(ISNUMBER(SEARCH("CCB",D43)),ISNUMBER(SEARCH("Pending",D43))),"CCB/PENDING",IF(OR(ISNUMBER(SEARCH("Expired",D43)),ISNUMBER(SEARCH("Closed",D43))),"CLOSED/EXPIRED",IF(E43="","NO RELEASE DATE","REVIEW APPROVAL")))) -> CLOSED/EXPIRED | N43: =IF(K43<>"","HIGH: SOURCE CONFLICT",IF(AND(L43="END DATE NOT PASSED",M43="REVIEW APPROVAL"),"HIGH: VERIFY",IF(L43="END DATE NOT PASSED","MEDIUM: CHECK STATUS","LOW: HISTORICAL"))) -> LOW: HISTORICAL | O43: Validar documento firmado, revision/WO/sitio, material afectado y evidencia antes de activar alerta automatica.
A44: CTANJZ04583 | B44: D602497 | C44: STBU | D44: Expired | E44: 45796 | F44: 45866 | G44: 3 | H44: 3 | I44: 73-19337-01 | L44: =IF(F44="","REVIEW: DATE CONFLICT/EMPTY",IF(F44<'Change Overview'!$B$5,"END DATE PASSED","END DATE NOT PASSED")) -> END DATE PASSED | M44: =IF(K44<>"","REVIEW SOURCE CONFLICT",IF(OR(ISNUMBER(SEARCH("CCB",D44)),ISNUMBER(SEARCH("Pending",D44))),"CCB/PENDING",IF(OR(ISNUMBER(SEARCH("Expired",D44)),ISNUMBER(SEARCH("Closed",D44))),"CLOSED/EXPIRED",IF(E44="","NO RELEASE DATE","REVIEW APPROVAL")))) -> CLOSED/EXPIRED | N44: =IF(K44<>"","HIGH: SOURCE CONFLICT",IF(AND(L44="END DATE NOT PASSED",M44="REVIEW APPROVAL"),"HIGH: VERIFY",IF(L44="END DATE NOT PASSED","MEDIUM: CHECK STATUS","LOW: HISTORICAL"))) -> LOW: HISTORICAL | O44: Validar documento firmado, revision/WO/sitio, material afectado y evidencia antes de activar alerta automatica.
A45: CTANJZ04587 | B45: D603571 | C45: SRGBU | D45: Expired | E45: 45796 | F45: 45866 | G45: 2 | H45: 2 | L45: =IF(F45="","REVIEW: DATE CONFLICT/EMPTY",IF(F45<'Change Overview'!$B$5,"END DATE PASSED","END DATE NOT PASSED")) -> END DATE PASSED | M45: =IF(K45<>"","REVIEW SOURCE CONFLICT",IF(OR(ISNUMBER(SEARCH("CCB",D45)),ISNUMBER(SEARCH("Pending",D45))),"CCB/PENDING",IF(OR(ISNUMBER(SEARCH("Expired",D45)),ISNUMBER(SEARCH("Closed",D45))),"CLOSED/EXPIRED",IF(E45="","NO RELEASE DATE","REVIEW APPROVAL")))) -> CLOSED/EXPIRED | N45: =IF(K45<>"","HIGH: SOURCE CONFLICT",IF(AND(L45="END DATE NOT PASSED",M45="REVIEW APPROVAL"),"HIGH: VERIFY",IF(L45="END DATE NOT PASSED","MEDIUM: CHECK STATUS","LOW: HISTORICAL"))) -> LOW: HISTORICAL | O45: Validar documento firmado, revision/WO/sitio, material afectado y evidencia antes de activar alerta automatica.
A46: CTANJZ04588 | B46: D603105 | C46: SRGBU | D46: Expired | E46: 45796 | F46: 45868 | G46: 10 | H46: 10 | L46: =IF(F46="","REVIEW: DATE CONFLICT/EMPTY",IF(F46<'Change Overview'!$B$5,"END DATE PASSED","END DATE NOT PASSED")) -> END DATE PASSED | M46: =IF(K46<>"","REVIEW SOURCE CONFLICT",IF(OR(ISNUMBER(SEARCH("CCB",D46)),ISNUMBER(SEARCH("Pending",D46))),"CCB/PENDING",IF(OR(ISNUMBER(SEARCH("Expired",D46)),ISNUMBER(SEARCH("Closed",D46))),"CLOSED/EXPIRED",IF(E46="","NO RELEASE DATE","REVIEW APPROVAL")))) -> CLOSED/EXPIRED | N46: =IF(K46<>"","HIGH: SOURCE CONFLICT",IF(AND(L46="END DATE NOT PASSED",M46="REVIEW APPROVAL"),"HIGH: VERIFY",IF(L46="END DATE NOT PASSED","MEDIUM: CHECK STATUS","LOW: HISTORICAL"))) -> LOW: HISTORICAL | O46: Validar documento firmado, revision/WO/sitio, material afectado y evidencia antes de activar alerta automatica.
A47: CTANJZ04594 | B47: D603779 | C47: SRGBU | D47: Expired | E47: 45798 | F47: 45873 | G47: 2 | H47: 2 | L47: =IF(F47="","REVIEW: DATE CONFLICT/EMPTY",IF(F47<'Change Overview'!$B$5,"END DATE PASSED","END DATE NOT PASSED")) -> END DATE PASSED | M47: =IF(K47<>"","REVIEW SOURCE CONFLICT",IF(OR(ISNUMBER(SEARCH("CCB",D47)),ISNUMBER(SEARCH("Pending",D47))),"CCB/PENDING",IF(OR(ISNUMBER(SEARCH("Expired",D47)),ISNUMBER(SEARCH("Closed",D47))),"CLOSED/EXPIRED",IF(E47="","NO RELEASE DATE","REVIEW APPROVAL")))) -> CLOSED/EXPIRED | N47: =IF(K47<>"","HIGH: SOURCE CONFLICT",IF(AND(L47="END DATE NOT PASSED",M47="REVIEW APPROVAL"),"HIGH: VERIFY",IF(L47="END DATE NOT PASSED","MEDIUM: CHECK STATUS","LOW: HISTORICAL"))) -> LOW: HISTORICAL | O47: Validar documento firmado, revision/WO/sitio, material afectado y evidencia antes de activar alerta automatica.
A48: CTANJZ04600 | B48: D603808 | C48: SRGBU | D48: Expired | E48: 45798 | F48: 45875 | G48: 1 | H48: 1 | L48: =IF(F48="","REVIEW: DATE CONFLICT/EMPTY",IF(F48<'Change Overview'!$B$5,"END DATE PASSED","END DATE NOT PASSED")) -> END DATE PASSED | M48: =IF(K48<>"","REVIEW SOURCE CONFLICT",IF(OR(ISNUMBER(SEARCH("CCB",D48)),ISNUMBER(SEARCH("Pending",D48))),"CCB/PENDING",IF(OR(ISNUMBER(SEARCH("Expired",D48)),ISNUMBER(SEARCH("Closed",D48))),"CLOSED/EXPIRED",IF(E48="","NO RELEASE DATE","REVIEW APPROVAL")))) -> CLOSED/EXPIRED | N48: =IF(K48<>"","HIGH: SOURCE CONFLICT",IF(AND(L48="END DATE NOT PASSED",M48="REVIEW APPROVAL"),"HIGH: VERIFY",IF(L48="END DATE NOT PASSED","MEDIUM: CHECK STATUS","LOW: HISTORICAL"))) -> LOW: HISTORICAL | O48: Validar documento firmado, revision/WO/sitio, material afectado y evidencia antes de activar alerta automatica.
A49: CTANJZ04604 | B49: D603402 | C49: STBU | D49: Expired | E49: 45805 | F49: 46058 | G49: 8 | H49: 8 | I49: 73-102433-04, 73-102434-04, 73-102435-04 | L49: =IF(F49="","REVIEW: DATE CONFLICT/EMPTY",IF(F49<'Change Overview'!$B$5,"END DATE PASSED","END DATE NOT PASSED")) -> END DATE PASSED | M49: =IF(K49<>"","REVIEW SOURCE CONFLICT",IF(OR(ISNUMBER(SEARCH("CCB",D49)),ISNUMBER(SEARCH("Pending",D49))),"CCB/PENDING",IF(OR(ISNUMBER(SEARCH("Expired",D49)),ISNUMBER(SEARCH("Closed",D49))),"CLOSED/EXPIRED",IF(E49="","NO RELEASE DATE","REVIEW APPROVAL")))) -> CLOSED/EXPIRED | N49: =IF(K49<>"","HIGH: SOURCE CONFLICT",IF(AND(L49="END DATE NOT PASSED",M49="REVIEW APPROVAL"),"HIGH: VERIFY",IF(L49="END DATE NOT PASSED","MEDIUM: CHECK STATUS","LOW: HISTORICAL"))) -> LOW: HISTORICAL | O49: Validar documento firmado, revision/WO/sitio, material afectado y evidencia antes de activar alerta automatica.
A50: CTANJZ04607 | B50: D603592 | C50: STBU | D50: Expired | E50: 45807 | F50: 45881 | G50: 6 | H50: 6 | L50: =IF(F50="","REVIEW: DATE CONFLICT/EMPTY",IF(F50<'Change Overview'!$B$5,"END DATE PASSED","END DATE NOT PASSED")) -> END DATE PASSED | M50: =IF(K50<>"","REVIEW SOURCE CONFLICT",IF(OR(ISNUMBER(SEARCH("CCB",D50)),ISNUMBER(SEARCH("Pending",D50))),"CCB/PENDING",IF(OR(ISNUMBER(SEARCH("Expired",D50)),ISNUMBER(SEARCH("Closed",D50))),"CLOSED/EXPIRED",IF(E50="","NO RELEASE DATE","REVIEW APPROVAL")))) -> CLOSED/EXPIRED | N50: =IF(K50<>"","HIGH: SOURCE CONFLICT",IF(AND(L50="END DATE NOT PASSED",M50="REVIEW APPROVAL"),"HIGH: VERIFY",IF(L50="END DATE NOT PASSED","MEDIUM: CHECK STATUS","LOW: HISTORICAL"))) -> LOW: HISTORICAL | O50: Validar documento firmado, revision/WO/sitio, material afectado y evidencia antes de activar alerta automatica.
A51: CTANJZ04609 | B51: DP524872 | C51: CVEBU | D51: Expired | E51: 45805 | F51: 45852 | G51: 4 | H51: 4 | I51: 73-103720-03, 73-103820-03, 73-103920-03, 73-103922-03 | L51: =IF(F51="","REVIEW: DATE CONFLICT/EMPTY",IF(F51<'Change Overview'!$B$5,"END DATE PASSED","END DATE NOT PASSED")) -> END DATE PASSED | M51: =IF(K51<>"","REVIEW SOURCE CONFLICT",IF(OR(ISNUMBER(SEARCH("CCB",D51)),ISNUMBER(SEARCH("Pending",D51))),"CCB/PENDING",IF(OR(ISNUMBER(SEARCH("Expired",D51)),ISNUMBER(SEARCH("Closed",D51))),"CLOSED/EXPIRED",IF(E51="","NO RELEASE DATE","REVIEW APPROVAL")))) -> CLOSED/EXPIRED | N51: =IF(K51<>"","HIGH: SOURCE CONFLICT",IF(AND(L51="END DATE NOT PASSED",M51="REVIEW APPROVAL"),"HIGH: VERIFY",IF(L51="END DATE NOT PASSED","MEDIUM: CHECK STATUS","LOW: HISTORICAL"))) -> LOW: HISTORICAL | O51: Validar documento firmado, revision/WO/sitio, material afectado y evidencia antes de activar alerta automatica.
A52: CTANJZ04612 | B52: D603710 | C52: SRGBU | D52: Expired | E52: 45811 | F52: 45886 | G52: 3 | H52: 3 | L52: =IF(F52="","REVIEW: DATE CONFLICT/EMPTY",IF(F52<'Change Overview'!$B$5,"END DATE PASSED","END DATE NOT PASSED")) -> END DATE PASSED | M52: =IF(K52<>"","REVIEW SOURCE CONFLICT",IF(OR(ISNUMBER(SEARCH("CCB",D52)),ISNUMBER(SEARCH("Pending",D52))),"CCB/PENDING",IF(OR(ISNUMBER(SEARCH("Expired",D52)),ISNUMBER(SEARCH("Closed",D52))),"CLOSED/EXPIRED",IF(E52="","NO RELEASE DATE","REVIEW APPROVAL")))) -> CLOSED/EXPIRED | N52: =IF(K52<>"","HIGH: SOURCE CONFLICT",IF(AND(L52="END DATE NOT PASSED",M52="REVIEW APPROVAL"),"HIGH: VERIFY",IF(L52="END DATE NOT PASSED","MEDIUM: CHECK STATUS","LOW: HISTORICAL"))) -> LOW: HISTORICAL | O52: Validar documento firmado, revision/WO/sitio, material afectado y evidencia antes de activar alerta automatica.
A53: CTANJZ04613 | B53: D603986 | C53: CVEBU | D53: Expired | E53: 45811 | F53: 45886 | G53: 10 | H53: 10 | I53: 73-101504-01, 73-102022-02, 73-102197-02, 73-102226-06, 73-102797-02, 73-103103-04, 73-103226-06, 73-103603-04, 73-104022-01 | J53: BROOKLYN, DAVINCI, MILLENIUM | L53: =IF(F53="","REVIEW: DATE CONFLICT/EMPTY",IF(F53<'Change Overview'!$B$5,"END DATE PASSED","END DATE NOT PASSED")) -> END DATE PASSED | M53: =IF(K53<>"","REVIEW SOURCE CONFLICT",IF(OR(ISNUMBER(SEARCH("CCB",D53)),ISNUMBER(SEARCH("Pending",D53))),"CCB/PENDING",IF(OR(ISNUMBER(SEARCH("Expired",D53)),ISNUMBER(SEARCH("Closed",D53))),"CLOSED/EXPIRED",IF(E53="","NO RELEASE DATE","REVIEW APPROVAL")))) -> CLOSED/EXPIRED | N53: =IF(K53<>"","HIGH: SOURCE CONFLICT",IF(AND(L53="END DATE NOT PASSED",M53="REVIEW APPROVAL"),"HIGH: VERIFY",IF(L53="END DATE NOT PASSED","MEDIUM: CHECK STATUS","LOW: HISTORICAL"))) -> LOW: HISTORICAL | O53: Validar documento firmado, revision/WO/sitio, material afectado y evidencia antes de activar alerta automatica.
A54: CTANJZ04616 | B54: D603828 | C54: STBU | D54: Expired | E54: 45819 | F54: 45889 | G54: 2 | H54: 2 | I54: 73-21007-02 | L54: =IF(F54="","REVIEW: DATE CONFLICT/EMPTY",IF(F54<'Change Overview'!$B$5,"END DATE PASSED","END DATE NOT PASSED")) -> END DATE PASSED | M54: =IF(K54<>"","REVIEW SOURCE CONFLICT",IF(OR(ISNUMBER(SEARCH("CCB",D54)),ISNUMBER(SEARCH("Pending",D54))),"CCB/PENDING",IF(OR(ISNUMBER(SEARCH("Expired",D54)),ISNUMBER(SEARCH("Closed",D54))),"CLOSED/EXPIRED",IF(E54="","NO RELEASE DATE","REVIEW APPROVAL")))) -> CLOSED/EXPIRED | N54: =IF(K54<>"","HIGH: SOURCE CONFLICT",IF(AND(L54="END DATE NOT PASSED",M54="REVIEW APPROVAL"),"HIGH: VERIFY",IF(L54="END DATE NOT PASSED","MEDIUM: CHECK STATUS","LOW: HISTORICAL"))) -> LOW: HISTORICAL | O54: Validar documento firmado, revision/WO/sitio, material afectado y evidencia antes de activar alerta automatica.
A55: CTANJZ04617 | B55: D604044 | C55: CVEBU | D55: Expired | E55: 45826 | F55: 45889 | G55: 2 | H55: 2 | L55: =IF(F55="","REVIEW: DATE CONFLICT/EMPTY",IF(F55<'Change Overview'!$B$5,"END DATE PASSED","END DATE NOT PASSED")) -> END DATE PASSED | M55: =IF(K55<>"","REVIEW SOURCE CONFLICT",IF(OR(ISNUMBER(SEARCH("CCB",D55)),ISNUMBER(SEARCH("Pending",D55))),"CCB/PENDING",IF(OR(ISNUMBER(SEARCH("Expired",D55)),ISNUMBER(SEARCH("Closed",D55))),"CLOSED/EXPIRED",IF(E55="","NO RELEASE DATE","REVIEW APPROVAL")))) -> CLOSED/EXPIRED | N55: =IF(K55<>"","HIGH: SOURCE CONFLICT",IF(AND(L55="END DATE NOT PASSED",M55="REVIEW APPROVAL"),"HIGH: VERIFY",IF(L55="END DATE NOT PASSED","MEDIUM: CHECK STATUS","LOW: HISTORICAL"))) -> LOW: HISTORICAL | O55: Validar documento firmado, revision/WO/sitio, material afectado y evidencia antes de activar alerta automatica.
A56: CTANJZ04618 | B56: D603586 | C56: STBU | D56: Expired | E56: 45819 | F56: 45889 | G56: 3 | H56: 3 | I56: 73-20247-06 | J56: TUFNELL PARK | L56: =IF(F56="","REVIEW: DATE CONFLICT/EMPTY",IF(F56<'Change Overview'!$B$5,"END DATE PASSED","END DATE NOT PASSED")) -> END DATE PASSED | M56: =IF(K56<>"","REVIEW SOURCE CONFLICT",IF(OR(ISNUMBER(SEARCH("CCB",D56)),ISNUMBER(SEARCH("Pending",D56))),"CCB/PENDING",IF(OR(ISNUMBER(SEARCH("Expired",D56)),ISNUMBER(SEARCH("Closed",D56))),"CLOSED/EXPIRED",IF(E56="","NO RELEASE DATE","REVIEW APPROVAL")))) -> CLOSED/EXPIRED | N56: =IF(K56<>"","HIGH: SOURCE CONFLICT",IF(AND(L56="END DATE NOT PASSED",M56="REVIEW APPROVAL"),"HIGH: VERIFY",IF(L56="END DATE NOT PASSED","MEDIUM: CHECK STATUS","LOW: HISTORICAL"))) -> LOW: HISTORICAL | O56: Validar documento firmado, revision/WO/sitio, material afectado y evidencia antes de activar alerta automatica.
A57: CTANJZ04623 | B57: D604124 | C57: CVEBU | D57: Expired | E57: 45826 | F57: 45890 | G57: 1 | H57: 1 | L57: =IF(F57="","REVIEW: DATE CONFLICT/EMPTY",IF(F57<'Change Overview'!$B$5,"END DATE PASSED","END DATE NOT PASSED")) -> END DATE PASSED | M57: =IF(K57<>"","REVIEW SOURCE CONFLICT",IF(OR(ISNUMBER(SEARCH("CCB",D57)),ISNUMBER(SEARCH("Pending",D57))),"CCB/PENDING",IF(OR(ISNUMBER(SEARCH("Expired",D57)),ISNUMBER(SEARCH("Closed",D57))),"CLOSED/EXPIRED",IF(E57="","NO RELEASE DATE","REVIEW APPROVAL")))) -> CLOSED/EXPIRED | N57: =IF(K57<>"","HIGH: SOURCE CONFLICT",IF(AND(L57="END DATE NOT PASSED",M57="REVIEW APPROVAL"),"HIGH: VERIFY",IF(L57="END DATE NOT PASSED","MEDIUM: CHECK STATUS","LOW: HISTORICAL"))) -> LOW: HISTORICAL | O57: Validar documento firmado, revision/WO/sitio, material afectado y evidencia antes de activar alerta automatica.
A58: CTANJZ04631 | B58: D604068 | C58: STBU | D58: Expired | E58: 45826 | F58: 45895 | G58: 9 | H58: 9 | I58: 73-102433-04, 73-102433-05, 73-102434-04, 73-102434-05, 73-102435-04, 73-102435-05 | L58: =IF(F58="","REVIEW: DATE CONFLICT/EMPTY",IF(F58<'Change Overview'!$B$5,"END DATE PASSED","END DATE NOT PASSED")) -> END DATE PASSED | M58: =IF(K58<>"","REVIEW SOURCE CONFLICT",IF(OR(ISNUMBER(SEARCH("CCB",D58)),ISNUMBER(SEARCH("Pending",D58))),"CCB/PENDING",IF(OR(ISNUMBER(SEARCH("Expired",D58)),ISNUMBER(SEARCH("Closed",D58))),"CLOSED/EXPIRED",IF(E58="","NO RELEASE DATE","REVIEW APPROVAL")))) -> CLOSED/EXPIRED | N58: =IF(K58<>"","HIGH: SOURCE CONFLICT",IF(AND(L58="END DATE NOT PASSED",M58="REVIEW APPROVAL"),"HIGH: VERIFY",IF(L58="END DATE NOT PASSED","MEDIUM: CHECK STATUS","LOW: HISTORICAL"))) -> LOW: HISTORICAL | O58: Validar documento firmado, revision/WO/sitio, material afectado y evidencia antes de activar alerta automatica.
A59: CTANJZ04632 | B59: DP524922 | C59: STBU | D59: Expired | E59: 45819 | F59: 45866 | G59: 3 | H59: 3 | I59: 73-103558-04, 73-103633-04, 73-103648-04 | L59: =IF(F59="","REVIEW: DATE CONFLICT/EMPTY",IF(F59<'Change Overview'!$B$5,"END DATE PASSED","END DATE NOT PASSED")) -> END DATE PASSED | M59: =IF(K59<>"","REVIEW SOURCE CONFLICT",IF(OR(ISNUMBER(SEARCH("CCB",D59)),ISNUMBER(SEARCH("Pending",D59))),"CCB/PENDING",IF(OR(ISNUMBER(SEARCH("Expired",D59)),ISNUMBER(SEARCH("Closed",D59))),"CLOSED/EXPIRED",IF(E59="","NO RELEASE DATE","REVIEW APPROVAL")))) -> CLOSED/EXPIRED | N59: =IF(K59<>"","HIGH: SOURCE CONFLICT",IF(AND(L59="END DATE NOT PASSED",M59="REVIEW APPROVAL"),"HIGH: VERIFY",IF(L59="END DATE NOT PASSED","MEDIUM: CHECK STATUS","LOW: HISTORICAL"))) -> LOW: HISTORICAL | O59: Validar documento firmado, revision/WO/sitio, material afectado y evidencia antes de activar alerta automatica.
A60: CTANJZ04634 | B60: D604208 | C60: STBU | D60: Expired | E60: 45826 | F60: 45896 | G60: 2 | H60: 2 | L60: =IF(F60="","REVIEW: DATE CONFLICT/EMPTY",IF(F60<'Change Overview'!$B$5,"END DATE PASSED","END DATE NOT PASSED")) -> END DATE PASSED | M60: =IF(K60<>"","REVIEW SOURCE CONFLICT",IF(OR(ISNUMBER(SEARCH("CCB",D60)),ISNUMBER(SEARCH("Pending",D60))),"CCB/PENDING",IF(OR(ISNUMBER(SEARCH("Expired",D60)),ISNUMBER(SEARCH("Closed",D60))),"CLOSED/EXPIRED",IF(E60="","NO RELEASE DATE","REVIEW APPROVAL")))) -> CLOSED/EXPIRED | N60: =IF(K60<>"","HIGH: SOURCE CONFLICT",IF(AND(L60="END DATE NOT PASSED",M60="REVIEW APPROVAL"),"HIGH: VERIFY",IF(L60="END DATE NOT PASSED","MEDIUM: CHECK STATUS","LOW: HISTORICAL"))) -> LOW: HISTORICAL | O60: Validar documento firmado, revision/WO/sitio, material afectado y evidencia antes de activar alerta automatica.
A61: CTANJZ04635 | B61: D604078 | C61: STBU | D61: Expired | E61: 45827 | F61: 45896 | G61: 1 | H61: 1 | L61: =IF(F61="","REVIEW: DATE CONFLICT/EMPTY",IF(F61<'Change Overview'!$B$5,"END DATE PASSED","END DATE NOT PASSED")) -> END DATE PASSED | M61: =IF(K61<>"","REVIEW SOURCE CONFLICT",IF(OR(ISNUMBER(SEARCH("CCB",D61)),ISNUMBER(SEARCH("Pending",D61))),"CCB/PENDING",IF(OR(ISNUMBER(SEARCH("Expired",D61)),ISNUMBER(SEARCH("Closed",D61))),"CLOSED/EXPIRED",IF(E61="","NO RELEASE DATE","REVIEW APPROVAL")))) -> CLOSED/EXPIRED | N61: =IF(K61<>"","HIGH: SOURCE CONFLICT",IF(AND(L61="END DATE NOT PASSED",M61="REVIEW APPROVAL"),"HIGH: VERIFY",IF(L61="END DATE NOT PASSED","MEDIUM: CHECK STATUS","LOW: HISTORICAL"))) -> LOW: HISTORICAL | O61: Validar documento firmado, revision/WO/sitio, material afectado y evidencia antes de activar alerta automatica.
A62: CTANJZ04640 | B62: DP524361 | C62: STBU | D62: Expired | E62: 45834 | F62: 45871 | G62: 5 | H62: 5 | I62: 73-103633-02 | L62: =IF(F62="","REVIEW: DATE CONFLICT/EMPTY",IF(F62<'Change Overview'!$B$5,"END DATE PASSED","END DATE NOT PASSED")) -> END DATE PASSED | M62: =IF(K62<>"","REVIEW SOURCE CONFLICT",IF(OR(ISNUMBER(SEARCH("CCB",D62)),ISNUMBER(SEARCH("Pending",D62))),"CCB/PENDING",IF(OR(ISNUMBER(SEARCH("Expired",D62)),ISNUMBER(SEARCH("Closed",D62))),"CLOSED/EXPIRED",IF(E62="","NO RELEASE DATE","REVIEW APPROVAL")))) -> CLOSED/EXPIRED | N62: =IF(K62<>"","HIGH: SOURCE CONFLICT",IF(AND(L62="END DATE NOT PASSED",M62="REVIEW APPROVAL"),"HIGH: VERIFY",IF(L62="END DATE NOT PASSED","MEDIUM: CHECK STATUS","LOW: HISTORICAL"))) -> LOW: HISTORICAL | O62: Validar documento firmado, revision/WO/sitio, material afectado y evidencia antes de activar alerta automatica.
A63: CTANJZ04641 | B63: D604196 | C63: CVEBU | D63: Expired | E63: 45826 | F63: 45901 | G63: 2 | H63: 2 | L63: =IF(F63="","REVIEW: DATE CONFLICT/EMPTY",IF(F63<'Change Overview'!$B$5,"END DATE PASSED","END DATE NOT PASSED")) -> END DATE PASSED | M63: =IF(K63<>"","REVIEW SOURCE CONFLICT",IF(OR(ISNUMBER(SEARCH("CCB",D63)),ISNUMBER(SEARCH("Pending",D63))),"CCB/PENDING",IF(OR(ISNUMBER(SEARCH("Expired",D63)),ISNUMBER(SEARCH("Closed",D63))),"CLOSED/EXPIRED",IF(E63="","NO RELEASE DATE","REVIEW APPROVAL")))) -> CLOSED/EXPIRED | N63: =IF(K63<>"","HIGH: SOURCE CONFLICT",IF(AND(L63="END DATE NOT PASSED",M63="REVIEW APPROVAL"),"HIGH: VERIFY",IF(L63="END DATE NOT PASSED","MEDIUM: CHECK STATUS","LOW: HISTORICAL"))) -> LOW: HISTORICAL | O63: Validar documento firmado, revision/WO/sitio, material afectado y evidencia antes de activar alerta automatica.
A64: CTANJZ04645 | B64: DP524944 | C64: STBU | D64: Expired | E64: 45834 | F64: 45872 | G64: 8 | H64: 8 | L64: =IF(F64="","REVIEW: DATE CONFLICT/EMPTY",IF(F64<'Change Overview'!$B$5,"END DATE PASSED","END DATE NOT PASSED")) -> END DATE PASSED | M64: =IF(K64<>"","REVIEW SOURCE CONFLICT",IF(OR(ISNUMBER(SEARCH("CCB",D64)),ISNUMBER(SEARCH("Pending",D64))),"CCB/PENDING",IF(OR(ISNUMBER(SEARCH("Expired",D64)),ISNUMBER(SEARCH("Closed",D64))),"CLOSED/EXPIRED",IF(E64="","NO RELEASE DATE","REVIEW APPROVAL")))) -> CLOSED/EXPIRED | N64: =IF(K64<>"","HIGH: SOURCE CONFLICT",IF(AND(L64="END DATE NOT PASSED",M64="REVIEW APPROVAL"),"HIGH: VERIFY",IF(L64="END DATE NOT PASSED","MEDIUM: CHECK STATUS","LOW: HISTORICAL"))) -> LOW: HISTORICAL | O64: Validar documento firmado, revision/WO/sitio, material afectado y evidencia antes de activar alerta automatica.
A65: CTANJZ04646 | B65: D604197 | C65: STBU | D65: Expired | E65: 45839 | F65: 45902 | G65: 4 | H65: 4 | I65: 73-17499-07 | L65: =IF(F65="","REVIEW: DATE CONFLICT/EMPTY",IF(F65<'Change Overview'!$B$5,"END DATE PASSED","END DATE NOT PASSED")) -> END DATE PASSED | M65: =IF(K65<>"","REVIEW SOURCE CONFLICT",IF(OR(ISNUMBER(SEARCH("CCB",D65)),ISNUMBER(SEARCH("Pending",D65))),"CCB/PENDING",IF(OR(ISNUMBER(SEARCH("Expired",D65)),ISNUMBER(SEARCH("Closed",D65))),"CLOSED/EXPIRED",IF(E65="","NO RELEASE DATE","REVIEW APPROVAL")))) -> CLOSED/EXPIRED | N65: =IF(K65<>"","HIGH: SOURCE CONFLICT",IF(AND(L65="END DATE NOT PASSED",M65="REVIEW APPROVAL"),"HIGH: VERIFY",IF(L65="END DATE NOT PASSED","MEDIUM: CHECK STATUS","LOW: HISTORICAL"))) -> LOW: HISTORICAL | O65: Validar documento firmado, revision/WO/sitio, material afectado y evidencia antes de activar alerta automatica.
A66: CTANJZ04647 | B66: D604285 | C66: STBU | D66: Expired | E66: 45853 | F66: 45902 | G66: 2 | H66: 2 | L66: =IF(F66="","REVIEW: DATE CONFLICT/EMPTY",IF(F66<'Change Overview'!$B$5,"END DATE PASSED","END DATE NOT PASSED")) -> END DATE PASSED | M66: =IF(K66<>"","REVIEW SOURCE CONFLICT",IF(OR(ISNUMBER(SEARCH("CCB",D66)),ISNUMBER(SEARCH("Pending",D66))),"CCB/PENDING",IF(OR(ISNUMBER(SEARCH("Expired",D66)),ISNUMBER(SEARCH("Closed",D66))),"CLOSED/EXPIRED",IF(E66="","NO RELEASE DATE","REVIEW APPROVAL")))) -> CLOSED/EXPIRED | N66: =IF(K66<>"","HIGH: SOURCE CONFLICT",IF(AND(L66="END DATE NOT PASSED",M66="REVIEW APPROVAL"),"HIGH: VERIFY",IF(L66="END DATE NOT PASSED","MEDIUM: CHECK STATUS","LOW: HISTORICAL"))) -> LOW: HISTORICAL | O66: Validar documento firmado, revision/WO/sitio, material afectado y evidencia antes de activar alerta automatica.
A67: CTANJZ04648 | B67: D604046 | C67: STBU | D67: Expired | E67: 45834 | F67: 45902 | G67: 4 | H67: 4 | I67: 73-17497-04 | L67: =IF(F67="","REVIEW: DATE CONFLICT/EMPTY",IF(F67<'Change Overview'!$B$5,"END DATE PASSED","END DATE NOT PASSED")) -> END DATE PASSED | M67: =IF(K67<>"","REVIEW SOURCE CONFLICT",IF(OR(ISNUMBER(SEARCH("CCB",D67)),ISNUMBER(SEARCH("Pending",D67))),"CCB/PENDING",IF(OR(ISNUMBER(SEARCH("Expired",D67)),ISNUMBER(SEARCH("Closed",D67))),"CLOSED/EXPIRED",IF(E67="","NO RELEASE DATE","REVIEW APPROVAL")))) -> CLOSED/EXPIRED | N67: =IF(K67<>"","HIGH: SOURCE CONFLICT",IF(AND(L67="END DATE NOT PASSED",M67="REVIEW APPROVAL"),"HIGH: VERIFY",IF(L67="END DATE NOT PASSED","MEDIUM: CHECK STATUS","LOW: HISTORICAL"))) -> LOW: HISTORICAL | O67: Validar documento firmado, revision/WO/sitio, material afectado y evidencia antes de activar alerta automatica.
A68: CTANJZ04649 | B68: D604092 | C68: STBU | D68: Expired | E68: 45834 | F68: 45902 | G68: 4 | H68: 4 | I68: 73-17498-04 | L68: =IF(F68="","REVIEW: DATE CONFLICT/EMPTY",IF(F68<'Change Overview'!$B$5,"END DATE PASSED","END DATE NOT PASSED")) -> END DATE PASSED | M68: =IF(K68<>"","REVIEW SOURCE CONFLICT",IF(OR(ISNUMBER(SEARCH("CCB",D68)),ISNUMBER(SEARCH("Pending",D68))),"CCB/PENDING",IF(OR(ISNUMBER(SEARCH("Expired",D68)),ISNUMBER(SEARCH("Closed",D68))),"CLOSED/EXPIRED",IF(E68="","NO RELEASE DATE","REVIEW APPROVAL")))) -> CLOSED/EXPIRED | N68: =IF(K68<>"","HIGH: SOURCE CONFLICT",IF(AND(L68="END DATE NOT PASSED",M68="REVIEW APPROVAL"),"HIGH: VERIFY",IF(L68="END DATE NOT PASSED","MEDIUM: CHECK STATUS","LOW: HISTORICAL"))) -> LOW: HISTORICAL | O68: Validar documento firmado, revision/WO/sitio, material afectado y evidencia antes de activar alerta automatica.
A69: CTANJZ04650 | B69: D604195 | C69: STBU | D69: Expired | E69: 45839 | F69: 45902 | G69: 4 | H69: 4 | I69: 73-17499-07 | L69: =IF(F69="","REVIEW: DATE CONFLICT/EMPTY",IF(F69<'Change Overview'!$B$5,"END DATE PASSED","END DATE NOT PASSED")) -> END DATE PASSED | M69: =IF(K69<>"","REVIEW SOURCE CONFLICT",IF(OR(ISNUMBER(SEARCH("CCB",D69)),ISNUMBER(SEARCH("Pending",D69))),"CCB/PENDING",IF(OR(ISNUMBER(SEARCH("Expired",D69)),ISNUMBER(SEARCH("Closed",D69))),"CLOSED/EXPIRED",IF(E69="","NO RELEASE DATE","REVIEW APPROVAL")))) -> CLOSED/EXPIRED | N69: =IF(K69<>"","HIGH: SOURCE CONFLICT",IF(AND(L69="END DATE NOT PASSED",M69="REVIEW APPROVAL"),"HIGH: VERIFY",IF(L69="END DATE NOT PASSED","MEDIUM: CHECK STATUS","LOW: HISTORICAL"))) -> LOW: HISTORICAL | O69: Validar documento firmado, revision/WO/sitio, material afectado y evidencia antes de activar alerta automatica.
A70: CTANJZ04651 | B70: DP524724 | C70: STBU | D70: Expired | E70: 45834 | F70: 45873 | G70: 8 | H70: 8 | I70: 73-103557-03, 73-103633-03 | L70: =IF(F70="","REVIEW: DATE CONFLICT/EMPTY",IF(F70<'Change Overview'!$B$5,"END DATE PASSED","END DATE NOT PASSED")) -> END DATE PASSED | M70: =IF(K70<>"","REVIEW SOURCE CONFLICT",IF(OR(ISNUMBER(SEARCH("CCB",D70)),ISNUMBER(SEARCH("Pending",D70))),"CCB/PENDING",IF(OR(ISNUMBER(SEARCH("Expired",D70)),ISNUMBER(SEARCH("Closed",D70))),"CLOSED/EXPIRED",IF(E70="","NO RELEASE DATE","REVIEW APPROVAL")))) -> CLOSED/EXPIRED | N70: =IF(K70<>"","HIGH: SOURCE CONFLICT",IF(AND(L70="END DATE NOT PASSED",M70="REVIEW APPROVAL"),"HIGH: VERIFY",IF(L70="END DATE NOT PASSED","MEDIUM: CHECK STATUS","LOW: HISTORICAL"))) -> LOW: HISTORICAL | O70: Validar documento firmado, revision/WO/sitio, material afectado y evidencia antes de activar alerta automatica.
A71: CTANJZ04652 | B71: DP524450 | C71: STBU | D71: Expired | E71: 45834 | F71: 45873 | G71: 4 | H71: 4 | L71: =IF(F71="","REVIEW: DATE CONFLICT/EMPTY",IF(F71<'Change Overview'!$B$5,"END DATE PASSED","END DATE NOT PASSED")) -> END DATE PASSED | M71: =IF(K71<>"","REVIEW SOURCE CONFLICT",IF(OR(ISNUMBER(SEARCH("CCB",D71)),ISNUMBER(SEARCH("Pending",D71))),"CCB/PENDING",IF(OR(ISNUMBER(SEARCH("Expired",D71)),ISNUMBER(SEARCH("Closed",D71))),"CLOSED/EXPIRED",IF(E71="","NO RELEASE DATE","REVIEW APPROVAL")))) -> CLOSED/EXPIRED | N71: =IF(K71<>"","HIGH: SOURCE CONFLICT",IF(AND(L71="END DATE NOT PASSED",M71="REVIEW APPROVAL"),"HIGH: VERIFY",IF(L71="END DATE NOT PASSED","MEDIUM: CHECK STATUS","LOW: HISTORICAL"))) -> LOW: HISTORICAL | O71: Validar documento firmado, revision/WO/sitio, material afectado y evidencia antes de activar alerta automatica.
A72: CTANJZ04653 | B72: D604323 | C72: SRGBU | D72: Expired | E72: 45826 | F72: 45903 | G72: 1 | H72: 1 | L72: =IF(F72="","REVIEW: DATE CONFLICT/EMPTY",IF(F72<'Change Overview'!$B$5,"END DATE PASSED","END DATE NOT PASSED")) -> END DATE PASSED | M72: =IF(K72<>"","REVIEW SOURCE CONFLICT",IF(OR(ISNUMBER(SEARCH("CCB",D72)),ISNUMBER(SEARCH("Pending",D72))),"CCB/PENDING",IF(OR(ISNUMBER(SEARCH("Expired",D72)),ISNUMBER(SEARCH("Closed",D72))),"CLOSED/EXPIRED",IF(E72="","NO RELEASE DATE","REVIEW APPROVAL")))) -> CLOSED/EXPIRED | N72: =IF(K72<>"","HIGH: SOURCE CONFLICT",IF(AND(L72="END DATE NOT PASSED",M72="REVIEW APPROVAL"),"HIGH: VERIFY",IF(L72="END DATE NOT PASSED","MEDIUM: CHECK STATUS","LOW: HISTORICAL"))) -> LOW: HISTORICAL | O72: Validar documento firmado, revision/WO/sitio, material afectado y evidencia antes de activar alerta automatica.
A73: CTANJZ04654 | B73: DP524962 | C73: STBU | D73: Expired | E73: 45834 | F73: 45874 | G73: 1 | H73: 1 | I73: 73-103558-04 | L73: =IF(F73="","REVIEW: DATE CONFLICT/EMPTY",IF(F73<'Change Overview'!$B$5,"END DATE PASSED","END DATE NOT PASSED")) -> END DATE PASSED | M73: =IF(K73<>"","REVIEW SOURCE CONFLICT",IF(OR(ISNUMBER(SEARCH("CCB",D73)),ISNUMBER(SEARCH("Pending",D73))),"CCB/PENDING",IF(OR(ISNUMBER(SEARCH("Expired",D73)),ISNUMBER(SEARCH("Closed",D73))),"CLOSED/EXPIRED",IF(E73="","NO RELEASE DATE","REVIEW APPROVAL")))) -> CLOSED/EXPIRED | N73: =IF(K73<>"","HIGH: SOURCE CONFLICT",IF(AND(L73="END DATE NOT PASSED",M73="REVIEW APPROVAL"),"HIGH: VERIFY",IF(L73="END DATE NOT PASSED","MEDIUM: CHECK STATUS","LOW: HISTORICAL"))) -> LOW: HISTORICAL | O73: Validar documento firmado, revision/WO/sitio, material afectado y evidencia antes de activar alerta automatica.
A74: CTANJZ04655 | B74: D604352 | C74: SRGBU | D74: Expired | E74: 45826 | F74: 45904 | G74: 1 | H74: 1 | L74: =IF(F74="","REVIEW: DATE CONFLICT/EMPTY",IF(F74<'Change Overview'!$B$5,"END DATE PASSED","END DATE NOT PASSED")) -> END DATE PASSED | M74: =IF(K74<>"","REVIEW SOURCE CONFLICT",IF(OR(ISNUMBER(SEARCH("CCB",D74)),ISNUMBER(SEARCH("Pending",D74))),"CCB/PENDING",IF(OR(ISNUMBER(SEARCH("Expired",D74)),ISNUMBER(SEARCH("Closed",D74))),"CLOSED/EXPIRED",IF(E74="","NO RELEASE DATE","REVIEW APPROVAL")))) -> CLOSED/EXPIRED | N74: =IF(K74<>"","HIGH: SOURCE CONFLICT",IF(AND(L74="END DATE NOT PASSED",M74="REVIEW APPROVAL"),"HIGH: VERIFY",IF(L74="END DATE NOT PASSED","MEDIUM: CHECK STATUS","LOW: HISTORICAL"))) -> LOW: HISTORICAL | O74: Validar documento firmado, revision/WO/sitio, material afectado y evidencia antes de activar alerta automatica.
A75: CTANJZ04663 | B75: D603477 | C75: STBU | D75: Expired | E75: 45834 | F75: 45910 | G75: 4 | H75: 4 | L75: =IF(F75="","REVIEW: DATE CONFLICT/EMPTY",IF(F75<'Change Overview'!$B$5,"END DATE PASSED","END DATE NOT PASSED")) -> END DATE PASSED | M75: =IF(K75<>"","REVIEW SOURCE CONFLICT",IF(OR(ISNUMBER(SEARCH("CCB",D75)),ISNUMBER(SEARCH("Pending",D75))),"CCB/PENDING",IF(OR(ISNUMBER(SEARCH("Expired",D75)),ISNUMBER(SEARCH("Closed",D75))),"CLOSED/EXPIRED",IF(E75="","NO RELEASE DATE","REVIEW APPROVAL")))) -> CLOSED/EXPIRED | N75: =IF(K75<>"","HIGH: SOURCE CONFLICT",IF(AND(L75="END DATE NOT PASSED",M75="REVIEW APPROVAL"),"HIGH: VERIFY",IF(L75="END DATE NOT PASSED","MEDIUM: CHECK STATUS","LOW: HISTORICAL"))) -> LOW: HISTORICAL | O75: Validar documento firmado, revision/WO/sitio, material afectado y evidencia antes de activar alerta automatica.
A76: CTANJZ04665 | B76: D603650 | C76: STBU | D76: Expired | E76: 45834 | F76: 45912 | G76: 2 | H76: 2 | L76: =IF(F76="","REVIEW: DATE CONFLICT/EMPTY",IF(F76<'Change Overview'!$B$5,"END DATE PASSED","END DATE NOT PASSED")) -> END DATE PASSED | M76: =IF(K76<>"","REVIEW SOURCE CONFLICT",IF(OR(ISNUMBER(SEARCH("CCB",D76)),ISNUMBER(SEARCH("Pending",D76))),"CCB/PENDING",IF(OR(ISNUMBER(SEARCH("Expired",D76)),ISNUMBER(SEARCH("Closed",D76))),"CLOSED/EXPIRED",IF(E76="","NO RELEASE DATE","REVIEW APPROVAL")))) -> CLOSED/EXPIRED | N76: =IF(K76<>"","HIGH: SOURCE CONFLICT",IF(AND(L76="END DATE NOT PASSED",M76="REVIEW APPROVAL"),"HIGH: VERIFY",IF(L76="END DATE NOT PASSED","MEDIUM: CHECK STATUS","LOW: HISTORICAL"))) -> LOW: HISTORICAL | O76: Validar documento firmado, revision/WO/sitio, material afectado y evidencia antes de activar alerta automatica.
A77: CTANJZ04673 | B77: D604622 | C77: SRGBU | D77: Expired | E77: 45839 | F77: 45915 | G77: 1 | H77: 1 | L77: =IF(F77="","REVIEW: DATE CONFLICT/EMPTY",IF(F77<'Change Overview'!$B$5,"END DATE PASSED","END DATE NOT PASSED")) -> END DATE PASSED | M77: =IF(K77<>"","REVIEW SOURCE CONFLICT",IF(OR(ISNUMBER(SEARCH("CCB",D77)),ISNUMBER(SEARCH("Pending",D77))),"CCB/PENDING",IF(OR(ISNUMBER(SEARCH("Expired",D77)),ISNUMBER(SEARCH("Closed",D77))),"CLOSED/EXPIRED",IF(E77="","NO RELEASE DATE","REVIEW APPROVAL")))) -> CLOSED/EXPIRED | N77: =IF(K77<>"","HIGH: SOURCE CONFLICT",IF(AND(L77="END DATE NOT PASSED",M77="REVIEW APPROVAL"),"HIGH: VERIFY",IF(L77="END DATE NOT PASSED","MEDIUM: CHECK STATUS","LOW: HISTORICAL"))) -> LOW: HISTORICAL | O77: Validar documento firmado, revision/WO/sitio, material afectado y evidencia antes de activar alerta automatica.
A78: CTANJZ04676 | B78: D604366 | C78: STBU | D78: Expired | E78: 45853 | F78: 45916 | G78: 6 | H78: 6 | I78: 73-20247-05, 73-20249-05 | L78: =IF(F78="","REVIEW: DATE CONFLICT/EMPTY",IF(F78<'Change Overview'!$B$5,"END DATE PASSED","END DATE NOT PASSED")) -> END DATE PASSED | M78: =IF(K78<>"","REVIEW SOURCE CONFLICT",IF(OR(ISNUMBER(SEARCH("CCB",D78)),ISNUMBER(SEARCH("Pending",D78))),"CCB/PENDING",IF(OR(ISNUMBER(SEARCH("Expired",D78)),ISNUMBER(SEARCH("Closed",D78))),"CLOSED/EXPIRED",IF(E78="","NO RELEASE DATE","REVIEW APPROVAL")))) -> CLOSED/EXPIRED | N78: =IF(K78<>"","HIGH: SOURCE CONFLICT",IF(AND(L78="END DATE NOT PASSED",M78="REVIEW APPROVAL"),"HIGH: VERIFY",IF(L78="END DATE NOT PASSED","MEDIUM: CHECK STATUS","LOW: HISTORICAL"))) -> LOW: HISTORICAL | O78: Validar documento firmado, revision/WO/sitio, material afectado y evidencia antes de activar alerta automatica.
A79: CTANJZ04678 | B79: D604665 | C79: CVEBU | D79: Expired | E79: 45839 | F79: 45917 | G79: 1 | H79: 1 | L79: =IF(F79="","REVIEW: DATE CONFLICT/EMPTY",IF(F79<'Change Overview'!$B$5,"END DATE PASSED","END DATE NOT PASSED")) -> END DATE PASSED | M79: =IF(K79<>"","REVIEW SOURCE CONFLICT",IF(OR(ISNUMBER(SEARCH("CCB",D79)),ISNUMBER(SEARCH("Pending",D79))),"CCB/PENDING",IF(OR(ISNUMBER(SEARCH("Expired",D79)),ISNUMBER(SEARCH("Closed",D79))),"CLOSED/EXPIRED",IF(E79="","NO RELEASE DATE","REVIEW APPROVAL")))) -> CLOSED/EXPIRED | N79: =IF(K79<>"","HIGH: SOURCE CONFLICT",IF(AND(L79="END DATE NOT PASSED",M79="REVIEW APPROVAL"),"HIGH: VERIFY",IF(L79="END DATE NOT PASSED","MEDIUM: CHECK STATUS","LOW: HISTORICAL"))) -> LOW: HISTORICAL | O79: Validar documento firmado, revision/WO/sitio, material afectado y evidencia antes de activar alerta automatica.
A80: CTANJZ04679 | B80: DP525026 | C80: CVEBU | D80: Expired | E80: 45840 | F80: 45888 | G80: 2 | H80: 2 | I80: 73-103103-05, 73-103603-05 | J80: PICTORIS | L80: =IF(F80="","REVIEW: DATE CONFLICT/EMPTY",IF(F80<'Change Overview'!$B$5,"END DATE PASSED","END DATE NOT PASSED")) -> END DATE PASSED | M80: =IF(K80<>"","REVIEW SOURCE CONFLICT",IF(OR(ISNUMBER(SEARCH("CCB",D80)),ISNUMBER(SEARCH("Pending",D80))),"CCB/PENDING",IF(OR(ISNUMBER(SEARCH("Expired",D80)),ISNUMBER(SEARCH("Closed",D80))),"CLOSED/EXPIRED",IF(E80="","NO RELEASE DATE","REVIEW APPROVAL")))) -> CLOSED/EXPIRED | N80: =IF(K80<>"","HIGH: SOURCE CONFLICT",IF(AND(L80="END DATE NOT PASSED",M80="REVIEW APPROVAL"),"HIGH: VERIFY",IF(L80="END DATE NOT PASSED","MEDIUM: CHECK STATUS","LOW: HISTORICAL"))) -> LOW: HISTORICAL | O80: Validar documento firmado, revision/WO/sitio, material afectado y evidencia antes de activar alerta automatica.
A81: CTANJZ04680 | B81: D604676 | C81: CVEBU | D81: Expired | E81: 45846 | F81: 45918 | G81: 1 | H81: 1 | L81: =IF(F81="","REVIEW: DATE CONFLICT/EMPTY",IF(F81<'Change Overview'!$B$5,"END DATE PASSED","END DATE NOT PASSED")) -> END DATE PASSED | M81: =IF(K81<>"","REVIEW SOURCE CONFLICT",IF(OR(ISNUMBER(SEARCH("CCB",D81)),ISNUMBER(SEARCH("Pending",D81))),"CCB/PENDING",IF(OR(ISNUMBER(SEARCH("Expired",D81)),ISNUMBER(SEARCH("Closed",D81))),"CLOSED/EXPIRED",IF(E81="","NO RELEASE DATE","REVIEW APPROVAL")))) -> CLOSED/EXPIRED | N81: =IF(K81<>"","HIGH: SOURCE CONFLICT",IF(AND(L81="END DATE NOT PASSED",M81="REVIEW APPROVAL"),"HIGH: VERIFY",IF(L81="END DATE NOT PASSED","MEDIUM: CHECK STATUS","LOW: HISTORICAL"))) -> LOW: HISTORICAL | O81: Validar documento firmado, revision/WO/sitio, material afectado y evidencia antes de activar alerta automatica.
A82: CTANJZ04684 | B82: DP524972 | C82: STBU | D82: Expired | E82: 45853 | F82: 45892 | G82: 1 | H82: 1 | L82: =IF(F82="","REVIEW: DATE CONFLICT/EMPTY",IF(F82<'Change Overview'!$B$5,"END DATE PASSED","END DATE NOT PASSED")) -> END DATE PASSED | M82: =IF(K82<>"","REVIEW SOURCE CONFLICT",IF(OR(ISNUMBER(SEARCH("CCB",D82)),ISNUMBER(SEARCH("Pending",D82))),"CCB/PENDING",IF(OR(ISNUMBER(SEARCH("Expired",D82)),ISNUMBER(SEARCH("Closed",D82))),"CLOSED/EXPIRED",IF(E82="","NO RELEASE DATE","REVIEW APPROVAL")))) -> CLOSED/EXPIRED | N82: =IF(K82<>"","HIGH: SOURCE CONFLICT",IF(AND(L82="END DATE NOT PASSED",M82="REVIEW APPROVAL"),"HIGH: VERIFY",IF(L82="END DATE NOT PASSED","MEDIUM: CHECK STATUS","LOW: HISTORICAL"))) -> LOW: HISTORICAL | O82: Validar documento firmado, revision/WO/sitio, material afectado y evidencia antes de activar alerta automatica.
A83: CTANJZ04691 | B83: D604637 | C83: STBU | D83: Expired | E83: 45853 | F83: 45923 | G83: 12 | H83: 12 | I83: 73-20247-05, 73-20249-05 | L83: =IF(F83="","REVIEW: DATE CONFLICT/EMPTY",IF(F83<'Change Overview'!$B$5,"END DATE PASSED","END DATE NOT PASSED")) -> END DATE PASSED | M83: =IF(K83<>"","REVIEW SOURCE CONFLICT",IF(OR(ISNUMBER(SEARCH("CCB",D83)),ISNUMBER(SEARCH("Pending",D83))),"CCB/PENDING",IF(OR(ISNUMBER(SEARCH("Expired",D83)),ISNUMBER(SEARCH("Closed",D83))),"CLOSED/EXPIRED",IF(E83="","NO RELEASE DATE","REVIEW APPROVAL")))) -> CLOSED/EXPIRED | N83: =IF(K83<>"","HIGH: SOURCE CONFLICT",IF(AND(L83="END DATE NOT PASSED",M83="REVIEW APPROVAL"),"HIGH: VERIFY",IF(L83="END DATE NOT PASSED","MEDIUM: CHECK STATUS","LOW: HISTORICAL"))) -> LOW: HISTORICAL | O83: Validar documento firmado, revision/WO/sitio, material afectado y evidencia antes de activar alerta automatica.
A84: CTANJZ04693 | B84: D603586 | C84: STBU | D84: Expired | E84: 45853 | F84: 45889 | G84: 1 | H84: 1 | L84: =IF(F84="","REVIEW: DATE CONFLICT/EMPTY",IF(F84<'Change Overview'!$B$5,"END DATE PASSED","END DATE NOT PASSED")) -> END DATE PASSED | M84: =IF(K84<>"","REVIEW SOURCE CONFLICT",IF(OR(ISNUMBER(SEARCH("CCB",D84)),ISNUMBER(SEARCH("Pending",D84))),"CCB/PENDING",IF(OR(ISNUMBER(SEARCH("Expired",D84)),ISNUMBER(SEARCH("Closed",D84))),"CLOSED/EXPIRED",IF(E84="","NO RELEASE DATE","REVIEW APPROVAL")))) -> CLOSED/EXPIRED | N84: =IF(K84<>"","HIGH: SOURCE CONFLICT",IF(AND(L84="END DATE NOT PASSED",M84="REVIEW APPROVAL"),"HIGH: VERIFY",IF(L84="END DATE NOT PASSED","MEDIUM: CHECK STATUS","LOW: HISTORICAL"))) -> LOW: HISTORICAL | O84: Validar documento firmado, revision/WO/sitio, material afectado y evidencia antes de activar alerta automatica.
A85: CTANJZ04699 | B85: D604620 | C85: CVEBU | D85: Expired | E85: 45853 | F85: 45923 | G85: 1 | H85: 1 | L85: =IF(F85="","REVIEW: DATE CONFLICT/EMPTY",IF(F85<'Change Overview'!$B$5,"END DATE PASSED","END DATE NOT PASSED")) -> END DATE PASSED | M85: =IF(K85<>"","REVIEW SOURCE CONFLICT",IF(OR(ISNUMBER(SEARCH("CCB",D85)),ISNUMBER(SEARCH("Pending",D85))),"CCB/PENDING",IF(OR(ISNUMBER(SEARCH("Expired",D85)),ISNUMBER(SEARCH("Closed",D85))),"CLOSED/EXPIRED",IF(E85="","NO RELEASE DATE","REVIEW APPROVAL")))) -> CLOSED/EXPIRED | N85: =IF(K85<>"","HIGH: SOURCE CONFLICT",IF(AND(L85="END DATE NOT PASSED",M85="REVIEW APPROVAL"),"HIGH: VERIFY",IF(L85="END DATE NOT PASSED","MEDIUM: CHECK STATUS","LOW: HISTORICAL"))) -> LOW: HISTORICAL | O85: Validar documento firmado, revision/WO/sitio, material afectado y evidencia antes de activar alerta automatica.
A86: CTANJZ04702 | B86: D604757 | C86: STBU | D86: Expired | E86: 45856 | F86: 45930 | G86: 2 | H86: 2 | I86: 73-18490-09 | L86: =IF(F86="","REVIEW: DATE CONFLICT/EMPTY",IF(F86<'Change Overview'!$B$5,"END DATE PASSED","END DATE NOT PASSED")) -> END DATE PASSED | M86: =IF(K86<>"","REVIEW SOURCE CONFLICT",IF(OR(ISNUMBER(SEARCH("CCB",D86)),ISNUMBER(SEARCH("Pending",D86))),"CCB/PENDING",IF(OR(ISNUMBER(SEARCH("Expired",D86)),ISNUMBER(SEARCH("Closed",D86))),"CLOSED/EXPIRED",IF(E86="","NO RELEASE DATE","REVIEW APPROVAL")))) -> CLOSED/EXPIRED | N86: =IF(K86<>"","HIGH: SOURCE CONFLICT",IF(AND(L86="END DATE NOT PASSED",M86="REVIEW APPROVAL"),"HIGH: VERIFY",IF(L86="END DATE NOT PASSED","MEDIUM: CHECK STATUS","LOW: HISTORICAL"))) -> LOW: HISTORICAL | O86: Validar documento firmado, revision/WO/sitio, material afectado y evidencia antes de activar alerta automatica.
A87: CTANJZ04703 | B87: D604633 | C87: STBU | D87: Expired | E87: 45856 | F87: 45930 | G87: 2 | H87: 2 | I87: 73-18489-07 | L87: =IF(F87="","REVIEW: DATE CONFLICT/EMPTY",IF(F87<'Change Overview'!$B$5,"END DATE PASSED","END DATE NOT PASSED")) -> END DATE PASSED | M87: =IF(K87<>"","REVIEW SOURCE CONFLICT",IF(OR(ISNUMBER(SEARCH("CCB",D87)),ISNUMBER(SEARCH("Pending",D87))),"CCB/PENDING",IF(OR(ISNUMBER(SEARCH("Expired",D87)),ISNUMBER(SEARCH("Closed",D87))),"CLOSED/EXPIRED",IF(E87="","NO RELEASE DATE","REVIEW APPROVAL")))) -> CLOSED/EXPIRED | N87: =IF(K87<>"","HIGH: SOURCE CONFLICT",IF(AND(L87="END DATE NOT PASSED",M87="REVIEW APPROVAL"),"HIGH: VERIFY",IF(L87="END DATE NOT PASSED","MEDIUM: CHECK STATUS","LOW: HISTORICAL"))) -> LOW: HISTORICAL | O87: Validar documento firmado, revision/WO/sitio, material afectado y evidencia antes de activar alerta automatica.
A88: CTANJZ04705 | B88: D604634 | C88: STBU | D88: Expired | E88: 45856 | F88: 45930 | G88: 2 | H88: 2 | I88: 73-18488-07 | L88: =IF(F88="","REVIEW: DATE CONFLICT/EMPTY",IF(F88<'Change Overview'!$B$5,"END DATE PASSED","END DATE NOT PASSED")) -> END DATE PASSED | M88: =IF(K88<>"","REVIEW SOURCE CONFLICT",IF(OR(ISNUMBER(SEARCH("CCB",D88)),ISNUMBER(SEARCH("Pending",D88))),"CCB/PENDING",IF(OR(ISNUMBER(SEARCH("Expired",D88)),ISNUMBER(SEARCH("Closed",D88))),"CLOSED/EXPIRED",IF(E88="","NO RELEASE DATE","REVIEW APPROVAL")))) -> CLOSED/EXPIRED | N88: =IF(K88<>"","HIGH: SOURCE CONFLICT",IF(AND(L88="END DATE NOT PASSED",M88="REVIEW APPROVAL"),"HIGH: VERIFY",IF(L88="END DATE NOT PASSED","MEDIUM: CHECK STATUS","LOW: HISTORICAL"))) -> LOW: HISTORICAL | O88: Validar documento firmado, revision/WO/sitio, material afectado y evidencia antes de activar alerta automatica.
A89: CTANJZ04706 | B89: DP525064 | C89: CVEBU | D89: Expired | E89: 45853 | F89: 45900 | G89: 13 | H89: 13 | I89: 73-103698-04, 73-103758-03 | L89: =IF(F89="","REVIEW: DATE CONFLICT/EMPTY",IF(F89<'Change Overview'!$B$5,"END DATE PASSED","END DATE NOT PASSED")) -> END DATE PASSED | M89: =IF(K89<>"","REVIEW SOURCE CONFLICT",IF(OR(ISNUMBER(SEARCH("CCB",D89)),ISNUMBER(SEARCH("Pending",D89))),"CCB/PENDING",IF(OR(ISNUMBER(SEARCH("Expired",D89)),ISNUMBER(SEARCH("Closed",D89))),"CLOSED/EXPIRED",IF(E89="","NO RELEASE DATE","REVIEW APPROVAL")))) -> CLOSED/EXPIRED | N89: =IF(K89<>"","HIGH: SOURCE CONFLICT",IF(AND(L89="END DATE NOT PASSED",M89="REVIEW APPROVAL"),"HIGH: VERIFY",IF(L89="END DATE NOT PASSED","MEDIUM: CHECK STATUS","LOW: HISTORICAL"))) -> LOW: HISTORICAL | O89: Validar documento firmado, revision/WO/sitio, material afectado y evidencia antes de activar alerta automatica.
A90: CTANJZ04707 | B90: D604653 | C90: STBU | D90: Expired | E90: 45856 | F90: 45930 | G90: 2 | H90: 2 | I90: 73-17498-04 | L90: =IF(F90="","REVIEW: DATE CONFLICT/EMPTY",IF(F90<'Change Overview'!$B$5,"END DATE PASSED","END DATE NOT PASSED")) -> END DATE PASSED | M90: =IF(K90<>"","REVIEW SOURCE CONFLICT",IF(OR(ISNUMBER(SEARCH("CCB",D90)),ISNUMBER(SEARCH("Pending",D90))),"CCB/PENDING",IF(OR(ISNUMBER(SEARCH("Expired",D90)),ISNUMBER(SEARCH("Closed",D90))),"CLOSED/EXPIRED",IF(E90="","NO RELEASE DATE","REVIEW APPROVAL")))) -> CLOSED/EXPIRED | N90: =IF(K90<>"","HIGH: SOURCE CONFLICT",IF(AND(L90="END DATE NOT PASSED",M90="REVIEW APPROVAL"),"HIGH: VERIFY",IF(L90="END DATE NOT PASSED","MEDIUM: CHECK STATUS","LOW: HISTORICAL"))) -> LOW: HISTORICAL | O90: Validar documento firmado, revision/WO/sitio, material afectado y evidencia antes de activar alerta automatica.
A91: CTANJZ04709 | B91: D604651 | C91: STBU | D91: Expired | E91: 45856 | F91: 45930 | G91: 2 | H91: 2 | I91: 73-17498-04 | L91: =IF(F91="","REVIEW: DATE CONFLICT/EMPTY",IF(F91<'Change Overview'!$B$5,"END DATE PASSED","END DATE NOT PASSED")) -> END DATE PASSED | M91: =IF(K91<>"","REVIEW SOURCE CONFLICT",IF(OR(ISNUMBER(SEARCH("CCB",D91)),ISNUMBER(SEARCH("Pending",D91))),"CCB/PENDING",IF(OR(ISNUMBER(SEARCH("Expired",D91)),ISNUMBER(SEARCH("Closed",D91))),"CLOSED/EXPIRED",IF(E91="","NO RELEASE DATE","REVIEW APPROVAL")))) -> CLOSED/EXPIRED | N91: =IF(K91<>"","HIGH: SOURCE CONFLICT",IF(AND(L91="END DATE NOT PASSED",M91="REVIEW APPROVAL"),"HIGH: VERIFY",IF(L91="END DATE NOT PASSED","MEDIUM: CHECK STATUS","LOW: HISTORICAL"))) -> LOW: HISTORICAL | O91: Validar documento firmado, revision/WO/sitio, material afectado y evidencia antes de activar alerta automatica.
A92: CTANJZ04710 | B92: D604750 | C92: STBU | D92: Expired | E92: 45856 | F92: 45930 | G92: 2 | H92: 2 | I92: 73-18488-07 | L92: =IF(F92="","REVIEW: DATE CONFLICT/EMPTY",IF(F92<'Change Overview'!$B$5,"END DATE PASSED","END DATE NOT PASSED")) -> END DATE PASSED | M92: =IF(K92<>"","REVIEW SOURCE CONFLICT",IF(OR(ISNUMBER(SEARCH("CCB",D92)),ISNUMBER(SEARCH("Pending",D92))),"CCB/PENDING",IF(OR(ISNUMBER(SEARCH("Expired",D92)),ISNUMBER(SEARCH("Closed",D92))),"CLOSED/EXPIRED",IF(E92="","NO RELEASE DATE","REVIEW APPROVAL")))) -> CLOSED/EXPIRED | N92: =IF(K92<>"","HIGH: SOURCE CONFLICT",IF(AND(L92="END DATE NOT PASSED",M92="REVIEW APPROVAL"),"HIGH: VERIFY",IF(L92="END DATE NOT PASSED","MEDIUM: CHECK STATUS","LOW: HISTORICAL"))) -> LOW: HISTORICAL | O92: Validar documento firmado, revision/WO/sitio, material afectado y evidencia antes de activar alerta automatica.
A93: CTANJZ04711 | B93: D604652 | C93: STBU | D93: Expired | E93: 45856 | F93: 45930 | G93: 2 | H93: 2 | I93: 73-102433-05 | L93: =IF(F93="","REVIEW: DATE CONFLICT/EMPTY",IF(F93<'Change Overview'!$B$5,"END DATE PASSED","END DATE NOT PASSED")) -> END DATE PASSED | M93: =IF(K93<>"","REVIEW SOURCE CONFLICT",IF(OR(ISNUMBER(SEARCH("CCB",D93)),ISNUMBER(SEARCH("Pending",D93))),"CCB/PENDING",IF(OR(ISNUMBER(SEARCH("Expired",D93)),ISNUMBER(SEARCH("Closed",D93))),"CLOSED/EXPIRED",IF(E93="","NO RELEASE DATE","REVIEW APPROVAL")))) -> CLOSED/EXPIRED | N93: =IF(K93<>"","HIGH: SOURCE CONFLICT",IF(AND(L93="END DATE NOT PASSED",M93="REVIEW APPROVAL"),"HIGH: VERIFY",IF(L93="END DATE NOT PASSED","MEDIUM: CHECK STATUS","LOW: HISTORICAL"))) -> LOW: HISTORICAL | O93: Validar documento firmado, revision/WO/sitio, material afectado y evidencia antes de activar alerta automatica.
A94: CTANJZ04721 | B94: D605020 | C94: STBU | D94: Expired | E94: 45862 | F94: 46027 | G94: 7 | H94: 7 | I94: 73-20249-05 | L94: =IF(F94="","REVIEW: DATE CONFLICT/EMPTY",IF(F94<'Change Overview'!$B$5,"END DATE PASSED","END DATE NOT PASSED")) -> END DATE PASSED | M94: =IF(K94<>"","REVIEW SOURCE CONFLICT",IF(OR(ISNUMBER(SEARCH("CCB",D94)),ISNUMBER(SEARCH("Pending",D94))),"CCB/PENDING",IF(OR(ISNUMBER(SEARCH("Expired",D94)),ISNUMBER(SEARCH("Closed",D94))),"CLOSED/EXPIRED",IF(E94="","NO RELEASE DATE","REVIEW APPROVAL")))) -> CLOSED/EXPIRED | N94: =IF(K94<>"","HIGH: SOURCE CONFLICT",IF(AND(L94="END DATE NOT PASSED",M94="REVIEW APPROVAL"),"HIGH: VERIFY",IF(L94="END DATE NOT PASSED","MEDIUM: CHECK STATUS","LOW: HISTORICAL"))) -> LOW: HISTORICAL | O94: Validar documento firmado, revision/WO/sitio, material afectado y evidencia antes de activar alerta automatica.
A95: CTANJZ04726 | B95: D604890 | C95: STBU | D95: Expired | E95: 45864 | F95: 45939 | G95: 9 | H95: 9 | L95: =IF(F95="","REVIEW: DATE CONFLICT/EMPTY",IF(F95<'Change Overview'!$B$5,"END DATE PASSED","END DATE NOT PASSED")) -> END DATE PASSED | M95: =IF(K95<>"","REVIEW SOURCE CONFLICT",IF(OR(ISNUMBER(SEARCH("CCB",D95)),ISNUMBER(SEARCH("Pending",D95))),"CCB/PENDING",IF(OR(ISNUMBER(SEARCH("Expired",D95)),ISNUMBER(SEARCH("Closed",D95))),"CLOSED/EXPIRED",IF(E95="","NO RELEASE DATE","REVIEW APPROVAL")))) -> CLOSED/EXPIRED | N95: =IF(K95<>"","HIGH: SOURCE CONFLICT",IF(AND(L95="END DATE NOT PASSED",M95="REVIEW APPROVAL"),"HIGH: VERIFY",IF(L95="END DATE NOT PASSED","MEDIUM: CHECK STATUS","LOW: HISTORICAL"))) -> LOW: HISTORICAL | O95: Validar documento firmado, revision/WO/sitio, material afectado y evidencia antes de activar alerta automatica.
A96: CTANJZ04731 | B96: DP525122 | C96: CVEBU | D96: Expired | E96: 45862 | F96: 45913 | G96: 1 | H96: 1 | L96: =IF(F96="","REVIEW: DATE CONFLICT/EMPTY",IF(F96<'Change Overview'!$B$5,"END DATE PASSED","END DATE NOT PASSED")) -> END DATE PASSED | M96: =IF(K96<>"","REVIEW SOURCE CONFLICT",IF(OR(ISNUMBER(SEARCH("CCB",D96)),ISNUMBER(SEARCH("Pending",D96))),"CCB/PENDING",IF(OR(ISNUMBER(SEARCH("Expired",D96)),ISNUMBER(SEARCH("Closed",D96))),"CLOSED/EXPIRED",IF(E96="","NO RELEASE DATE","REVIEW APPROVAL")))) -> CLOSED/EXPIRED | N96: =IF(K96<>"","HIGH: SOURCE CONFLICT",IF(AND(L96="END DATE NOT PASSED",M96="REVIEW APPROVAL"),"HIGH: VERIFY",IF(L96="END DATE NOT PASSED","MEDIUM: CHECK STATUS","LOW: HISTORICAL"))) -> LOW: HISTORICAL | O96: Validar documento firmado, revision/WO/sitio, material afectado y evidencia antes de activar alerta automatica.
A97: CTANJZ04732 | B97: D604140 | C97: STBU | D97: Expired | E97: 45866 | F97: 45944 | G97: 1 | H97: 1 | L97: =IF(F97="","REVIEW: DATE CONFLICT/EMPTY",IF(F97<'Change Overview'!$B$5,"END DATE PASSED","END DATE NOT PASSED")) -> END DATE PASSED | M97: =IF(K97<>"","REVIEW SOURCE CONFLICT",IF(OR(ISNUMBER(SEARCH("CCB",D97)),ISNUMBER(SEARCH("Pending",D97))),"CCB/PENDING",IF(OR(ISNUMBER(SEARCH("Expired",D97)),ISNUMBER(SEARCH("Closed",D97))),"CLOSED/EXPIRED",IF(E97="","NO RELEASE DATE","REVIEW APPROVAL")))) -> CLOSED/EXPIRED | N97: =IF(K97<>"","HIGH: SOURCE CONFLICT",IF(AND(L97="END DATE NOT PASSED",M97="REVIEW APPROVAL"),"HIGH: VERIFY",IF(L97="END DATE NOT PASSED","MEDIUM: CHECK STATUS","LOW: HISTORICAL"))) -> LOW: HISTORICAL | O97: Validar documento firmado, revision/WO/sitio, material afectado y evidencia antes de activar alerta automatica.
A98: CTANJZ04733 | B98: DP525134 | C98: STBU | D98: Expired | E98: 45863 | F98: 45915 | G98: 4 | H98: 4 | L98: =IF(F98="","REVIEW: DATE CONFLICT/EMPTY",IF(F98<'Change Overview'!$B$5,"END DATE PASSED","END DATE NOT PASSED")) -> END DATE PASSED | M98: =IF(K98<>"","REVIEW SOURCE CONFLICT",IF(OR(ISNUMBER(SEARCH("CCB",D98)),ISNUMBER(SEARCH("Pending",D98))),"CCB/PENDING",IF(OR(ISNUMBER(SEARCH("Expired",D98)),ISNUMBER(SEARCH("Closed",D98))),"CLOSED/EXPIRED",IF(E98="","NO RELEASE DATE","REVIEW APPROVAL")))) -> CLOSED/EXPIRED | N98: =IF(K98<>"","HIGH: SOURCE CONFLICT",IF(AND(L98="END DATE NOT PASSED",M98="REVIEW APPROVAL"),"HIGH: VERIFY",IF(L98="END DATE NOT PASSED","MEDIUM: CHECK STATUS","LOW: HISTORICAL"))) -> LOW: HISTORICAL | O98: Validar documento firmado, revision/WO/sitio, material afectado y evidencia antes de activar alerta automatica.
A99: CTANJZ04734 | B99: DP525135 | C99: STBU | D99: Expired | E99: 45863 | F99: 45915 | G99: 1 | H99: 1 | I99: 73-103633-04 | L99: =IF(F99="","REVIEW: DATE CONFLICT/EMPTY",IF(F99<'Change Overview'!$B$5,"END DATE PASSED","END DATE NOT PASSED")) -> END DATE PASSED | M99: =IF(K99<>"","REVIEW SOURCE CONFLICT",IF(OR(ISNUMBER(SEARCH("CCB",D99)),ISNUMBER(SEARCH("Pending",D99))),"CCB/PENDING",IF(OR(ISNUMBER(SEARCH("Expired",D99)),ISNUMBER(SEARCH("Closed",D99))),"CLOSED/EXPIRED",IF(E99="","NO RELEASE DATE","REVIEW APPROVAL")))) -> CLOSED/EXPIRED | N99: =IF(K99<>"","HIGH: SOURCE CONFLICT",IF(AND(L99="END DATE NOT PASSED",M99="REVIEW APPROVAL"),"HIGH: VERIFY",IF(L99="END DATE NOT PASSED","MEDIUM: CHECK STATUS","LOW: HISTORICAL"))) -> LOW: HISTORICAL | O99: Validar documento firmado, revision/WO/sitio, material afectado y evidencia antes de activar alerta automatica.
A100: CTANJZ04739 | B100: D605179 | C100: STBU | D100: Expired | E100: 45868 | F100: 45946 | G100: 1 | H100: 1 | L100: =IF(F100="","REVIEW: DATE CONFLICT/EMPTY",IF(F100<'Change Overview'!$B$5,"END DATE PASSED","END DATE NOT PASSED")) -> END DATE PASSED | M100: =IF(K100<>"","REVIEW SOURCE CONFLICT",IF(OR(ISNUMBER(SEARCH("CCB",D100)),ISNUMBER(SEARCH("Pending",D100))),"CCB/PENDING",IF(OR(ISNUMBER(SEARCH("Expired",D100)),ISNUMBER(SEARCH("Closed",D100))),"CLOSED/EXPIRED",IF(E100="","NO RELEASE DATE","REVIEW APPROVAL")))) -> CLOSED/EXPIRED | N100: =IF(K100<>"","HIGH: SOURCE CONFLICT",IF(AND(L100="END DATE NOT PASSED",M100="REVIEW APPROVAL"),"HIGH: VERIFY",IF(L100="END DATE NOT PASSED","MEDIUM: CHECK STATUS","LOW: HISTORICAL"))) -> LOW: HISTORICAL | O100: Validar documento firmado, revision/WO/sitio, material afectado y evidencia antes de activar alerta automatica.
...

Sheet Deviation Instructions
A1: CTAN Number | B1: Customer Deviation# | C1: SKU (document text) | D1: Target PN | E1: RefDes | F1: Change Operation | G1: Old / Remove CPN | H1: New / Add CPN | I1: Proposed Validation | J1: Source Excerpt (verbatim) | K1: Source Workflow | L1: Effective Until (source) | M1: Auto Gate | N1: Review State | O1: Source File | P1: Critical Note
A2: CTANJZ05414 | B2: D613039 | C2: HEIMDALL | D2: 73-103459-02 | E2: U65 | F2: REMOVE | G2: 15-109506-01 | I2: BOM / P&P / FAI | J2: Remove U65/15-109506-01 from BOM | K2: FAI Status | L2: 2026-10-29 | M2: NO - PENDING REVIEW | N2: Pending Review | O2: Deviation.csv | P2: Aplica solo si la desviacion se usa en la WO; requiere confirmar sustitucion Renesas/TI. El PN 73-103758-04 se menciona como referencia, no como BOM objetivo.
A3: CTANJZ05414 | B3: D613039 | C3: HEIMDALL | D3: 73-103459-02 | E3: U66 | F3: ADD | H3: 15-109628-01 | I3: BOM / P&P / FAI | J3: Add U66/15-109628-01 to BOM | K3: FAI Status | L3: 2026-10-29 | M3: NO - PENDING REVIEW | N3: Pending Review | O3: Deviation.csv | P3: Aplica solo si la desviacion se usa en la WO; requiere confirmar sustitucion Renesas/TI. El PN 73-103758-04 se menciona como referencia, no como BOM objetivo.
A4: CTANJZ05414 | B4: D613039 | C4: HEIMDALL | D4: 73-103459-02 | E4: R149 | F4: REPLACE | G4: 12-4443-01 | H4: 12-2567-02 | I4: BOM / P&P / ICT | J4: Change R149 from 12-4443-01 to 12-2567-02 | K4: FAI Status | L4: 2026-10-29 | M4: NO - PENDING REVIEW | N4: Pending Review | O4: Deviation.csv | P4: Aplica solo si la desviacion se usa en la WO; requiere confirmar sustitucion Renesas/TI. El PN 73-103758-04 se menciona como referencia, no como BOM objetivo.
A5: CTANJZ05414 | B5: D613039 | C5: HEIMDALL | D5: 73-103459-02 | E5: R151 | F5: REPLACE | G5: 12-100278-01 | H5: 12-4978-01 | I5: BOM / P&P / ICT | J5: Change R151 from 12-100278-01 to 12-4978-01 | K5: FAI Status | L5: 2026-10-29 | M5: NO - PENDING REVIEW | N5: Pending Review | O5: Deviation.csv | P5: Aplica solo si la desviacion se usa en la WO; requiere confirmar sustitucion Renesas/TI. El PN 73-103758-04 se menciona como referencia, no como BOM objetivo.
A6: CTANJZ05519 | B6: D614380 | C6: PICTORIS | D6: 73-103603-05 | E6: U417 | F6: REPLACE | G6: 15-108939-01 | H6: 15-108939-03 | I6: BOM / AOI / FAI | J6: For refdes U417Remove from BOM15-108939-01 | K6: CCB | L6: 2027-01-01 | M6: NO - PENDING REVIEW | N6: Pending Review | O6: Deviation.csv | P6: CSV en estado CCB; NO aprobado. La revision B0 consta en descripcion, confirmar aplicabilidad para cada PCBA.
A7: CTANJZ05519 | B7: D614380 | C7: PICTORIS | D7: 73-103103-05 | E7: U417 | F7: REPLACE | G7: 15-108939-01 | H7: 15-108939-03 | I7: BOM / AOI / FAI | J7: For refdes U417Remove from BOM15-108939-01 | K7: CCB | L7: 2027-01-01 | M7: NO - PENDING REVIEW | N7: Pending Review | O7: Deviation.csv | P7: CSV en estado CCB; NO aprobado. La revision B0 consta en descripcion, confirmar aplicabilidad para cada PCBA.
A8: CTANJZ05408 | B8: D613038 | C8: TYNE | D8: 68-104853-01 | F8: MODULE_REPLACE | G8: 800-117978-03 | H8: 800-118978-03 | I8: Assembly BOM / module PN / FAI | J8: FJZ is hereby allowed to replace Taylor Module CPN 800-117978-03 with 800-118978-03 | K8: FAI Status | L8: 2026-10-27 | M8: NO - PENDING REVIEW | N8: Pending Review | O8: Deviation.csv | P8: Cambiar MODULO completo; la descripcion indica explicitamente que 15-110522-02 NO reemplaza individualmente 15-110522-01.
A9: CTANJZ05408 | B9: D613038 | C9: TYNE | D9: 68-104854-01 | F9: MODULE_REPLACE | G9: 800-117978-03 | H9: 800-118978-03 | I9: Assembly BOM / module PN / FAI | J9: FJZ is hereby allowed to replace Taylor Module CPN 800-117978-03 with 800-118978-03 | K9: FAI Status | L9: 2026-10-27 | M9: NO - PENDING REVIEW | N9: Pending Review | O9: Deviation.csv | P9: Cambiar MODULO completo; la descripcion indica explicitamente que 15-110522-02 NO reemplaza individualmente 15-110522-01.

Sheet Traducciones ECN ECO
A1: SMTinel Yokoten | Descripciones del customer en español
A2: Objetivo | B2: Mostrar primero el resumen y la traducción técnica en español sin eliminar el original en inglés.
A3: Alcance actual | B3: 487 desviaciones + 728 ECO con numero de documento valido. 464 filas de CSV sin ECO # quedan en ECO Items como no vinculadas; no se inventan documentos ECN.
A4: Cambio solicitado | B4: Para ECO: Related Document=Agile ECN; Match por PCBA PN EXACTO y New Rev EXACTA; Old Rev es la transicion de origen, no una segunda aplicabilidad.
A5: Summary ES | B5: Síntesis de impacto: producto, PN, referencias, sustitución y condición de validación.
A6: Change Description ES | B6: Traducción técnica fiel del texto original; NO alterar códigos, CPN/MPN, PN, RefDes, revision ni unidades.
A7: Translation Review | B7: Traduccion para consulta / Requiere revision: este campo jamás significa que el cambio está aprobado.
A8: Texto original | B8: Se conserva intacto en Change Register / Change Description y se muestra expandible en Yokoten.
A9: Sin traducción | B9: Yokoten debe mostrar "Traducción pendiente" y permitir consultar el texto original. No inventar traducción.
A10: Fuente de verdad | B10: Estado, aplicabilidad y vigencia provienen del documento oficial; la traducción solo ayuda a leerlo.
A11: Priorizacion | B11: Traducir primero los ECO que realmente coinciden por PN y nueva revisión; conservar original del customer sin cambios.
A12: Nota sobre desviaciones | B12: Se prepararon 10 traducciones técnicas de documentos ejemplares; las 477 restantes conservan el texto inglés.
A13: Flujo GitHub | B13: Publicar el libro actualizado como SMTinel_Yokoten_Knowledge_DB.xlsx en el repositorio para lectura dinámica.

Sheet Qualification
A1: Record ID | B1: Product | C1: Part Number | D1: Rev | E1: Side | F1: Line | G1: Status | H1: P&P Program | I1: AOI Library | J1: Last Qualification | K1: Owner | L1: FAI Link | M1: SOP Link | N1: Notes | O1: Active
A2: QUAL-PICTORIS-B0-L13 | B2: PICTORIS | C2: 73-103603-05 | D2: B0 | E2: Top | F2: L13 | G2: Requal Required | N2: Queja histórica por orientación de J73. Actualizar la calificación después de revisar los controles. | O2: Y
A3: QUAL-PICTORIS-B0-L17 | B3: PICTORIS | C3: 73-103603-05 | D3: B0 | E3: Top | F3: L17 | G3: Requal Required | N3: Aplicar esta lección antes de liberar la línea. | O3: Y

Sheet Findings
A1: Finding ID | B1: Scope | C1: Product | D1: Part Number | E1: Component CPN | F1: RefDes | G1: Rev | H1: Line | I1: Finding | J1: Critical Characteristic | K1: Migration Gate | L1: Severity | M1: Source | N1: 8D / LL Link | O1: Status | P1: Owner | Q1: Active
A2: LL-PICTORIS-J73 | B2: PRODUCT | C2: PICTORIS | D2: 73-103603-05 | E2: 27-100137-01 | F2: J73 | G2: B0 | H2: L13 | I2: Queja de cliente: J73 se instaló al revés. | J2: Orientación de J73. El cuerpo blanco va hacia el pin 1. No usar el triángulo como guía. | K2: Antes de liberar la línea, confirmar que el cuerpo blanco apunta al pin 1. Revisar la orientación con AOI y en la primera pieza. | L2: Critical | M2: Queja de cliente / lección 8D | O2: Open | Q2: Y
A3: LL-PICTORIS-J73-L13 | B3: PRODUCT_REV_LINE | C3: PICTORIS | D3: 73-103603-05 | E3: 27-100137-01 | F3: J73 | G3: B0 | H3: L13 | I3: La revisión de AOI no detectó J73 instalado al revés. | J3: Orientación de J73. El cuerpo blanco va hacia el pin 1. No usar el triángulo como guía. | K3: Probar que AOI detecte una pieza correcta y otra con J73 al revés. Repetir la prueba al calificar o recalificar la línea. | L3: High | M3: Hallazgo histórico de línea | O3: Open | Q3: Y
A4: LL-PICTORIS-WO-IDENTITY | B4: PRODUCT | C4: PICTORIS | D4: 73-103603-05 | I4: Se usó una revisión incorrecta y, en otra orden, un número de parte incorrecto. | J4: Número de parte y revisión liberada de la orden de trabajo. | K4: Antes de crear o liberar la orden, confirmar número de parte y revisión. Revisar modelo, número de parte y revisión en la primera pieza. | L4: High | M4: Control de cambios 2026-09-15 · EVT-08 / EVT-09 | O4: Open | P4: Planeación / PM | Q4: Y
A5: LL-BAYFRONT-BOM-LOADLIST | B5: PRODUCT | C5: BAYFRONT | D5: 73-103826-05 | I5: La lista de carga no coincidía con la BOM: había diferencias en parte, posición o cantidad. | J5: Coincidencia entre BOM liberada y lista de carga. | K5: Antes de aprobar la lista de carga, comparar número de parte, posición, cantidad y revisión contra la BOM liberada. | L5: Medium | M5: Control de cambios 2026-09-15 · EVT-01 | O5: Open | P5: Programación / Calidad | Q5: Y
A6: LL-ARATA-ODM-CONFIG | B6: REVISION | C6: ARATA | D6: 74-133408-02 | G6: B0 | I6: El número de parte por sí solo no identifica esta configuración. U58, la revisión y el cambio deben coincidir en SMT e ICT. | J6: Configuración correcta: U58, revisión y cambio liberado. | K6: Antes de liberar, confirmar U58, revisión y cambio en la orden. Revisar que SMT e ICT usen la misma configuración y pruebas. | L6: High | M6: Control de cambios 2026-09-15 · EVT-02 / EVT-03 / EVT-04 | O6: Open | P6: Planeación / Producto / SMT / ICT | Q6: Y
A7: LL-TAYLOR-LARGE-BODY-CLEARANCE | B7: PRODUCT | C7: TAYLOR | I7: Algunos componentes grandes quedan demasiado cerca o se tocan. AOI no siempre detecta esta separación. | J7: Separación entre componentes y tamaño aprobado del cuerpo. | K7: Antes de liberar, revisar tamaño, centrado y posición de los componentes. Medir la separación después de colocar y soldar. Repetir si cambia el proveedor o componente. | L7: High | M7: Control de cambios 2026-09-15 · EVT-19 / EVT-20 / EVT-21; caso Taylor | O7: Open | P7: Carlos Martínez / Josué Rangel / José Cruz | Q7: Y
A8: LL-NIXIE-MIC-SEATING | B8: PRODUCT | C8: NIXIE | I8: El micrófono puede levantarse o mover las bolas de soldadura si se presiona demasiado. Se probaron boquillas y ajustes; la causa aún no está confirmada. | J8: Asiento del micrófono y bolas de soldadura sin desplazamiento. | K8: Usar la boquilla y los ajustes aprobados por el proveedor. Revisar después de colocar y soldar. Revalidar si cambia el proveedor, la boquilla o el programa. | L8: High | M8: Caso SMTinel NIXIE Q1WK08 / WK10 | N8: https://chatgpt.com/c/6ab960a3-208c-83e8-8009-8c18a39dd451 | O8: Monitoring | P8: SMT-P&P / Carlos Martínez | Q8: Y
A9: LL-TUFNELL-DEVIATION-SCOPE-HI | B9: PRODUCT | C9: TUFNELL PARK | D9: 73-20247-06 | E9: 15-102981-01; 15-102981-02 | F9: U23 | I9: Una desviación de CRBU podría permitir material cancelado en NGFWBU, donde no aplica. | J9: La desviación de U23 solo aplica al producto y orden aprobados. | K9: Antes de aceptar el material, confirmar unidad de negocio, producto y orden contra la desviación. Si no coinciden, mantener el bloqueo en SAP. | L9: Critical | M9: Análisis de desviación CRBU / NGFWBU | O9: Open | Q9: Y
A10: LL-TUFNELL-DEVIATION-SCOPE-LO | B10: PRODUCT | C10: TUFNELL PARK | D10: 73-20249-06 | E10: 15-102981-01; 15-102981-02 | F10: U23 | I10: Una desviación de CRBU podría permitir material cancelado en NGFWBU, donde no aplica. | J10: La desviación de U23 solo aplica al producto y orden aprobados. | K10: Antes de aceptar el material, confirmar unidad de negocio, producto y orden contra la desviación. Si no coinciden, mantener el bloqueo en SAP. | L10: Critical | M10: Análisis de desviación CRBU / NGFWBU | O10: Open | Q10: Y
A11: LL-CHARON-CR95-POLARITY | B11: PRODUCT | C11: CHARON | D11: 73-21231-05 | E11: 25-100369-01 | F11: CR95 | G11: C0 | H11: L13 | I11: CR95 se encontró al revés. En esta pieza, la marca verde indica el ánodo. La tablilla tiene el silkscreen al contrario: no guiarse por él. | J11: Orientación de CR95. La marca verde va en sentido opuesto a la marca de polaridad del silkscreen. | K11: Antes de liberar, revisar que la marca verde quede al lado opuesto al silkscreen de polaridad. Usar la ayuda visual aprobada. | L11: Critical | M11: Revisión del caso Charon / correo de polaridad CR95 | O11: Closed | Q11: Y
A12: LL-PICTORIS-BOTON-FLUX | B12: PRODUCT | C12: PICTORIS | D12: 73-103603-05 | E12: 22-100214-01 | F12: S1 | I12: El flux aplicado directamente al cuerpo del botón reprodujo el atasco. El botón puede quedar húmedo o pegajoso y los residuos solidificarse con las horas. Rechazar y reemplazar si hay humedad por flux, pegajosidad o residuos, aunque todavía funcione. | J12: Botón sin flux ni residuos, con accionamiento y retorno libres. | K12: Antes del retrabajo, proteger con Kapton toda el área de conectores y el cuerpo del botón, sin presionar el actuador. No aplicar flux al componente. Revisar al 100 % antes y después. Ante contaminación, reemplazar sin esperar al atasco. Para probar el botón, presionar solo con el dedo. No usar pinzas puntiagudas. | M12: Alerta de calidad CVEBU QAF350 Rev03. Experimento y criterios reportados el 30/09/2026. | O12: Open | Q12: Y
A13: LL-MILLENIUM-BOTON-FLUX | B13: PRODUCT | C13: MILLENIUM | D13: 73-102226-06 | E13: 22-100214-01 | F13: S1 | I13: El flux aplicado directamente al cuerpo del botón reprodujo el atasco. El botón puede quedar húmedo o pegajoso y los residuos solidificarse con las horas. Rechazar y reemplazar si hay humedad por flux, pegajosidad o residuos, aunque todavía funcione. | J13: Botón sin flux ni residuos, con accionamiento y retorno libres. | K13: Antes del retrabajo, proteger con Kapton toda el área de conectores y el cuerpo del botón, sin presionar el actuador. No aplicar flux al componente. Revisar al 100 % antes y después. Ante contaminación, reemplazar sin esperar al atasco. Para probar el botón, presionar solo con el dedo. No usar pinzas puntiagudas. | M13: Alerta de calidad CVEBU QAF350 Rev03. Experimento y criterios reportados el 30/09/2026. | O13: Open | Q13: Y
A14: LL-OCTAVIO-BOTON-FLUX | B14: PRODUCT | C14: OCTAVIO | D14: 73-102701-01 | E14: 22-100214-01 | F14: S1 | I14: El flux aplicado directamente al cuerpo del botón reprodujo el atasco. El botón puede quedar húmedo o pegajoso y los residuos solidificarse con las horas. Rechazar y reemplazar si hay humedad por flux, pegajosidad o residuos, aunque todavía funcione. | J14: Botón sin flux ni residuos, con accionamiento y retorno libres. | K14: Antes del retrabajo, proteger con Kapton toda el área de conectores y el cuerpo del botón, sin presionar el actuador. No aplicar flux al componente. Revisar al 100 % antes y después. Ante contaminación, reemplazar sin esperar al atasco. Para probar el botón, presionar solo con el dedo. No usar pinzas puntiagudas. | M14: Alerta de calidad CVEBU QAF350 Rev03. Experimento y criterios reportados el 30/09/2026. | O14: Open | Q14: Y
A15: LL-BROOKLYN-BOTON-FLUX | B15: PRODUCT | C15: BROOKLYN | D15: 73-102022-02 | E15: 22-100214-01 | F15: S1 | I15: El flux aplicado directamente al cuerpo del botón reprodujo el atasco. El botón puede quedar húmedo o pegajoso y los residuos solidificarse con las horas. Rechazar y reemplazar si hay humedad por flux, pegajosidad o residuos, aunque todavía funcione. | J15: Botón sin flux ni residuos, con accionamiento y retorno libres. | K15: Antes del retrabajo, proteger con Kapton toda el área de conectores y el cuerpo del botón, sin presionar el actuador. No aplicar flux al componente. Revisar al 100 % antes y después. Ante contaminación, reemplazar sin esperar al atasco. Para probar el botón, presionar solo con el dedo. No usar pinzas puntiagudas. | M15: Alerta de calidad CVEBU QAF350 Rev03. Experimento y criterios reportados el 30/09/2026. | O15: Open | Q15: Y
A16: LL-DAVINCI-BOTON-FLUX | B16: PRODUCT | C16: DAVINCI | D16: 73-102797-02 | E16: 22-100214-01 | F16: S1 | I16: El flux aplicado directamente al cuerpo del botón reprodujo el atasco. El botón puede quedar húmedo o pegajoso y los residuos solidificarse con las horas. Rechazar y reemplazar si hay humedad por flux, pegajosidad o residuos, aunque todavía funcione. | J16: Botón sin flux ni residuos, con accionamiento y retorno libres. | K16: Antes del retrabajo, proteger con Kapton toda el área de conectores y el cuerpo del botón, sin presionar el actuador. No aplicar flux al componente. Revisar al 100 % antes y después. Ante contaminación, reemplazar sin esperar al atasco. Para probar el botón, presionar solo con el dedo. No usar pinzas puntiagudas. | M16: Alerta de calidad CVEBU QAF350 Rev03. Experimento y criterios reportados el 30/09/2026. | O16: Open | Q16: Y
A17: LL-HEIMDALL-CLIP-CUSTODY | B17: REVISION | C17: HEIMDALL | D17: 73-103459-02 | E17: 700-136420-01 | F17: J3-J8 | G17: A0 | I17: El cambio agregó clips en J3-J8, pero no quedó claro qué proceso los instala ni cómo se revisan. | J17: Clip presente y fijo en J3-J8. Contacto dorado limpio y proceso de ensamble definido. | K17: Antes de liberar un cambio, definir quién instala cada pieza, cómo se instala y cómo se revisa. Si no está claro, detener la liberación y pedir aclaración al equipo del cliente. | L17: Critical | M17: PCAMAP 61-107350-02 · investigación del clip Heimdall | O17: Open | Q17: Y
A18: LL-GREENFORD-AOI-MARCADO | B18: PRODUCT | C18: GREENFORD | D18: 73-104532-01 | E18: 17-103689-02; 17-103691-01; 17-102460-07 | I18: El usuario reportó un paro de 5 horas en tercer turno después de aceptar material reprogramado y ajustar OCV/OCR en otra corrida. La decisión no quedó disponible para todas las librerías/turnos. El reply aclara C1 como identificación aceptada y solicita referencia oficial. Lección: una liberación local requiere referencia controlada y despliegue verificado por CPN. El historial de cambios debe comprobar la propagación real. | J18: Identificación autorizada del material reprogramado y revisión vigente OCV/OCR | K18: Antes del cambio de modelo o línea, cotejar PN, programación, marcado autorizado y librería vigente. Sin referencia oficial disponible, retener y escalar. No extender C1 a otros PN o programaciones por semejanza. | M18: Chat Análisis de causa raíz, 01/10/2026. Relato del usuario y síntesis de PILOTO GREENFORD / Re: PILOTO GREENFORD. La revisión de los adjuntos debe respaldar la autorización. | N18: https://chatgpt.com/g/g-p-6abe462c09308191916f0eed68e0b198/c/6abe43f8-a784-83e8-9f10-f6d0d31564a3 | O18: Open | Q18: Y
A19: LL-BROOKLYN-S1-ACCIONAMIENTO | B19: PRODUCT | C19: BROOKLYN | D19: 73-102022-02 | E19: 22-100214-01 | F19: S1 | I19: En el experimento con 5 unidades Brooklyn se reportó que el accionamiento con tweezer puntiaguda podía sacar el actuador de sus guías. Lección: la verificación del botón debe detectar la falla sin introducir daño. El ensayo de alcohol/flux corresponde a LL-BROOKLYN-BOTON-FLUX y no prueba inmunidad ante todos los procesos de limpieza. | J19: Accionamiento y retorno de S1 sin fuerza lateral ni herramienta punzante | K19: Definir en WI el método de accionamiento controlado. Antes/después del retrabajo revisar retorno libre, atasco, retorno lento, decoloración y residuos. Separar defecto previo de daño durante inspección. | M19: Chat Investigación profunda 8D, 30/09/2026. Experimento en 5 Brooklyn recuperado del historial: flux reprodujo atasco; alcohol no lo reprodujo en esa muestra; observación de tweezer. | N19: https://chatgpt.com/g/g-p-6ab5f35ed9d08191805565e89e7b1a6d/c/6ab7e69c-30b0-83e8-a989-621112ddf261 | O19: Open | Q19: Y
A20: LL-CVEBU-S1-TERMICO | B20: PRODUCT | C20: CVEBU | E20: 22-100214-01 | F20: S1 | I20: Se observó que el calor de retrabajo se propaga por la PCB hasta el botón. La degradación del mecanismo por conducción a través de cobre es una hipótesis contribuyente pendiente de medición. Lección de investigación: medir temperatura e historial de ciclos antes de atribuir el atasco al layout. La distancia en assembly drawing no demuestra aislamiento térmico. | J20: Exposición térmica indirecta y acumulada de S1 durante retrabajo | K20: Evaluar cada producto/revisión por separado. Medir cuerpo y terminal de S1, zona intervenida y referencia PCB; correlacionar con fuerza, recorrido y retorno. No fijar distancia o límite térmico sin especificación y validación. | M20: Chat Estándares IPC Térmicos, 01/10/2026. Observación del usuario y plan experimental propuesto. Productos a comparar: Pictoris, Millenium, Octavio, Brooklyn y Davinci. | N20: https://chatgpt.com/g/g-p-6ab5f35ed9d08191805565e89e7b1a6d/c/6abf35e3-0b6c-83e8-a8c2-defe530ca3f4 | O20: Open | Q20: N
A21: LL-LANCER-CAP-PREICT | B21: PRODUCT | C21: LANCER | E21: 11-101935-01 | I21: Las validaciones reportadas el 01/10/2026 encontraron el mismo síntoma de capacitor antes de ICT, incluida una unidad que nunca pasó por ICT. Esto descarta ICT como causa iniciadora de toda la población. Lección: localizar primero el punto de introducción y comparar por RefDes/circuito y población de origen. La concentración QSFP o diferencia por date code no confirma causalidad. | J21: Condición del capacitor antes de ICT y localización de la primera degradación | K21: Comparar evidencia pre-ICT/post-ICT y trazabilidad por WO, lote y RefDes. No liberar ni cerrar la investigación suponiendo picos ICT o que todos los componentes de un lote deban fallar. | M21: Chat Traducir reporte a inglés / Lancer, 30/09–01/10/2026. Validaciones posteriores descartan ICT como origen. Síntesis del correo: FJZ303626L6 y FJZ303609VF. PN de board y RefDes exactos pendientes. | N21: https://chatgpt.com/c/6abd16d8-6e58-83e8-90e0-5c916d86d0f1 | O21: Open | Q21: Y
A22: LL-VORETJ-PTH-PUENTES | B22: PRODUCT | C22: VoreTJ-48PXPLX | D22: 73-103083-04 | E22: 29-102727-02 | F22: J2/J4/J7/J13 | I22: En Quake/Mobius se reportaron 27 seriales con puentes físicos en conectores, provenientes de distintas WOs/líneas SMT. La ola PTH fue el proceso común observado, pero no se confirmó causa raíz. Lección: definir la población por genealogía de proceso y verificar físicamente el defecto antes de adjudicarlo a una línea SMT o a proveedor. | J22: Ausencia de puentes de soldadura en conectores después de PTH | K22: Inspeccionar las referencias afectadas después de PTH y segregar desde el último serial conforme ante recurrencia. Revalidar receta y controles cuando cambien ola, pallet, producto o parámetros. | M22: Chat Quake/Mobius, 04/08/2026 hora México / 05/08 UTC. Relato de 27 SN; síntesis del historial: PTH P21S1CT1/P21S4CT1 y RefDes J2/J4/J7/J13. Causa raíz pendiente. | O22: Open | Q22: Y
A23: LL-TTM-TDR-RAYONES | B23: PRODUCT | D23: 28-14458-04 | F23: TDR coupon | I23: Se reportaron 400 PCB TTM con rayones en cupones TDR durante descarga AOI. El cupón ensayado fue reportado OK y se discutió aceptación específica condicionada. Lección: proteger el cupón durante manejo y conservar evidencia de integridad/aceptación de la población exacta; un cupón OK no autoriza rayones en lotes futuros ni demuestra por sí solo integridad de todos los circuitos. | J23: Integridad del cupón TDR y del PCB durante descarga/manejo | K23: Proteger el panel/cupón durante manejo AOI. Ante rayón, retener, evaluar alcance y obtener disposición documentada para ese lote. Confirmar board/modelo de uso antes de heredar al producto. | M23: Chat TTM PCB 28-14458-04, 10/08/2026. 400 piezas y cupón probado OK. La síntesis también menciona coupon trace open: cotejar reporte original para conciliar condiciones/poblaciones. | O23: Open | Q23: N
A24: LL-731991908-LAVADO-REIMPRESION | B24: PRODUCT | D24: 73-19919-08 | I24: Para WO 000001289594 se documentaron múltiples intentos de impresión y limpieza manual entre intentos en lugar de lavadora, con residuos/cortos reportados. Lección: una PCB con impresión rechazada debe seguir el método de lavado y verificación aprobado antes de volver a imprimir. No mezclar este caso con intercambio de feeders sin evidencia específica. | J24: PCB limpia y verificada antes de reimpresión de pasta | K24: Segregar PCB con impresión rechazada, enviarla al lavado aprobado y verificar limpieza antes de reintroducirla. Registrar intentos y disposición; detener/escalar si el defecto de impresión se repite. | M24: Chats ICT Short Fail 73-19919-08 / WO 000001289594, 21/08/2026. 890 unidades, 18 afectadas, 873 ICT Pass y 17 pendientes son cifras de momentos/poblaciones por conciliar. No calcular tasa con ellas. | O24: Open | Q24: Y
A25: LL-PRESSFIT-CENTRADO | B25: PRODUCT | F25: P1/P2 | I25: Se reportó asentamiento incompleto de stack connectors por fuerza desigual con fixture descentrado. Se discutieron láser/gage y validación de 100 PCBA; el resumen reporta 0 fallas en VI, 5DX y PCBFT. Lección: controlar centrado y verificar altura/gap después de prensar, además de la primera pieza. PN/modelo sin recuperar y rangos dimensionales contradictorios entre chats: pendiente cotejo del reporte aprobado. | J25: Centrado del fixture y asentamiento completo después de press-fit | K25: Confirmar modelo, PN y especificación vigente antes de publicar. Verificar centrado, soporte, paralelismo y seating mediante gage aprobado. No usar 0.042 in como límite de aceptación. | M25: Chats Stack connectors not fully seated / Improper Seating, 13–25/08/2026. P1/P2 en el reporte final; otro chat menciona M3/M4. La medición 0.042 in y los rangos deben cotejarse con drawing. | O25: Open | Q25: N

Sheet Actions
A1: Action ID | B1: Finding ID | C1: Product | D1: Part Number | E1: Rev | F1: Line | G1: Owner | H1: Action | I1: Due Date | J1: Status | K1: Evidence Link | L1: Closure Note | M1: Active | N1: Component CPN | O1: RefDes | P1: Direct Component Control | Q1: Critical Category | R1: Critical Reason | S1: Critical Source | T1: Critical Condition
A2: ACT-PICTORIS-J73-PNP | B2: LL-PICTORIS-J73 | C2: PICTORIS | D2: 73-103603-05 | E2: B0 | G2: Josué Rangel | H2: Corregir la orientación de J73 en los programas P&P de L13 y L17 según el plano aprobado. | J2: Closed | L2: Cerrado según revisión 8D: se registró la corrección de orientación en P&P. | M2: Y | N2: 27-100137-01 | O2: J73 | P2: Y | Q2: Orientación | R2: Escape previo / riesgo conocido | S2: Queja de cliente / lección 8D | T2: Orientación invertida
A3: ACT-PICTORIS-J73-AOI | B3: LL-PICTORIS-J73 | C3: PICTORIS | D3: 73-103603-05 | E3: B0 | G3: Alberto Cruz | H3: Ajustar AOI y probar una pieza correcta y otra con J73 girado 180° antes de liberar. | J3: Closed | L3: Cerrado según revisión 8D: se probaron piezas con orientación correcta e invertida. | M3: Y | N3: 27-100137-01 | O3: J73 | P3: Y | Q3: Orientación | R3: Escape previo / riesgo conocido | S3: Queja de cliente / lección 8D | T3: Orientación invertida
A4: ACT-PICTORIS-J73-REQUAL | B4: LL-PICTORIS-J73 | C4: PICTORIS | D4: 73-103603-05 | G4: Carlos Martínez | H4: Al calificar o recalificar una línea, revisar orientación P&P, prueba AOI correcto/invertido y primera pieza antes de liberar. | J4: Open | M4: Y | N4: 27-100137-01 | O4: J73 | P4: Y | Q4: Orientación | R4: Escape previo / riesgo conocido | S4: Queja de cliente / lección 8D | T4: Orientación invertida
A5: ACT-PICTORIS-J73-TEST-COVERAGE | B5: LL-PICTORIS-J73 | C5: PICTORIS | D5: 73-103603-05 | G5: David Pacheco | H5: Revisar si las pruebas detectan J73 al revés. No contar la prueba funcional como control de orientación sin evidencia. | J5: Open | M5: Y | N5: 27-100137-01 | O5: J73 | P5: Y | Q5: Orientación | R5: Escape previo / riesgo conocido | S5: Queja de cliente / lección 8D | T5: Orientación invertida
A6: ACT-PICTORIS-WO-PN-REV-BLOCK | B6: LL-PICTORIS-WO-IDENTITY | C6: PICTORIS | D6: 73-103603-05 | G6: Planeación / PM | H6: Agregar un bloqueo para impedir crear o liberar órdenes con número de parte o revisión incorrectos. | J6: Open | M6: Y
A7: ACT-PICTORIS-WO-FIRST-PIECE-ID | B7: LL-PICTORIS-WO-IDENTITY | C7: PICTORIS | D7: 73-103603-05 | G7: Planeación / PM | H7: Antes de producir, confirmar modelo, número de parte y revisión en la primera pieza. Corregir cualquier diferencia en la orden. | J7: Open | M7: Y
A8: ACT-BAYFRONT-BOM-LOADLIST-CHECK | B8: LL-BAYFRONT-BOM-LOADLIST | C8: BAYFRONT | D8: 73-103826-05 | G8: Programación / Calidad | H8: Comparar automáticamente número de parte, posición, cantidad y revisión entre BOM y lista de carga antes de aprobar. | J8: Open | M8: Y
A9: ACT-ARATA-U58-CONFIG-GATE | B9: LL-ARATA-ODM-CONFIG | C9: ARATA | D9: 74-133408-02 | E9: B0 | G9: Planeación / Producto / SMT / ICT | H9: Registrar U58, revisión y documento de cambio en la orden. Completar la revisión conjunta antes de liberar. | J9: Open | M9: Y
A10: ACT-ARATA-ICT-CHANGE-VALIDATION | B10: LL-ARATA-ODM-CONFIG | C10: ARATA | D10: 74-133408-02 | E10: B0 | G10: ICT / Planeación / SMT | H10: Antes de liberar un cambio, confirmar que ICT tenga las pruebas correctas para la configuración física, incluida U602 cuando aplique. | J10: Open | M10: Y
A11: ACT-ARATA-REFDES-CLOSEOUT | B11: LL-ARATA-ODM-CONFIG | C11: ARATA | D11: 74-133408-02 | E11: B0 | G11: SMT / ICT | H11: Antes de liberar la orden, revisar cada posición afectada y confirmar el cambio físico y las pruebas correspondientes. | J11: Open | M11: Y
A12: ACT-TAYLOR-PNP-DEBUG | B12: LL-TAYLOR-LARGE-BODY-CLEARANCE | C12: TAYLOR | G12: Josué Rangel | H12: Revisar las zonas críticas en el modo de ajuste P&P. Confirmar pieza, centrado, posición, ángulo y separación con muestras buenas y malas. | J12: Open | M12: Y
A13: ACT-TAYLOR-AOI-CLEARANCE | B13: LL-TAYLOR-LARGE-BODY-CLEARANCE | C13: TAYLOR | G13: José Cruz | H13: Ajustar AOI para revisar las posiciones críticas con muestras buenas y malas. Si no puede detectarlo, documentar otro método de inspección. | J13: Open | M13: Y
A14: ACT-TAYLOR-AVL-BODY-ENVELOPE | B14: LL-TAYLOR-LARGE-BODY-CLEARANCE | C14: TAYLOR | G14: Carlos Martínez | H14: Limitar las piezas grandes a tamaños aprobados para mantener la separación. Volver a revisar si cambia proveedor o modelo. | J14: Open | M14: Y
A15: ACT-TAYLOR-XRAY-2000 | B15: LL-TAYLOR-LARGE-BODY-CLEARANCE | C15: TAYLOR | H15: Inspeccionar con rayos X las primeras 2,000 piezas de validación y vigilar las zonas críticas. | J15: Monitoring | M15: Y
A16: ACT-NIXIE-PNP-NOZZLE-STANDARD | B16: LL-NIXIE-MIC-SEATING | C16: NIXIE | G16: SMT-P&P | H16: Definir la boquilla y los ajustes P&P del micrófono según la hoja del proveedor. Controlar la presión al colocarlo. | J16: Open | K16: https://chatgpt.com/c/6ab960a3-208c-83e8-8009-8c18a39dd451 | M16: Y
A17: ACT-NIXIE-GETTOP-WK10-SAFELAUNCH | B17: LL-NIXIE-MIC-SEATING | C17: NIXIE | G17: Quality / Carlos Martínez | H17: Durante la validación WK10 / WO1290100, usar solo GETTOP MD-HRA261-H10-2 y mantener MERRY bloqueado. Revisar después de colocar y soldar. | J17: Monitoring | K17: https://chatgpt.com/c/6ab960a3-208c-83e8-8009-8c18a39dd451 | M17: Y
A18: ACT-TUFNELL-HI-BLOCK-TOSHIBA | B18: LL-TUFNELL-DEVIATION-SCOPE-HI | C18: TUFNELL PARK | D18: 73-20247-06 | H18: Bloquear material Toshiba para NGFWBU hasta corregir el alcance de la desviación. La aprobación de CRBU no autoriza su uso en NGFWBU. | J18: Monitoring | M18: Y | N18: 15-102981-01; 15-102981-02 | O18: U23 | P18: Y | S18: Análisis de desviación CRBU / NGFWBU
A19: ACT-TUFNELL-HI-DEVIATION-SCOPE | B19: LL-TUFNELL-DEVIATION-SCOPE-HI | C19: TUFNELL PARK | D19: 73-20247-06 | H19: Antes de aplicar una desviación, confirmar unidad de negocio, producto y orden. Si no coinciden, mantener el bloqueo en SAP. | J19: Open | M19: Y | N19: 15-102981-01; 15-102981-02 | O19: U23 | P19: Y | S19: Análisis de desviación CRBU / NGFWBU
A20: ACT-TUFNELL-LO-BLOCK-TOSHIBA | B20: LL-TUFNELL-DEVIATION-SCOPE-LO | C20: TUFNELL PARK | D20: 73-20249-06 | H20: Bloquear material Toshiba para NGFWBU hasta corregir el alcance de la desviación. La aprobación de CRBU no autoriza su uso en NGFWBU. | J20: Monitoring | M20: Y | N20: 15-102981-01; 15-102981-02 | O20: U23 | P20: Y | S20: Análisis de desviación CRBU / NGFWBU
A21: ACT-TUFNELL-LO-DEVIATION-SCOPE | B21: LL-TUFNELL-DEVIATION-SCOPE-LO | C21: TUFNELL PARK | D21: 73-20249-06 | H21: Antes de aplicar una desviación, confirmar unidad de negocio, producto y orden. Si no coinciden, mantener el bloqueo en SAP. | J21: Open | M21: Y | N21: 15-102981-01; 15-102981-02 | O21: U23 | P21: Y | S21: Análisis de desviación CRBU / NGFWBU
A22: ACT-CHARON-CR95-SOP-VISUAL | B22: LL-CHARON-CR95-POLARITY | C22: CHARON | H22: Agregar una ayuda visual al procedimiento SMT para CR95. Confirmar en producción que la marca verde quede opuesta a la marca de polaridad de la tablilla. | J22: Closed | L22: La revisión posterior indicó que la ayuda visual se cerró durante NPI. La marca verde indica ánodo y va opuesta al silkscreen. | M22: Y | N22: 25-100369-01 | O22: CR95 | P22: Y | Q22: Orientación | R22: Lección aprendida / riesgo conocido | S22: Revisión del caso Charon / correo de polaridad CR95 | T22: Orientación contraria al silkscreen
A23: ACT-PICTORIS-BOTON-FLUX-PROTEGER | B23: LL-PICTORIS-BOTON-FLUX | C23: PICTORIS | H23: No aplicar flux al botón, su cuerpo ni sus aberturas. Cubrir con Kapton toda el área de conectores y proteger el botón sin presionar el actuador. Mantener la protección durante el retrabajo. | J23: Open | M23: Y | N23: 22-100214-01 | O23: S1 | P23: Y | S23: Alerta de calidad CVEBU QAF350 Rev03. Experimento y criterios reportados el 30/09/2026.
A24: ACT-PICTORIS-BOTON-FLUX-REEMPLAZAR | B24: LL-PICTORIS-BOTON-FLUX | C24: PICTORIS | H24: Inspeccionar el botón al 100 % antes y después del retrabajo. Si está húmedo por flux, pegajoso o con residuos, rechazar la unidad y reemplazar el componente completo por el método aprobado. No esperar a que se pegue. La limpieza o el funcionamiento temporal no sustituyen el reemplazo. | J24: Open | M24: Y | N24: 22-100214-01 | O24: S1 | P24: Y | S24: Alerta de calidad CVEBU QAF350 Rev03. Experimento y criterios reportados el 30/09/2026.
A25: ACT-PICTORIS-BOTON-FLUX-VERIFICAR | B25: LL-PICTORIS-BOTON-FLUX | C25: PICTORIS | H25: Después del reemplazo, comprobar limpieza, accionamiento y retorno del botón. Ejecutar la prueba funcional aplicable y registrar el reemplazo y resultado por número de serie antes de liberar la unidad. | J25: Open | M25: Y | N25: 22-100214-01 | O25: S1 | P25: Y | S25: Alerta de calidad CVEBU QAF350 Rev03. Experimento y criterios reportados el 30/09/2026.
A26: ACT-MILLENIUM-BOTON-FLUX-PROTEGER | B26: LL-MILLENIUM-BOTON-FLUX | C26: MILLENIUM | H26: No aplicar flux al botón, su cuerpo ni sus aberturas. Cubrir con Kapton toda el área de conectores y proteger el botón sin presionar el actuador. Mantener la protección durante el retrabajo. | J26: Open | M26: Y | N26: 22-100214-01 | O26: S1 | P26: Y | S26: Alerta de calidad CVEBU QAF350 Rev03. Experimento y criterios reportados el 30/09/2026.
A27: ACT-MILLENIUM-BOTON-FLUX-REEMPLAZAR | B27: LL-MILLENIUM-BOTON-FLUX | C27: MILLENIUM | H27: Inspeccionar el botón al 100 % antes y después del retrabajo. Si está húmedo por flux, pegajoso o con residuos, rechazar la unidad y reemplazar el componente completo por el método aprobado. No esperar a que se pegue. La limpieza o el funcionamiento temporal no sustituyen el reemplazo. | J27: Open | M27: Y | N27: 22-100214-01 | O27: S1 | P27: Y | S27: Alerta de calidad CVEBU QAF350 Rev03. Experimento y criterios reportados el 30/09/2026.
A28: ACT-MILLENIUM-BOTON-FLUX-VERIFICAR | B28: LL-MILLENIUM-BOTON-FLUX | C28: MILLENIUM | H28: Después del reemplazo, comprobar limpieza, accionamiento y retorno del botón. Ejecutar la prueba funcional aplicable y registrar el reemplazo y resultado por número de serie antes de liberar la unidad. | J28: Open | M28: Y | N28: 22-100214-01 | O28: S1 | P28: Y | S28: Alerta de calidad CVEBU QAF350 Rev03. Experimento y criterios reportados el 30/09/2026.
A29: ACT-OCTAVIO-BOTON-FLUX-PROTEGER | B29: LL-OCTAVIO-BOTON-FLUX | C29: OCTAVIO | H29: No aplicar flux al botón, su cuerpo ni sus aberturas. Cubrir con Kapton toda el área de conectores y proteger el botón sin presionar el actuador. Mantener la protección durante el retrabajo. | J29: Open | M29: Y | N29: 22-100214-01 | O29: S1 | P29: Y | S29: Alerta de calidad CVEBU QAF350 Rev03. Experimento y criterios reportados el 30/09/2026.
A30: ACT-OCTAVIO-BOTON-FLUX-REEMPLAZAR | B30: LL-OCTAVIO-BOTON-FLUX | C30: OCTAVIO | H30: Inspeccionar el botón al 100 % antes y después del retrabajo. Si está húmedo por flux, pegajoso o con residuos, rechazar la unidad y reemplazar el componente completo por el método aprobado. No esperar a que se pegue. La limpieza o el funcionamiento temporal no sustituyen el reemplazo. | J30: Open | M30: Y | N30: 22-100214-01 | O30: S1 | P30: Y | S30: Alerta de calidad CVEBU QAF350 Rev03. Experimento y criterios reportados el 30/09/2026.
A31: ACT-OCTAVIO-BOTON-FLUX-VERIFICAR | B31: LL-OCTAVIO-BOTON-FLUX | C31: OCTAVIO | H31: Después del reemplazo, comprobar limpieza, accionamiento y retorno del botón. Ejecutar la prueba funcional aplicable y registrar el reemplazo y resultado por número de serie antes de liberar la unidad. | J31: Open | M31: Y | N31: 22-100214-01 | O31: S1 | P31: Y | S31: Alerta de calidad CVEBU QAF350 Rev03. Experimento y criterios reportados el 30/09/2026.
A32: ACT-BROOKLYN-BOTON-FLUX-PROTEGER | B32: LL-BROOKLYN-BOTON-FLUX | C32: BROOKLYN | H32: No aplicar flux al botón, su cuerpo ni sus aberturas. Cubrir con Kapton toda el área de conectores y proteger el botón sin presionar el actuador. Mantener la protección durante el retrabajo. | J32: Open | M32: Y | N32: 22-100214-01 | O32: S1 | P32: Y | S32: Alerta de calidad CVEBU QAF350 Rev03. Experimento y criterios reportados el 30/09/2026.
A33: ACT-BROOKLYN-BOTON-FLUX-REEMPLAZAR | B33: LL-BROOKLYN-BOTON-FLUX | C33: BROOKLYN | H33: Inspeccionar el botón al 100 % antes y después del retrabajo. Si está húmedo por flux, pegajoso o con residuos, rechazar la unidad y reemplazar el componente completo por el método aprobado. No esperar a que se pegue. La limpieza o el funcionamiento temporal no sustituyen el reemplazo. | J33: Open | M33: Y | N33: 22-100214-01 | O33: S1 | P33: Y | S33: Alerta de calidad CVEBU QAF350 Rev03. Experimento y criterios reportados el 30/09/2026.
A34: ACT-BROOKLYN-BOTON-FLUX-VERIFICAR | B34: LL-BROOKLYN-BOTON-FLUX | C34: BROOKLYN | H34: Después del reemplazo, comprobar limpieza, accionamiento y retorno del botón. Ejecutar la prueba funcional aplicable y registrar el reemplazo y resultado por número de serie antes de liberar la unidad. | J34: Open | M34: Y | N34: 22-100214-01 | O34: S1 | P34: Y | S34: Alerta de calidad CVEBU QAF350 Rev03. Experimento y criterios reportados el 30/09/2026.
... A37: ACT-DAVINCI-BOTON-FLUX-VERIFICAR | B37: LL-DAVINCI-BOTON-FLUX | C37: DAVINCI | H37: Después del reemplazo, comprobar limpieza, accionamiento y retorno del botón. Ejecutar la prueba funcional aplicable y registrar el reemplazo y resultado por número de serie antes de liberar la unidad. | J37: Open | M37: Y | N37: 22-100214-01 | O37: S1 | P37: Y | S37: Alerta de calidad CVEBU QAF350 Rev03. Experimento y criterios reportados el 30/09/2026.
A38: ACT-HEIMDALL-CLIP-REWORK | B38: LL-HEIMDALL-CLIP-CUSTODY | C38: HEIMDALL | D38: 73-103459-02 | E38: A0 | H38: Retrabajar la población afectada instalando el clip P/N 700-136420-01 en J3-J8 mediante el procedimiento aprobado. Verificar presencia, fijación, limpieza de la superficie dorada de contacto y ejecutar 100 % X-Ray en J3-J8 antes de liberar cada unidad. | J38: Open | L38: Contención / Producto | M38: Y | N38: 700-136420-01 | O38: J3-J8 | P38: Y | S38: PCAMAP 61-107350-02 · investigación del clip Heimdall
A39: ACT-HEIMDALL-CLIP-PROCESS-DEFINITION | B39: LL-HEIMDALL-CLIP-CUSTODY | C39: HEIMDALL | D39: 73-103459-02 | E39: A0 | H39: Definir y documentar de manera explícita dónde se instala el clip 700-136420-01, qué proceso acepta su custodia y cuál es el método de ensamble. Actualizar los documentos aplicables de proceso (lista de carga/programa, stencil cuando aplique, WI/SOP y criterio de inspección) para la revisión 73-103459-02 A0. | J39: Open | L39: Implementación de proceso | M39: Y | N39: 700-136420-01 | O39: J3-J8 | P39: Y | S39: PCAMAP 61-107350-02 · investigación del clip Heimdall
A40: ACT-HEIMDALL-PCAMAP-CUSTODY-GATE | B40: LL-HEIMDALL-CLIP-CUSTODY | C40: HEIMDALL | D40: 73-103459-02 | E40: A0 | H40: Implementar el PCAMAP Reference Custody Gate: todo P/N afectado por ECN que tenga RefDes o relación física con la PCBA debe tener destino de manufactura, owner, método de ensamble, documento de control y método de verificación antes de liberar. La falta de palabras SMT/PTH/press-fit en la descripción no permite cerrar el ítem como N/A. | J40: Open | L40: Sistema / Prevención | M40: Y | N40: 700-136420-01 | O40: J3-J8 | P40: Y | S40: PCAMAP 61-107350-02 · investigación del clip Heimdall
A41: ACT-HEIMDALL-ECN-CFT-REVIEW | B41: LL-HEIMDALL-CLIP-CUSTODY | C41: HEIMDALL | D41: 73-103459-02 | E41: A0 | H41: Incorporar esta revisión como punto obligatorio en las juntas de ECN/ECO. El CFT debe revisar activamente el delta de BOM/PCAMAP/drawing, asignar custodia por referencia y completar el checklist antes de aprobar la implementación. Una referencia sin owner o método definido permanece UNRESOLVED / HOLD. | J41: Open | L41: Sistema / ECN | M41: Y | N41: 700-136420-01 | O41: J3-J8 | P41: Y | S41: PCAMAP 61-107350-02 · investigación del clip Heimdall
A42: ACT-HEIMDALL-CISCO-HEADUP | B42: LL-HEIMDALL-CLIP-CUSTODY | C42: HEIMDALL | D42: 73-103459-02 | E42: A0 | H42: Cuando el CFT no pueda determinar de forma concluyente dónde va una referencia, quién la ensambla o cómo debe implementarse con la documentación disponible, escalar un Head-Up / Technical Clarification al grupo de Cisco antes de liberar la construcción. No cerrar por suposición, prefijo de RefDes o descripción del material. | J42: Open | L42: Escalación | M42: Y | N42: 700-136420-01 | O42: J3-J8 | P42: Y | S42: PCAMAP 61-107350-02 · investigación del clip Heimdall
A43: ACT-HEIMDALL-VECTOR-EXPOSURE | B43: LL-HEIMDALL-CLIP-CUSTODY | C43: HEIMDALL | D43: 73-103459-02 | E43: A0 | H43: Agregar en VECTOR el control de custodia por referencia y el cálculo de exposición desde la fecha de efectividad del cambio hasta la fecha de asignación/corrección: WOs, seriales, líneas, días de exposición y población potencial de retrabajo. | J43: Open | L43: Sistema / VECTOR | M43: Y | N43: 700-136420-01 | O43: J3-J8 | P43: Y | S43: PCAMAP 61-107350-02 · investigación del clip Heimdall
A44: ACT-HEIMDALL-CUSTODY-EFFECTIVENESS | B44: LL-HEIMDALL-CLIP-CUSTODY | C44: HEIMDALL | D44: 73-103459-02 | E44: A0 | H44: Verificar efectividad durante los siguientes 10 ECN aplicables o 90 días: 100 % de referencias agregadas/cambiadas con proceso, owner, método, documento y evidencia de verificación definidos antes de release; cero referencias cerradas como N/A sin justificación documentada y cero liberaciones con estatus UNRESOLVED. | J44: Open | L44: Efectividad | M44: Y | N44: 700-136420-01 | O44: J3-J8 | P44: Y | S44: PCAMAP 61-107350-02 · investigación del clip Heimdall
A45: ACT-GREENFORD-AOI-MARCADO-REFERENCIA | B45: LL-GREENFORD-AOI-MARCADO | C45: GREENFORD | D45: 73-104532-01 | H45: Obtener y publicar la referencia oficial de aceptación por CPN/programación, con foto del marcado permitido, fuente de autorización y revisión accesible a los tres turnos. | J45: Open | K45: https://chatgpt.com/g/g-p-6abe462c09308191916f0eed68e0b198/c/6abe43f8-a784-83e8-9f10-f6d0d31564a3 | L45: Propuesta documentada. Ejecución y cierre sin confirmar. Para cerrar: Referencia aprobada y disponible en punto de uso; pieza permitida y pieza no autorizada identificadas. | M45: Y | N45: 17-103689-02; 17-103691-01; 17-102460-07
A46: ACT-GREENFORD-AOI-MARCADO-DESPLIEGUE | B46: LL-GREENFORD-AOI-MARCADO | C46: GREENFORD | D46: 73-104532-01 | H46: Buscar todos los modelos/librerías que usan los CPN afectados. Registrar versión antes/después, guardar el cambio y validar cada librería impactada con muestra permitida y no permitida. | J46: Open | K46: https://chatgpt.com/g/g-p-6abe462c09308191916f0eed68e0b198/c/6abe43f8-a784-83e8-9f10-f6d0d31564a3 | L46: Propuesta documentada. Ejecución y cierre sin confirmar. Para cerrar: Matriz de impacto completa, revisiones guardadas y evidencia de aceptación/rechazo en cada librería aplicable. | M46: Y | N46: 17-103689-02; 17-103691-01; 17-102460-07
A47: ACT-GREENFORD-AOI-MARCADO-SIGUIENTE-CORRIDA | B47: LL-GREENFORD-AOI-MARCADO | C47: GREENFORD | D47: 73-104532-01 | H47: En la siguiente corrida tras cambio de modelo/línea, verificar que la librería cargada coincide con la revisión aprobada y repetir el reto OCV/OCR. | J47: Open | K47: https://chatgpt.com/g/g-p-6abe462c09308191916f0eed68e0b198/c/6abe43f8-a784-83e8-9f10-f6d0d31564a3 | L47: Propuesta documentada. Ejecución y cierre sin confirmar. Para cerrar: Registro de máquina, modelo, revisión cargada y resultado del reto en la siguiente corrida. | M47: Y | N47: 17-103689-02; 17-103691-01; 17-102460-07
A48: ACT-GREENFORD-AOI-MARCADO-HISTORIAL | B48: LL-GREENFORD-AOI-MARCADO | C48: GREENFORD | D48: 73-104532-01 | H48: Revisar logs, usuarios, timestamps y revisiones para demostrar dónde se guardó o no se propagó el cambio. Usar esa evidencia en el RCCA de recurrencia. | J48: Open | K48: https://chatgpt.com/g/g-p-6abe462c09308191916f0eed68e0b198/c/6abe43f8-a784-83e8-9f10-f6d0d31564a3 | L48: Propuesta documentada. Ejecución y cierre sin confirmar. Para cerrar: Trazabilidad de cambios y población de librerías afectadas; causa sistémica sustentada sin atribuir intención al personal. | M48: Y | N48: 17-103689-02; 17-103691-01; 17-102460-07
A49: ACT-BROOKLYN-S1-ACCIONAMIENTO-WI | B49: LL-BROOKLYN-S1-ACCIONAMIENTO | C49: BROOKLYN | D49: 73-102022-02 | H49: Actualizar el método de verificación de S1: accionamiento controlado según WI, sin pinza puntiaguda ni empuje lateral. Registrar condición antes y después de intervenir. | J49: Open | K49: https://chatgpt.com/g/g-p-6ab5f35ed9d08191805565e89e7b1a6d/c/6ab7e69c-30b0-83e8-a989-621112ddf261 | L49: Propuesta documentada. Ejecución y cierre sin confirmar. Para cerrar: WI aprobada y demostración de que el método verifica retorno sin dañar guías ni actuador. | M49: Y | N49: 22-100214-01 | O49: S1 | P49: Y | S49: Chat Investigación profunda 8D, 30/09/2026. Experimento en 5 Brooklyn recuperado del historial: flux reprodujo atasco; alcohol no lo reprodujo en esa muestra; observación de tweezer.
A50: ACT-BROOKLYN-S1-ACCIONAMIENTO-FIXTURE | B50: LL-BROOKLYN-S1-ACCIONAMIENTO | C50: BROOKLYN | D50: 73-102022-02 | H50: Revisar alineación, altura/recorrido, contacto y desgaste del actuador de test. Validar repetibilidad del accionamiento sin sobrecarga ni fuerza lateral. | J50: Open | K50: https://chatgpt.com/g/g-p-6ab5f35ed9d08191805565e89e7b1a6d/c/6ab7e69c-30b0-83e8-a989-621112ddf261 | L50: Propuesta documentada. Ejecución y cierre sin confirmar. Para cerrar: Comparación antes/después y evidencia funcional/mecánica del método aprobado. No cerrar por un solo accionamiento correcto. | M50: Y | N50: 22-100214-01 | O50: S1 | P50: Y | S50: Chat Investigación profunda 8D, 30/09/2026. Experimento en 5 Brooklyn recuperado del historial: flux reprodujo atasco; alcohol no lo reprodujo en esa muestra; observación de tweezer.
A51: ACT-CVEBU-S1-TERMICO-TERMOPARES | B51: LL-CVEBU-S1-TERMICO | C51: CVEBU | H51: Instrumentar cuerpo y terminal/pad de S1, punto de retrabajo y zona de referencia. Registrar temperatura pico, tiempo y ciclos con el mismo retrabajo normalizado por producto. | J51: Open | K51: https://chatgpt.com/g/g-p-6ab5f35ed9d08191805565e89e7b1a6d/c/6abf35e3-0b6c-83e8-a8c2-defe530ca3f4 | L51: Propuesta documentada. Ejecución y cierre sin confirmar. Para cerrar: Curvas medidas por producto/revisión y parámetros reales del retrabajo; límites cotejados con especificación particular del componente. | M51: Y | N51: 22-100214-01 | O51: S1 | P51: Y | S51: Chat Estándares IPC Térmicos, 01/10/2026. Observación del usuario y plan experimental propuesto. Productos a comparar: Pictoris, Millenium, Octavio, Brooklyn y Davinci.
A52: ACT-CVEBU-S1-TERMICO-COBRE | B52: LL-CVEBU-S1-TERMICO | C52: CVEBU | H52: Revisar CAD/Gerber para identificar planos, vías y caminos de cobre entre zonas de retrabajo y S1. Comparar puntos a distancia similar con conectividad térmica diferente. | J52: Open | K52: https://chatgpt.com/g/g-p-6ab5f35ed9d08191805565e89e7b1a6d/c/6abf35e3-0b6c-83e8-a8c2-defe530ca3f4 | L52: Propuesta documentada. Ejecución y cierre sin confirmar. Para cerrar: Mapas de cobre y correlación con temperaturas medidas; modelo/PN/revisión y aplicabilidad confirmados antes de publicar. | M52: Y | N52: 22-100214-01 | O52: S1 | P52: Y | S52: Chat Estándares IPC Térmicos, 01/10/2026. Observación del usuario y plan experimental propuesto. Productos a comparar: Pictoris, Millenium, Octavio, Brooklyn y Davinci.
A53: ACT-CVEBU-S1-TERMICO-MECANICA | B53: LL-CVEBU-S1-TERMICO | C53: CVEBU | H53: Medir fuerza, recorrido y retorno antes y después de ciclos térmicos controlados, separando calor, contaminación y método de accionamiento. | J53: Open | K53: https://chatgpt.com/g/g-p-6ab5f35ed9d08191805565e89e7b1a6d/c/6abf35e3-0b6c-83e8-a8c2-defe530ca3f4 | L53: Propuesta documentada. Ejecución y cierre sin confirmar. Para cerrar: Datos que confirmen o descarten degradación térmica. Actualizar D4/PFMEA solo con mecanismo demostrado y documento aprobado. | M53: Y | N53: 22-100214-01 | O53: S1 | P53: Y | S53: Chat Estándares IPC Térmicos, 01/10/2026. Observación del usuario y plan experimental propuesto. Productos a comparar: Pictoris, Millenium, Octavio, Brooklyn y Davinci.
A54: ACT-LANCER-CAP-PREICT-TRAZABILIDAD | B54: LL-LANCER-CAP-PREICT | C54: LANCER | H54: Consolidar población con evidencia pre-ICT/post-ICT por serial, WO, lote/date code, estación previa y RefDes. Separar unidades nunca probadas en ICT. | J54: Open | K54: https://chatgpt.com/c/6abd16d8-6e58-83e8-90e0-5c916d86d0f1 | L54: Propuesta documentada. Ejecución y cierre sin confirmar. Para cerrar: Evidencia por serial que ubique la primera detección y preserve denominadores de cada población. | M54: Y | N54: 11-101935-01
A55: ACT-LANCER-CAP-PREICT-MECANISMO | B55: LL-LANCER-CAP-PREICT | C55: LANCER | H55: Comparar referencias QSFP falladas con referencias sanas del mismo PN. Revisar SMT/reflow, historial de manejo/retrabajo y exposiciones eléctricas anteriores a ICT. | J55: Open | K55: https://chatgpt.com/c/6abd16d8-6e58-83e8-90e0-5c916d86d0f1 | L55: Propuesta documentada. Ejecución y cierre sin confirmar. Para cerrar: Mecanismo reproducido o descartado mediante comparación controlada; sin atribuir causalidad solo a una correlación. | M55: Y | N55: 11-101935-01
A56: ACT-LANCER-CAP-PREICT-ACTUALIZAR-RCCA | B56: LL-LANCER-CAP-PREICT | C56: LANCER | H56: Actualizar la investigación y comunicación con la evidencia pre-ICT. Retirar ICT como causa iniciadora de toda la población y mantener abierto el mecanismo de degradación. | J56: Open | K56: https://chatgpt.com/c/6abd16d8-6e58-83e8-90e0-5c916d86d0f1 | L56: Propuesta documentada. Ejecución y cierre sin confirmar. Para cerrar: RCCA refleja las validaciones realizadas, mecanismo pendiente y población confirmada; sin cierre causal por descarte aislado. | M56: Y | N56: 11-101935-01
A57: ACT-VORETJ-PTH-PUENTES-CONTENCION | B57: LL-VORETJ-PTH-PUENTES | C57: VoreTJ-48PXPLX | D57: 73-103083-04 | H57: Implementar inspección 100 % post-PTH de los conectores afectados. Ante el primer puente, detener, segregar desde el último serial bueno y registrar alcance por WO/serial. | J57: Open | L57: Propuesta documentada. Ejecución y cierre sin confirmar. Para cerrar: Lista de población y resultados por serial; última unidad buena identificada y autorización de reinicio documentada. | M57: Y | N57: 29-102727-02 | O57: J2/J4/J7/J13 | P57: Y | S57: Chat Quake/Mobius, 04/08/2026 hora México / 05/08 UTC. Relato de 27 SN; síntesis del historial: PTH P21S1CT1/P21S4CT1 y RefDes J2/J4/J7/J13. Causa raíz pendiente.
A58: ACT-VORETJ-PTH-PUENTES-OLA | B58: LL-VORETJ-PTH-PUENTES | C58: VoreTJ-48PXPLX | D58: 73-103083-04 | H58: Revisar receta, flux, preheat, conveyor, ola, pallet y terminales. Comparar condiciones de unidades con y sin puentes y validar el cambio seleccionado. | J58: Open | L58: Propuesta documentada. Ejecución y cierre sin confirmar. Para cerrar: Comparativo y corrida controlada que sustenten el mecanismo y efectividad del control. | M58: Y | N58: 29-102727-02 | O58: J2/J4/J7/J13 | P58: Y | S58: Chat Quake/Mobius, 04/08/2026 hora México / 05/08 UTC. Relato de 27 SN; síntesis del historial: PTH P21S1CT1/P21S4CT1 y RefDes J2/J4/J7/J13. Causa raíz pendiente.
A59: ACT-TTM-TDR-RAYONES-MANEJO | B59: LL-TTM-TDR-RAYONES | D59: 28-14458-04 | H59: Implementar separación con film y método de manejo que evite contacto/roce en cupones durante descarga AOI. Revisar punto físico de generación del rayón. | J59: Open | L59: Propuesta documentada. Ejecución y cierre sin confirmar. Para cerrar: WI/método aprobado y evidencia de descarga sin rayones en validación. | M59: Y | O59: TDR coupon
A60: ACT-TTM-TDR-RAYONES-DISPOSICION | B60: LL-TTM-TDR-RAYONES | D60: 28-14458-04 | H60: Conciliar resultados TDR, condición de cupones y alcance del daño. Registrar lote, date code, cantidad, embarque y aceptación específica del cliente antes de liberar la población. | J60: Open | L60: Propuesta documentada. Ejecución y cierre sin confirmar. Para cerrar: Disposición aprobada de la población exacta, trazabilidad y resolución de discrepancias del reporte. | M60: Y | O60: TDR coupon
A61: ACT-731991908-LAVADO-REIMPRESION-LAVADO | B61: LL-731991908-LAVADO-REIMPRESION | D61: 73-19919-08 | H61: Reforzar la ruta de lavado aprobada para PCBs con impresión rechazada y verificar limpieza antes de reimpresión. Evitar sustituir lavadora por limpieza manual no autorizada. | J61: Open | L61: Acción documentada. Cierre sin confirmar. Para cerrar: Registros de lavado/verificación y cumplimiento de WI en la siguiente corrida aplicable. | M61: Y
A62: ACT-731991908-LAVADO-REIMPRESION-BUFFER | B62: LL-731991908-LAVADO-REIMPRESION | D62: 73-19919-08 | H62: Crear buffer identificado y control de trazabilidad para separar PCBs pendientes de lavado, limpias y autorizadas para reimpresión. | J62: Open | L62: Acción documentada. Cierre sin confirmar. Para cerrar: Separación física y registro que impidan regresar una unidad pendiente de lavado a impresora. | M62: Y
A63: ACT-731991908-LAVADO-REIMPRESION-REINCIDENCIA | B63: LL-731991908-LAVADO-REIMPRESION | D63: 73-19919-08 | H63: Entrenar en Stop, Call and Wait ante impresión repetidamente rechazada. Conciliar población afectada y verificar efectividad en la siguiente corrida. | J63: Open | L63: Acción documentada. Cierre sin confirmar. Para cerrar: Entrenamiento y auditoría de ruta; conteos por estación reconciliados, sin repetir residuos/cortos asociados. | M63: Y
A64: ACT-PRESSFIT-CENTRADO-ALINEACION | B64: LL-PRESSFIT-CENTRADO | H64: Implementar y validar láser/referencia de centrado para el fixture, verificando soporte, paralelismo y contacto uniforme bajo el dado. | J64: Open | L64: Propuesta documentada. Ejecución y cierre sin confirmar. Para cerrar: Producto y fixture identificados, alineación controlada y evidencia de distribución/asentamiento conforme. | M64: Y | O64: P1/P2 | P64: Y | S64: Chats Stack connectors not fully seated / Improper Seating, 13–25/08/2026. P1/P2 en el reporte final; otro chat menciona M3/M4. La medición 0.042 in y los rangos deben cotejarse con drawing.
A65: ACT-PRESSFIT-CENTRADO-GAGE | B65: LL-PRESSFIT-CENTRADO | H65: Validar gage post-pressfit para medir seating/gap según drawing aprobado. Definir en WI reacción ante pins elevados o asentamiento incompleto. | J65: Open | L65: Propuesta documentada. Ejecución y cierre sin confirmar. Para cerrar: Gage y criterio aprobados con muestras conformes/no conformes; discrepancias dimensionales resueltas. | M65: Y | O65: P1/P2 | P65: Y | S65: Chats Stack connectors not fully seated / Improper Seating, 13–25/08/2026. P1/P2 en el reporte final; otro chat menciona M3/M4. La medición 0.042 in y los rangos deben cotejarse con drawing.
A66: ACT-PRESSFIT-CENTRADO-EFECTIVIDAD | B66: LL-PRESSFIT-CENTRADO | H66: Cotejar registros de las 100 PCBA reportadas con VI/5DX/PCBFT y el plan AOI 20 %. Confirmar qué controles quedaron instalados y cuáles siguen propuestos. | J66: Open | L66: Propuesta documentada. Ejecución y cierre sin confirmar. Para cerrar: Reporte por población/prueba y evidencia del control permanente; no cerrar láser por el resultado de contención. | M66: Y | O66: P1/P2 | P66: Y | S66: Chats Stack connectors not fully seated / Improper Seating, 13–25/08/2026. P1/P2 en el reporte final; otro chat menciona M3/M4. La medición 0.042 in y los rangos deben cotejarse con drawing.
A67: ACT-NIXIE-MIC-SEATING-STENCIL-DOE | B67: LL-NIXIE-MIC-SEATING | C67: NIXIE | H67: Ejecutar DOE de geometrías de aperturas del aro discutidas: comparar stencil actual de 3 gajos con alternativas segmentadas/semiabiertas, manteniendo criterios de voids y volumen. No adoptar ring completo solo para eliminar beads. | J67: Open | K67: https://chatgpt.com/c/6ab960a3-208c-83e8-8009-8c18a39dd451 | L67: Propuesta documentada. Ejecución y cierre sin confirmar. Para cerrar: Datos por condición de impresión/reflow, beads internas/externas, tilt y voids; diseño seleccionado y aprobado. | M67: Y
A68: ACT-NIXIE-MIC-SEATING-CORRELACION-ACUSTICA | B68: LL-NIXIE-MIC-SEATING | C68: NIXIE | H68: Correlacionar RX de bead/tilt/voids y coplanaridad con sensibilidad dBFS a 94 dBSPL y respuesta a 1/3.15/10 kHz, según límites aprobados para el producto. | J68: Open | K68: https://chatgpt.com/c/6ab960a3-208c-83e8-8009-8c18a39dd451 | L68: Propuesta documentada. Ejecución y cierre sin confirmar. Para cerrar: Resultados de unidades conformes/no conformes que confirmen o descarten el mecanismo; puerto alineado/libre y criterio acústico documentados. | M68: Y
A69: ACT-NIXIE-MIC-SEATING-CONTROL-PLAN | B69: LL-NIXIE-MIC-SEATING | C69: NIXIE | H69: Actualizar WI/PFMEA/Control Plan con los límites y método de inspección/prueba validados tras DOE. Incorporar reacción ante levantamiento y pérdida acústica. | J69: Open | K69: https://chatgpt.com/c/6ab960a3-208c-83e8-8009-8c18a39dd451 | L69: Propuesta documentada. Ejecución y cierre sin confirmar. Para cerrar: Documentos aprobados y prueba de efectividad de la nueva condición; no publicar mecanismo causal antes de verificarlo. | M69: Y
A70: ACT-PICTORIS-J9-SOP-YOKOTEN | C70: PICTORIS | D70: 73-103603-05 | G70: Procesos | H70: Revisar el control definido antes de liberar producción. Integrar el control aprobado en SOP y SMTinel Yokoten. | J70: Open | L70: Cerrar cuando la SOP/ayuda visual esté aprobada e implementada. Al cerrar, conservar J9 en Yokoten como Histórico controlado. | M70: Y | N70: 29-103310-01 | O70: J9 | P70: Y | Q70: Daño físico | R70: Condición detectada al llegar a FVN | S70: FVN | T70: Terminales levantadas
A71: ACT-PICTORIS-J73-SOP-YOKOTEN | B71: LL-PICTORIS-J73 | C71: PICTORIS | D71: 73-103603-05 | G71: Procesos | H71: Integrar en SOP/ayuda visual el control de orientación de J73: cuerpo blanco hacia pin 1; no usar el triángulo como guía. Mantener la referencia visible en SMTinel Yokoten. | J71: Open | L71: Cerrar cuando la SOP/ayuda visual esté aprobada e implementada. Al cerrar, conservar J73 en Yokoten como Histórico controlado. | M71: Y | N71: 27-100137-01 | O71: J73 | P71: Y | Q71: Orientación | R71: Escape previo / riesgo conocido | S71: Queja de cliente / lección 8D | T71: Orientación invertida
A72: ACT-PICTORIS-J8-SOP-YOKOTEN | C72: PICTORIS | D72: 73-103603-05 | G72: Procesos | H72: Aplicar el control definido por Procesos / SOP antes de liberar producción y mantener la referencia visible en SMTinel Yokoten. | J72: Open | L72: Cerrar cuando el control de J8 quede definido, aprobado e implementado. Al cerrar, conservar J8 en Yokoten como Histórico controlado. | M72: Y | N72: 27-100137-01 | O72: J8 | P72: Y | Q72: Otro | R72: Acción directa sobre componente | S72: Action Tracker | T72: Referencia crítica
A73: ACT-BROOKLYN-J59-SOP-YOKOTEN | C73: BROOKLYN | D73: 73-102022-02 | G73: Procesos | H73: Integrar en SOP/ayuda visual el control de orientación de J59 y mantener la referencia visible en SMTinel Yokoten antes de liberar producción. | J73: Open | L73: Cerrar cuando la SOP/ayuda visual esté aprobada e implementada. Al cerrar, conservar J59 en Yokoten como Histórico controlado. | M73: Y | N73: 29 105251 01 | O73: J59 | P73: Y | Q73: Orientación | R73: Escape previo / riesgo conocido | S73: 8D Brooklyn J59 / Action Tracker | T73: Orientación invertida

Sheet Critical Characteristics
A1: CC ID | B1: Scope | C1: Product | D1: Part Number | E1: Rev | F1: Line | G1: Component CPN | H1: RefDes | I1: Characteristic | J1: Control / Detection | K1: Migration Requirement | L1: Source | M1: Owner | N1: Active
A2: CC-PICTORIS-J73 | B2: PRODUCT | C2: PICTORIS | D2: 73-103603-05 | G2: 27-100137-01 | H2: J73 | I2: Orientación de J73. Cuerpo blanco hacia pin 1. No usar el triángulo como guía. | J2: Revisar orientación en P&P y AOI. Confirmar primera pieza. | K2: Repetir la prueba de orientación al calificar o recalificar la línea. | L2: Queja de cliente / lección aprendida | M2: Josué Rangel / Alberto Cruz / Carlos Martínez | N2: Y
A3: CC-PICTORIS-WO-IDENTITY | B3: PRODUCT | C3: PICTORIS | D3: 73-103603-05 | H3: WO / First Piece | I3: Número de parte y revisión correctos. | J3: Validar ambos datos en la orden y en la primera pieza. | K3: Detener la orden si el número de parte o la revisión no coincide. | L3: Control de configuración · EVT-08 / EVT-09 | M3: Planeación / PM | N3: Y
A4: CC-BAYFRONT-BOM-LOADLIST | B4: PRODUCT | C4: BAYFRONT | D4: 73-103826-05 | H4: BOM / Load List | I4: Coincidencia de parte, posición, cantidad y revisión. | J4: Comparar BOM liberada contra lista de carga antes de liberar. | K4: No liberar si hay diferencias. | L4: Control de configuración · EVT-01 | M4: Programación / Calidad | N4: Y
A5: CC-ARATA-ODM-CONFIG | B5: REVISION | C5: ARATA | D5: 74-133408-02 | E5: B0 | H5: U58 / impacted RefDes | I5: Configuración ODM: U58, revisión y cambio aplicado. | J5: Confirmar orden, configuración física SMT y pruebas ICT. | K5: Volver a revisar si cambia U58, la revisión o las pruebas afectadas. | L5: Control de configuración · EVT-02 / EVT-03 / EVT-04 | M5: Planeación / Producto / SMT / ICT | N5: Y
A6: CC-TAYLOR-CLEARANCE | B6: PRODUCT | C6: TAYLOR | H6: C69_B/C4_B; C267/C268; C280/C282/C283/C284/C274/C67/C70 | I6: Separación mínima entre componentes y tamaño aprobado. | J6: Revisar tamaño, colocación y separación después de soldar. Usar AOI u otra inspección aprobada. | K6: Revisar de nuevo si cambia proveedor, pieza, boquilla o programa. | L6: Caso Taylor / registro SMTinel | M6: Carlos Martínez / Josué Rangel / José Cruz | N6: Y
A7: CC-NIXIE-MIC-SEATING | B7: PRODUCT | C7: NIXIE | H7: Microphone | I7: Micrófono asentado. Bolas de soldadura sin desplazamiento. | J7: Usar boquilla y ajustes aprobados. Revisar después de colocar y soldar. | K7: Revalidar si cambia proveedor, boquilla o programa. | L7: Caso NIXIE Q1WK08 / WK10 | M7: SMT-P&P / Carlos Martínez | N7: Y
A8: CC-TUFNELL-DEVIATION-SCOPE-HI | B8: PRODUCT | C8: TUFNELL PARK | D8: 73-20247-06 | G8: 15-102981-01; 15-102981-02 | H8: U23 | I8: La aprobación de material solo aplica al producto y orden indicados. | J8: Revisar material, producto y orden contra SAP y la desviación. | K8: No permitir excepciones fuera del alcance aprobado. | L8: Análisis de desviación CRBU / NGFWBU | N8: Y
A9: CC-TUFNELL-DEVIATION-SCOPE-LO | B9: PRODUCT | C9: TUFNELL PARK | D9: 73-20249-06 | G9: 15-102981-01; 15-102981-02 | H9: U23 | I9: La aprobación de material solo aplica al producto y orden indicados. | J9: Revisar material, producto y orden contra SAP y la desviación. | K9: No permitir excepciones fuera del alcance aprobado. | L9: Análisis de desviación CRBU / NGFWBU | N9: Y
A10: CC-CHARON-CR95-POLARITY | B10: PRODUCT | C10: CHARON | G10: 25-100369-01 | H10: CR95 | I10: Orientación de CR95. La marca verde indica el ánodo. | J10: Revisar con la ayuda visual aprobada. La marca verde va opuesta al silkscreen. | K10: Confirmar la orientación al iniciar en una línea nueva o recalificar. | L10: Revisión Charon / correo de polaridad CR95 | N10: Y
A11: CC-PICTORIS-BOTON-FLUX | B11: PRODUCT | C11: PICTORIS | I11: Botón seco, sin flux ni pegajosidad, con accionamiento y retorno libres. | J11: Proteger el botón y toda el área de conectores con Kapton durante el retrabajo. Inspeccionar al 100 %. Rechazar y reemplazar ante residuos o pegajosidad, aunque el botón aún accione. Para probarlo, usar solo el dedo. No usar pinzas puntiagudas. | K11: Aplicar estos controles en cada línea nueva o recalificación del producto. Confirmar que el personal conoce el criterio de reemplazo y verificar función después de cambiar el componente. | L11: Alerta de calidad CVEBU QAF350 Rev03. Experimento y criterios reportados el 30/09/2026. | N11: Y
A12: CC-MILLENIUM-BOTON-FLUX | B12: PRODUCT | C12: MILLENIUM | I12: Botón seco, sin flux ni pegajosidad, con accionamiento y retorno libres. | J12: Proteger el botón y toda el área de conectores con Kapton durante el retrabajo. Inspeccionar al 100 %. Rechazar y reemplazar ante residuos o pegajosidad, aunque el botón aún accione. Para probarlo, usar solo el dedo. No usar pinzas puntiagudas. | K12: Aplicar estos controles en cada línea nueva o recalificación del producto. Confirmar que el personal conoce el criterio de reemplazo y verificar función después de cambiar el componente. | L12: Alerta de calidad CVEBU QAF350 Rev03. Experimento y criterios reportados el 30/09/2026. | N12: Y
A13: CC-OCTAVIO-BOTON-FLUX | B13: PRODUCT | C13: OCTAVIO | I13: Botón seco, sin flux ni pegajosidad, con accionamiento y retorno libres. | J13: Proteger el botón y toda el área de conectores con Kapton durante el retrabajo. Inspeccionar al 100 %. Rechazar y reemplazar ante residuos o pegajosidad, aunque el botón aún accione. Para probarlo, usar solo el dedo. No usar pinzas puntiagudas. | K13: Aplicar estos controles en cada línea nueva o recalificación del producto. Confirmar que el personal conoce el criterio de reemplazo y verificar función después de cambiar el componente. | L13: Alerta de calidad CVEBU QAF350 Rev03. Experimento y criterios reportados el 30/09/2026. | N13: Y
A14: CC-BROOKLYN-BOTON-FLUX | B14: PRODUCT | C14: BROOKLYN | I14: Botón seco, sin flux ni pegajosidad, con accionamiento y retorno libres. | J14: Proteger el botón y toda el área de conectores con Kapton durante el retrabajo. Inspeccionar al 100 %. Rechazar y reemplazar ante residuos o pegajosidad, aunque el botón aún accione. Para probarlo, usar solo el dedo. No usar pinzas puntiagudas. | K14: Aplicar estos controles en cada línea nueva o recalificación del producto. Confirmar que el personal conoce el criterio de reemplazo y verificar función después de cambiar el componente. | L14: Alerta de calidad CVEBU QAF350 Rev03. Experimento y criterios reportados el 30/09/2026. | N14: Y
A15: CC-DAVINCI-BOTON-FLUX | B15: PRODUCT | C15: DAVINCI | I15: Botón seco, sin flux ni pegajosidad, con accionamiento y retorno libres. | J15: Proteger el botón y toda el área de conectores con Kapton durante el retrabajo. Inspeccionar al 100 %. Rechazar y reemplazar ante residuos o pegajosidad, aunque el botón aún accione. Para probarlo, usar solo el dedo. No usar pinzas puntiagudas. | K15: Aplicar estos controles en cada línea nueva o recalificación del producto. Confirmar que el personal conoce el criterio de reemplazo y verificar función después de cambiar el componente. | L15: Alerta de calidad CVEBU QAF350 Rev03. Experimento y criterios reportados el 30/09/2026. | N15: Y
A16: CC-HEIMDALL-CLIP-CUSTODY | B16: REVISION | C16: HEIMDALL | D16: 73-103459-02 | E16: A0 | G16: 700-136420-01 | H16: J3-J8 | I16: Presencia, fijación y continuidad del clip J3-J8; superficie dorada de contacto limpia; custodia de manufactura definida por referencia. | J16: PCAMAP + BOM/RefDes + documento de proceso aprobado + 100 % X-Ray en J3-J8. | K16: En cada ECN/ECO, nueva revisión, cambio de línea o requalificación, confirmar el owner, destino y método de ensamble de J3-J8. Si algún campo queda sin resolver, mantener HOLD y escalar al CFT/Cisco. | L16: PCAMAP 61-107350-02 · Heimdall 73-103459-02 ECN / clip investigation | N16: Y
A17: CC-GREENFORD-MARCADO | B17: PRODUCT | C17: GREENFORD | D17: 73-104532-01 | G17: 17-103689-02; 17-103691-01; 17-102460-07 | I17: Identificación autorizada del material reprogramado y revisión vigente OCV/OCR | J17: Referencia oficial de marcado + revisión OCV/OCR controlada + reto positivo/negativo. | K17: Antes del cambio de modelo o línea, cotejar PN, programación, marcado autorizado y librería vigente. Sin referencia oficial disponible, retener y escalar. No extender C1 a otros PN o programaciones por semejanza. | L17: Chat Análisis de causa raíz, 01/10/2026. Relato del usuario y síntesis de PILOTO GREENFORD / Re: PILOTO GREENFORD. La revisión de los adjuntos debe respaldar la autorización. | N17: Y
A18: CC-BROOKLYN-S1-ACCIONAMIENTO | B18: PRODUCT | C18: BROOKLYN | D18: 73-102022-02 | G18: 22-100214-01 | H18: S1 | I18: Accionamiento y retorno de S1 sin fuerza lateral ni herramienta punzante | J18: WI de accionamiento controlado y verificación antes/después. No usar herramienta punzante. | K18: Definir en WI el método de accionamiento controlado. Antes/después del retrabajo revisar retorno libre, atasco, retorno lento, decoloración y residuos. Separar defecto previo de daño durante inspección. | L18: Chat Investigación profunda 8D, 30/09/2026. Experimento en 5 Brooklyn recuperado del historial: flux reprodujo atasco; alcohol no lo reprodujo en esa muestra; observación de tweezer. | N18: Y
A19: CC-VORETJ-PTH-PUENTES | B19: PRODUCT | C19: VoreTJ-48PXPLX | D19: 73-103083-04 | G19: 29-102727-02 | H19: J2/J4/J7/J13 | I19: Ausencia de puentes de soldadura en conectores después de PTH | J19: Inspección post-PTH de J2/J4/J7/J13 y receta/fixture controlados. | K19: Inspeccionar las referencias afectadas después de PTH y segregar desde el último serial conforme ante recurrencia. Revalidar receta y controles cuando cambien ola, pallet, producto o parámetros. | L19: Chat Quake/Mobius, 04/08/2026 hora México / 05/08 UTC. Relato de 27 SN; síntesis del historial: PTH P21S1CT1/P21S4CT1 y RefDes J2/J4/J7/J13. Causa raíz pendiente. | N19: Y
A20: CC-731991908-LAVADO | B20: PRODUCT | D20: 73-19919-08 | I20: PCB limpia y verificada antes de reimpresión de pasta | J20: Ruta aprobada de lavado, buffer segregado y verificación antes de reimpresión. | K20: Segregar PCB con impresión rechazada, enviarla al lavado aprobado y verificar limpieza antes de reintroducirla. Registrar intentos y disposición; detener/escalar si el defecto de impresión se repite. | L20: Chats ICT Short Fail 73-19919-08 / WO 000001289594, 21/08/2026. 890 unidades, 18 afectadas, 873 ICT Pass y 17 pendientes son cifras de momentos/poblaciones por conciliar. No calcular tasa con ellas. | N20: Y

Sheet Component Cross Reference
A1: Mapping ID | B1: Component CPN | C1: Product | D1: Board Part Number | E1: Rev | F1: RefDes | G1: Side | H1: MPN | I1: Description | J1: Source | K1: Notes | L1: Active
A2: MAP-PICTORIS-J73 | B2: 27-100137-01 | C2: PICTORIS | D2: 73-103603-05 | F2: J73 | I2: Conector J73. Revisar orientación. | J2: Queja de cliente / lección aprendida | K2: Componente asociado al hallazgo J73. La posición cambia según la tablilla. | L2: Y
A3: MAP-TUFNELL-HI-U23-OLD | B3: 15-102981-01 | C3: TUFNELL PARK | D3: 73-20247-06 | F3: U23 | I3: Material U23 antes del cambio liberado. | J3: Análisis de desviación CRBU / NGFWBU | K3: Transición documentada de 15-102981-01 a 15-102981-02. | L3: Y
A4: MAP-TUFNELL-HI-U23-NEW | B4: 15-102981-02 | C4: TUFNELL PARK | D4: 73-20247-06 | F4: U23 | I4: Material U23 después del cambio liberado. | J4: Análisis de desviación CRBU / NGFWBU | K4: Transición documentada de 15-102981-01 a 15-102981-02. | L4: Y
A5: MAP-TUFNELL-LO-U23-OLD | B5: 15-102981-01 | C5: TUFNELL PARK | D5: 73-20249-06 | F5: U23 | I5: Material U23 antes del cambio liberado. | J5: Análisis de desviación CRBU / NGFWBU | K5: Transición documentada de 15-102981-01 a 15-102981-02. | L5: Y
A6: MAP-TUFNELL-LO-U23-NEW | B6: 15-102981-02 | C6: TUFNELL PARK | D6: 73-20249-06 | F6: U23 | I6: Material U23 después del cambio liberado. | J6: Análisis de desviación CRBU / NGFWBU | K6: Transición documentada de 15-102981-01 a 15-102981-02. | L6: Y
A7: MAP-HEIMDALL-CLIP-J3-J8 | B7: 700-136420-01 | C7: HEIMDALL | D7: 73-103459-02 | E7: A0 | F7: J3-J8 | I7: Clip de contacto BeCu con acabado Au/Ni para la interfaz eléctrica/mecánica con los spring terminals del speaker. | J7: PCAMAP 61-107350-02 · ECN / Heimdall clip investigation | K7: El PCAMAP identifica J3-J8 como posiciones de clip y requiere X-Ray. El método de ensamble y la custodia del proceso deben quedar explícitos en la implementación del ECN. | L7: Y
A8: MAP-VORETJ-PULSE-CONECTORES | B8: 29-102727-02 | C8: VoreTJ-48PXPLX | D8: 73-103083-04 | F8: J2/J4/J7/J13 | I8: Conector PULSE con puentes reportados post-PTH. | J8: Chat Quake/Mobius, 04/08/2026 hora México / 05/08 UTC. Relato de 27 SN; síntesis del historial: PTH P21S1CT1/P21S4CT1 y RefDes J2/J4/J7/J13. Causa raíz pendiente. | K8: Mapeo recuperado del historial; cotejar BOM/RefDes vigente al implementar en otra revisión. | L8: Y
A9: MAP-PICTORIS-S1 | B9: 22-100214-01 | C9: PICTORIS | D9: 73-103603-05 | F9: S1 | I9: Botón S1 CVEBU. | J9: Findings existentes LL-PICTORIS-BOTON-FLUX. Base suministrada por el usuario. | K9: Mapeo ya documentado en Findings. La herencia de controles térmicos requiere validación específica del producto/layout. | L9: Y
A10: MAP-MILLENIUM-S1 | B10: 22-100214-01 | C10: MILLENIUM | D10: 73-102226-06 | F10: S1 | I10: Botón S1 CVEBU. | J10: Findings existentes LL-MILLENIUM-BOTON-FLUX. Base suministrada por el usuario. | K10: Mapeo ya documentado en Findings. La herencia de controles térmicos requiere validación específica del producto/layout. | L10: Y
A11: MAP-OCTAVIO-S1 | B11: 22-100214-01 | C11: OCTAVIO | D11: 73-102701-01 | F11: S1 | I11: Botón S1 CVEBU. | J11: Findings existentes LL-OCTAVIO-BOTON-FLUX. Base suministrada por el usuario. | K11: Mapeo ya documentado en Findings. La herencia de controles térmicos requiere validación específica del producto/layout. | L11: Y
A12: MAP-BROOKLYN-S1 | B12: 22-100214-01 | C12: BROOKLYN | D12: 73-102022-02 | F12: S1 | I12: Botón S1 CVEBU. | J12: Findings existentes LL-BROOKLYN-BOTON-FLUX. Base suministrada por el usuario. | K12: Mapeo ya documentado en Findings. La herencia de controles térmicos requiere validación específica del producto/layout. | L12: Y
A13: MAP-DAVINCI-S1 | B13: 22-100214-01 | C13: DAVINCI | D13: 73-102797-02 | F13: S1 | I13: Botón S1 CVEBU. | J13: Findings existentes LL-DAVINCI-BOTON-FLUX. Base suministrada por el usuario. | K13: Mapeo ya documentado en Findings. La herencia de controles térmicos requiere validación específica del producto/layout. | L13: Y

Sheet Instructions
A1: Section | B1: Guidance
A2: Purpose | B2: Base manual de lecciones Yokoten para SMTinel. Los datos de producción, órdenes, pruebas y reparaciones están en Common DB / Handoff / Test Performance / Repair Record.
A3: Root filename | B3: Guardar con el nombre SMTinel_Yokoten_Knowledge_DB.xlsx en la carpeta principal.
A4: Scope values | B4: Usar PRODUCT, REVISION, LINE o PRODUCT_REV_LINE. PRODUCT aplica a todas las líneas. PRODUCT_REV_LINE aplica solo a esa revisión y línea.
A5: Active | B5: Y publica el registro. N lo conserva sin cargarlo en SMTinel.
A6: Qualification | B6: Agregar una fila por producto, número de parte, revisión y línea cuando exista evidencia de calificación.
A7: Findings | B7: Una fila por lección aprendida o hallazgo. Usar un Finding ID único y estable.
A8: Actions | B8: Las acciones pueden ligarse al Finding ID y a una persona/equipo responsable. Finding ID puede quedar vacío solo para una referencia crítica iniciada directamente desde Action Tracker; no crear un Finding hasta que la lección esté validada según la regla de curación.
A9: Critical Characteristics | B9: Controles importantes del producto que deben mantenerse al cambiar de línea.
A10: Links | B10: Usar enlaces HTTPS a FAI, SOP, 8D, lección aprendida o evidencia. No insertar archivos adjuntos.
A11: Size discipline | B11: Guardar solo texto. No pegar imágenes, listas de series, registros de producción ni reportes de reparación.
A12: Curation rule | B12: Esta regla aplica a Findings y Critical Characteristics: publicar lecciones solo con análisis respaldado y conclusión validada. Actions sí puede contener controles Open/Monitoring pendientes de implementación; no convertir una acción propuesta en causa confirmada.
... A41: Change Control / source | B41: Más reglas en hoja Change Rules. Mantener históricos y vínculos auditables, sin copiar adjuntos binarios.

Sheet Change Register
A1: Change ID | B1: Document Type | C1: Document Number | D1: Document Revision | E1: Change Description | F1: Approval Status | G1: Document State | H1: Scope Class | I1: BU | J1: Related Document | K1: Approval Date | L1: Effective From | M1: Effective Until | N1: Effective WO From | O1: Effective WO Until | P1: Official Source URL | Q1: Engineering Owner | R1: Quality Reviewer | S1: Review Date | T1: Active | U1: Notes | V1: Summary ES | W1: Change Description ES | X1: Translation Review | Y1: ECO Release Date (source) | Z1: ECO BOM Date (source, single only) | AA1: ECO Implementation Type (source)
A2: DEV-CTANJZ04014 | B2: DEVIATION | C2: D598638 | E2: D598638 TBABU: This is extension of D585507.Deviation Leverages # D585507 (Purpose of the new deviation is to reference new version of DVD 80-100592-02 with old 01 version)The solution for this problem requires IT tool changes in order to permanently resolve the issue; therefore we are using the deviation process (with Director approval) for an extensive period of time.This Deviation will officially authorizes to all Sites to follow Order Fulfillment EAC Compliance DVD Disc Insertion Process during pack outPlease see PageThree for details | F2: Pending | G2: Closed | H2: Pending Review | I2: SRGBU | J2: CTANJZ04014 | M2: 47790 | T2: Y | U2: FUENTE: Deviation.csv, filas CSV 1249-1249; Workflow=Closed; Date Released=2024-08-10; Date Originated=2024-08-06; Site=FJZP, Plant=MCGA (sin convertir automaticamente a FJZ); 1 filas PN; APROBACION Y APLICABILIDAD NO VALIDADAS.
A3: DEV-CTANJZ04427 | B3: DEVIATION | C3: D601187 | E3: D601187NGFWBU: Risk Buy: GQR No: GQR000020121; AQR No: AQR000831374; CPN:20-0645-01; MFR NAME: INFINEON TECHNOLOGIES; MPN: IRLML9303TRPBFTo execute the above AQR at CM Site. | F3: Pending | G3: Expired | H3: Pending Review | I3: STBU | J3: CTANJZ04427 | M3: 45775 | T3: Y | U3: FUENTE: Deviation.csv, filas CSV 1549-1551; Workflow=Expired; Date Released=2025-02-25; Date Originated=2025-02-03; Site=FJZP, Plant=MCGA (sin convertir automaticamente a FJZ); 3 filas PN; APROBACION Y APLICABILIDAD NO VALIDADAS.
A4: DEV-CTANJZ04430 | B4: DEVIATION | C4: D601838 | E4: D601838 Use 16-100671-01 MPN MTFDDAK480TGB-1BC16ABYY in place of 16-100670-01. | F4: Pending | G4: Expired | H4: Pending Review | I4: STBU | J4: CTANJZ04430 | M4: 45783 | T4: Y | U4: FUENTE: Deviation.csv, filas CSV 471-471; Workflow=Expired; Date Released=2025-02-21; Date Originated=2025-02-06; Site=FJZP, Plant=MCGA (sin convertir automaticamente a FJZ); 1 filas PN; APROBACION Y APLICABILIDAD NO VALIDADAS. | V4: Sustitución de material: utilizar 16-100671-01, MPN MTFDDAK480TGB-1BC16ABYY, en lugar de 16-100670-01. | W4: D601838: utilizar el CPN 16-100671-01, MPN MTFDDAK480TGB-1BC16ABYY, en reemplazo del CPN 16-100670-01. No se indican RefDes, revisiones ni evidencia de liberación en este texto; confirmar su alcance en el documento oficial. | X4: Traduccion para consulta
A5: DEV-CTANJZ04431 | B5: DEVIATION | C5: D601949 | E5: D601949 Allow FJZ to use material that change qual status to Cancel for the MCO113085:17-102102-0217-102040-0517-16001-05 | F5: Pending | G5: Expired | H5: Pending Review | I5: STBU | J5: CTANJZ04431 | M5: 45783 | T5: Y | U5: FUENTE: Deviation.csv, filas CSV 710-714; Workflow=Expired; Date Released=2025-02-25; Date Originated=2025-02-06; Site=FJZP, Plant=MCGA (sin convertir automaticamente a FJZ); 5 filas PN; APROBACION Y APLICABILIDAD NO VALIDADAS.
A6: DEV-CTANJZ04432 | B6: DEVIATION | C6: D601971 | E6: D601971 Please see PageThree for details | F6: Pending | G6: Expired | H6: Pending Review | I6: SRGBU | J6: CTANJZ04432 | M6: 45783 | T6: Y | U6: FUENTE: Deviation.csv, filas CSV 472-473; Workflow=Expired; Date Released=2025-02-21; Date Originated=2025-02-06; Site=FJZP, Plant=MCGA (sin convertir automaticamente a FJZ); 2 filas PN; APROBACION Y APLICABILIDAD NO VALIDADAS.
A7: DEV-CTANJZ04435 | B7: DEVIATION | C7: D596346 | E7: D596346 NGFWBU: GEN2 Net Mod; 68-104010-01 FNLASY; FPR-X-NM; GEN2;8X1G; BOROUGH. The Borough PCBA is not sufficiently supported by the Borough mechanical Carrier. Additional metal Spacer(s) and Formex insulator film is required to support the PCBA and prevent any risk of component damage and prevent potential electrical shorting of active components and via's. This Deviation supports the evaluation of a temporary fix until a permanent change is implemented. | F7: Pending | G7: Expired | H7: Pending Review | I7: STBU | J7: CTANJZ04435 | M7: 45783 | T7: Y | U7: FUENTE: Deviation.csv, filas CSV 1733-1733; Workflow=Expired; Date Released=2025-02-21; Date Originated=2025-02-06; Site=FJZP, Plant=MCGA (sin convertir automaticamente a FJZ); 1 filas PN; APROBACION Y APLICABILIDAD NO VALIDADAS.
A8: DEV-CTANJZ04441 | B8: DEVIATION | C8: D601899 | E8: D601899 SRGBU: VG410 - Allow FOC to use non A0 parts to ship to customer.There is no HW difference from PP to Pilot; and the RDT units can be shipped to customer.Below are the CPNs and qtys: CPN Rev QTY MPN74-129859-01 -05 28 74-129859-0174-129860-01 -05 29 74-129860-01800-51476-01 -01 43 74-130046-01 | F8: Pending | G8: Expired | H8: Pending Review | I8: SRGBU | J8: CTANJZ04441 | M8: 45788 | T8: Y | U8: FUENTE: Deviation.csv, filas CSV 653-655; Workflow=Expired; Date Released=2025-02-25; Date Originated=2025-02-11; Site=FJZP, Plant=MCGA (sin convertir automaticamente a FJZ); 3 filas PN; APROBACION Y APLICABILIDAD NO VALIDADAS.
A9: DEV-CTANJZ04443 | B9: DEVIATION | C9: D601883 | E9: D601883 Allow use the old packaging 84-100494-02 and not use the new end caps 501-102028-01 | F9: Pending | G9: Expired | H9: Pending Review | I9: STBU | J9: CTANJZ04443 | M9: 45788 | T9: Y | U9: FUENTE: Deviation.csv, filas CSV 348-349; Workflow=Expired; Date Released=2025-02-21; Date Originated=2025-02-11; Site=FJZP, Plant=MCGA (sin convertir automaticamente a FJZ); 2 filas PN; APROBACION Y APLICABILIDAD NO VALIDADAS.
A10: DEV-CTANJZ04449 | B10: DEVIATION | C10: D602143 | E10: D602143FJZ will to change the battery placement to 800-level on assy area for the KP products and do a manual discharge before placing the battery. | F10: Pending | G10: Expired | H10: Pending Review | I10: STBU | J10: CTANJZ04449 | M10: 45789 | T10: Y | U10: FUENTE: Deviation.csv, filas CSV 656-664; Workflow=Expired; Date Released=2025-02-21; Date Originated=2025-02-12; Site=FJZP, Plant=MCGA (sin convertir automaticamente a FJZ); 9 filas PN; APROBACION Y APLICABILIDAD NO VALIDADAS.
A11: DEV-CTANJZ04450 | B11: DEVIATION | C11: D602145 | E11: D602145Use 74-126726-01 as substitute of 74-113291-01 on DF | F11: Pending | G11: Expired | H11: Pending Review | I11: STBU | J11: CTANJZ04450 | M11: 45789 | T11: Y | U11: FUENTE: Deviation.csv, filas CSV 679-685; Workflow=Expired; Date Released=2025-02-25; Date Originated=2025-02-12; Site=FJZP, Plant=MCGA (sin convertir automaticamente a FJZ); 7 filas PN; APROBACION Y APLICABILIDAD NO VALIDADAS.
A12: DEV-CTANJZ04453 | B12: DEVIATION | C12: D601097 | E12: D601097NGFWBU: Risk Buy: GQR No: GQR000041154; AQR No: AQR001673096; CPN:36-0227-01; MFR NAME: TAI-TECH ADVANCED ELECTRONICS; MPN:MB15K601-03CTo execute the above AQR at CM Site. | F12: Pending | G12: Expired | H12: Pending Review | I12: STBU | J12: CTANJZ04453 | M12: 45790 | T12: Y | U12: FUENTE: Deviation.csv, filas CSV 1411-1413; Workflow=Expired; Date Released=2025-02-21; Date Originated=2025-02-13; Site=FJZP, Plant=MCGA (sin convertir automaticamente a FJZ); 3 filas PN; APROBACION Y APLICABILIDAD NO VALIDADAS.
A13: DEV-CTANJZ04465 | B13: DEVIATION | C13: D602184 | E13: D602184SRGBU-Promethium; Promethium-L; Tabei-L:Allow the use of the Re-Spin fab by the JDM partner; while waiting for confirmation from the MCN/AQR team | F13: Pending | G13: Expired | H13: Pending Review | I13: SRGBU | J13: CTANJZ04465 | M13: 45796 | T13: Y | U13: FUENTE: Deviation.csv, filas CSV 1734-1736; Workflow=Expired; Date Released=2025-02-25; Date Originated=2025-02-19; Site=FJZP, Plant=MCGA (sin convertir automaticamente a FJZ); 3 filas PN; APROBACION Y APLICABILIDAD NO VALIDADAS.
A14: DEV-CTANJZ04466 | B14: DEVIATION | C14: D602196 | E14: D602196 Allow FJZ to use the alternative part PR1983 (NJSS-M3-1.53-P) from PENCOM | F14: Pending | G14: Expired | H14: Pending Review | I14: STBU | J14: CTANJZ04466 | M14: 45796 | T14: Y | U14: FUENTE: Deviation.csv, filas CSV 1595-1599; Workflow=Expired; Date Released=2025-02-28; Date Originated=2025-02-19; Site=FJZP, Plant=MCGA (sin convertir automaticamente a FJZ); 5 filas PN; APROBACION Y APLICABILIDAD NO VALIDADAS.
A15: DEV-CTANJZ04473 | B15: DEVIATION | C15: D602345 | E15: D602345 Please see PageThree for details | F15: Pending | G15: Expired | H15: Pending Review | I15: STBU | J15: CTANJZ04473 | M15: 45799 | T15: Y | U15: FUENTE: Deviation.csv, filas CSV 1737-1741; Workflow=Expired; Date Released=2025-03-04; Date Originated=2025-02-22; Site=FJZP, Plant=MCGA (sin convertir automaticamente a FJZ); 5 filas PN; APROBACION Y APLICABILIDAD NO VALIDADAS.
A16: DEV-CTANJZ04475 | B16: DEVIATION | C16: D602181 | E16: D602181 SRGBU/IOTBU hot plug issue component substitution:This deviation instructs FOL/FVN/FDO/FJZ PCBA to use 15-10118-01 instead of 15-10118-02 for new builds.FOL/FVN/FDO/FJZ PCBA should pipeline material for Renesas QS3VH245QG and TI SN74CBTLV3245ADBQR as diodes PI3B3245QEX will not be used for new builds | F16: Pending | G16: Expired | H16: Pending Review | I16: SRGBU | J16: CTANJZ04475 | M16: 45799 | T16: Y | U16: FUENTE: Deviation.csv, filas CSV 338-365; Workflow=Expired; Date Released=2025-03-04; Date Originated=2025-02-22; Site=FJZP, Plant=MCGA (sin convertir automaticamente a FJZ); 17 filas PN; APROBACION Y APLICABILIDAD NO VALIDADAS.
... A55: DEV-CTANJZ04617 | B55: DEVIATION | C55: D604044 | E55: D604044 Allow AVer to use 50% recycled plastic bag to pack the camera and 35% recycled plastic bag to pack cable cover | F55: Pending | G55: Expired | H55: Pending Review | I55: CVEBU | J55: CTANJZ04617 | M55: 45889 | T55: Y | U55: FUENTE: Deviation.csv, filas CSV 804-805; Workflow=Expired; Date Released=2025-06-18; Date Originated=2025-05-23; Site=FJZP, Plant=MCGA (sin convertir automaticamente a FJZ); 2 filas PN; APROBACION Y APLICABILIDAD NO VALIDADAS.
A56: DEV-CTANJZ04618 | B56: DEVIATION | C56: D603586 | E56: D603586 NGFWBU: Risk Buy: GQR No: GQR000047935; AQR No: AQR002263531 ; CPN: 20-0405-01; MFR NAME: ROHM; MPN: US6K1To execute the above AQR at CM Site. | F56: Pending | G56: Expired | H56: Pending Review | I56: STBU | J56: CTANJZ04618 | M56: 45889 | T56: Y | U56: FUENTE: Deviation.csv, filas CSV 1408-1410; Workflow=Expired; Date Released=2025-06-11; Date Originated=2025-05-23; Site=FJZP, Plant=MCGA (sin convertir automaticamente a FJZ); 3 filas PN; APROBACION Y APLICABILIDAD NO VALIDADAS. | V56: Calificación / compra de riesgo: tramitar AQR002263531 para el CPN 20-0405-01, fabricante ROHM, MPN US6K1, en el sitio de manufactura. Se solicita revisar y firmar el documento recargado. | W56: D603586: observación: documento equivalente a CTANJZ04618; se volvió a cargar D603586 y se solicita revisión y aprobación. NGFWBU: compra de riesgo asociada al GQR000047935 y AQR002263531, CPN 20-0405-01, fabricante ROHM, MPN US6K1. La intención es ejecutar la calificación AQR mencionada en el sitio CM. Solicitar la evidencia de aprobación antes de tratarla como autorización. | X56: Traduccion para consulta
A57: DEV-CTANJZ04623 | B57: DEVIATION | C57: D604124 | E57: D604124 Add Custom cardboard cutouts and edge boards during palletisation and a note not to depalletize in transit | F57: Pending | G57: Expired | H57: Pending Review | I57: CVEBU | J57: CTANJZ04623 | M57: 45890 | T57: Y | U57: FUENTE: Deviation.csv, filas CSV 1843-1843; Workflow=Expired; Date Released=2025-06-18; Date Originated=2025-05-24; Site=FJZP, Plant=MCGA (sin convertir automaticamente a FJZ); 1 filas PN; APROBACION Y APLICABILIDAD NO VALIDADAS.
A58: DEV-CTANJZ04631 | B58: DEVIATION | C58: D604068 | E58: D604068 Warwick: Current connector solder tail length is 125 mils; while Warwick PCB is ~137 mils thick. This lead protrusion (lack of) making it difficult to inspect Warwick PCBAs; as well as a causing a number of units to have insufficient thru-hole barrel fill. Longer solder tails will provide better soldering; eliminate thru-hole barrel fill concerns.Deviation is to allow FJZ to implement first the ECO EA616344 that includes only the replacement of the current connector -29-104201-01 (125 mil solder tail length) with 29-104201-02 (165 mil solder tail length)The ECO EA608077 released in December 2024; will be implement in November 2025 to use all the old material | F58: Pending | G58: Expired | H58: Pending Review | I58: STBU | J58: CTANJZ04631 | M58: 45895 | T58: Y | U58: FUENTE: Deviation.csv, filas CSV 2-37; Workflow=Expired; Date Released=2025-06-18; Date Originated=2025-05-29; Site=FJZP, Plant=MCGA (sin convertir automaticamente a FJZ); 9 filas PN; APROBACION Y APLICABILIDAD NO VALIDADAS. | V58: WARWICK: cambiar conector 29-104201-01 (terminal de soldadura de 125 mil) por 29-104201-02 (165 mil) para mejorar la protrusión y el llenado de barril en PCB de aproximadamente 137 mil de espesor. | W58: D604068, Warwick: la longitud actual de las terminales de soldadura del conector es de 125 mil, mientras que la PCB tiene un espesor aproximado de 137 mil. Esta falta de protrusión dificulta la inspección y se relaciona con llenado insuficiente de los barriles metalizados. Las terminales más largas permitirán mejor soldadura. La desviación describe permitir a FJZ implementar antes el ECO EA616344, reemplazando únicamente el conector 29-104201-01 (terminal de 125 mil) por 29-104201-02 (terminal de 165 mil). También se menciona el ECO EA608077 liberado en diciembre de 2024 y un plan histórico de implementación para noviembre de 2025 con agotamiento del material anterior. Conservar el estado del documento antes de cualquier aplicación. | X58: Traduccion para consulta
A59: DEV-CTANJZ04632 | B59: DEVIATION | C59: DP524922 | E59: DP524922 For Pre-pilot build- FJZ can follow AVL build matrix Provided by PE (Priyanka anshu) for MB; ESW and Mezz | F59: Pending | G59: Expired | H59: Pending Review | I59: STBU | J59: CTANJZ04632 | M59: 45866 | T59: Y | U59: FUENTE: Deviation.csv, filas CSV 354-356; Workflow=Expired; Date Released=2025-06-11; Date Originated=2025-05-30; Site=FJZP, Plant=MCGA (sin convertir automaticamente a FJZ); 3 filas PN; APROBACION Y APLICABILIDAD NO VALIDADAS.
A60: DEV-CTANJZ04634 | B60: DEVIATION | C60: D604208 | E60: D604208 FJZ to change the stock of the part 15-104142-01 to 15-104142-02 for MPN HMA82GU7DJR8N-XN (28 units) and SR5722G822AUJUMME1 (2840 units) these M]PNs are used on both parts and can be converted from -01 to be used as -02 | F60: Pending | G60: Expired | H60: Pending Review | I60: STBU | J60: CTANJZ04634 | M60: 45896 | T60: Y | U60: FUENTE: Deviation.csv, filas CSV 807-808; Workflow=Expired; Date Released=2025-06-18; Date Originated=2025-05-30; Site=FJZP, Plant=MCGA (sin convertir automaticamente a FJZ); 2 filas PN; APROBACION Y APLICABILIDAD NO VALIDADAS.
A61: DEV-CTANJZ04635 | B61: DEVIATION | C61: D604078 | E61: D604078 Use individual bag 502-00269-01 per memory instead of use a single bag for 2 memories | F61: Pending | G61: Expired | H61: Pending Review | I61: STBU | J61: CTANJZ04635 | M61: 45896 | T61: Y | U61: FUENTE: Deviation.csv, filas CSV 1844-1844; Workflow=Expired; Date Released=2025-06-19; Date Originated=2025-05-30; Site=FJZP, Plant=MCGA (sin convertir automaticamente a FJZ); 1 filas PN; APROBACION Y APLICABILIDAD NO VALIDADAS.
A62: DEV-CTANJZ04640 | B62: DEVIATION | C62: DP524361 | E62: DP524361 Please see PageThree for details | F62: Pending | G62: Expired | H62: Pending Review | I62: STBU | J62: CTANJZ04640 | M62: 45871 | T62: Y | U62: FUENTE: Deviation.csv, filas CSV 766-770; Workflow=Expired; Date Released=2025-06-26; Date Originated=2025-06-04; Site=FJZP, Plant=MCGA (sin convertir automaticamente a FJZ); 5 filas PN; APROBACION Y APLICABILIDAD NO VALIDADAS.
A63: DEV-CTANJZ04641 | B63: DEVIATION | C63: D604196 | E63: D604196 CVEBUPWR-CORD-IND-F Power Cord for India 5m 10A PWR-CORD-IND-F= Power Cord for India 5m 10A SPAREIn BOMs:37-100881-02 POWER CORD;India;STRANDED;250.0 V;6.0 A;5M;GREY;3x 1.0 mm2IPQ: Feller 5122-FE0-0-5100IPQ: Volex VLX-37-100881-02-MP3PWR-CORD-IND-B Power Cord for India 2m 10A PWR-CORD-IND-B= Power Cord for India 2m 10A SPARE37-100894-02 OWER CORD;India;STRANDED;250.0 V;6.0 A;2M;GREY;3x 1.0 mm2IPQ: Volex VLX-37-100894-02-MP3DF and BTS sites are allowed to start sourcing non-China power cords for India which is still in IPQ. | F63: Pending | G63: Expired | H63: Pending Review | I63: CVEBU | J63: CTANJZ04641 | M63: 45901 | T63: Y | U63: FUENTE: Deviation.csv, filas CSV 393-394; Workflow=Expired; Date Released=2025-06-18; Date Originated=2025-06-04; Site=FJZP, Plant=MCGA (sin convertir automaticamente a FJZ); 2 filas PN; APROBACION Y APLICABILIDAD NO VALIDADAS.
A64: DEV-CTANJZ04645 | B64: DEVIATION | C64: DP524944 | E64: DP524944 Please see PageThree for details | F64: Pending | G64: Expired | H64: Pending Review | I64: STBU | J64: CTANJZ04645 | M64: 45872 | T64: Y | U64: FUENTE: Deviation.csv, filas CSV 771-778; Workflow=Expired; Date Released=2025-06-26; Date Originated=2025-06-05; Site=FJZP, Plant=MCGA (sin convertir automaticamente a FJZ); 8 filas PN; APROBACION Y APLICABILIDAD NO VALIDADAS.
A65: DEV-CTANJZ04646 | B65: DEVIATION | C65: D604197 | E65: D604197 NGFWBU: Risk Buy: GQR No: GQR000055332; AQR No:AQR002398401; CPN: 15-5000-01; MFR NAME: TOSHIBA; MPN: TC7PZ34FU;LCISJ(CB | F65: Pending | G65: Expired | H65: Pending Review | I65: STBU | J65: CTANJZ04646 | M65: 45902 | T65: Y | U65: FUENTE: Deviation.csv, filas CSV 1466-1469; Workflow=Expired; Date Released=2025-07-01; Date Originated=2025-06-05; Site=FJZP, Plant=MCGA (sin convertir automaticamente a FJZ); 4 filas PN; APROBACION Y APLICABILIDAD NO VALIDADAS.
A66: DEV-CTANJZ04647 | B66: DEVIATION | C66: D604285 | E66: D604285::::::::::::::NGFWBU FPR4K::::::::::::::::::This deviation seek to allow FJZ to place Risk Buy PO for 16-101919-01 with MPNs:SAMSUNG SEMICONDUCTORS - MZTL21T9HCJR-00A07HYNIX SEMICONDUCTOR - HFS1T9GEEWX091NThis Deviation also allows for FJZ to use Qualified MPNs:SAMSUNG SEMICONDUCTORS - MZTL21T9HCJR-00A07HYNIX SEMICONDUCTOR - HFS1T9GEEWX091N | F66: Pending | G66: Expired | H66: Pending Review | I66: STBU | J66: CTANJZ04647 | M66: 45902 | T66: Y | U66: FUENTE: Deviation.csv, filas CSV 1423-1465; Workflow=Expired; Date Released=2025-07-15; Date Originated=2025-06-05; Site=FJZP, Plant=MCGA (sin convertir automaticamente a FJZ); 2 filas PN; APROBACION Y APLICABILIDAD NO VALIDADAS.
A67: DEV-CTANJZ04648 | B67: DEVIATION | C67: D604046 | E67: D604046 NGFWBU: Risk Buy: GQR No: GQR000054859; AQR No:AQR002377427; CPN: 20-0443-01; MFR NAME: CYSTECH ELECTRONICS CORP; MPN: MTB2D6N03RJ3 | F67: Pending | G67: Expired | H67: Pending Review | I67: STBU | J67: CTANJZ04648 | M67: 45902 | T67: Y | U67: FUENTE: Deviation.csv, filas CSV 1419-1422; Workflow=Expired; Date Released=2025-06-26; Date Originated=2025-06-05; Site=FJZP, Plant=MCGA (sin convertir automaticamente a FJZ); 4 filas PN; APROBACION Y APLICABILIDAD NO VALIDADAS.
A68: DEV-CTANJZ04649 | B68: DEVIATION | C68: D604092 | E68: D604092 NGFWBU: Risk Buy: GQR No: GQR000052832; AQR No:AQR002399499; CPN: 20-0187-01; MFR NAME: DIODES INC; MPN: DZT2222A-13 | F68: Pending | G68: Expired | H68: Pending Review | I68: STBU | J68: CTANJZ04649 | M68: 45902 | T68: Y | U68: FUENTE: Deviation.csv, filas CSV 1415-1418; Workflow=Expired; Date Released=2025-06-26; Date Originated=2025-06-05; Site=FJZP, Plant=MCGA (sin convertir automaticamente a FJZ); 4 filas PN; APROBACION Y APLICABILIDAD NO VALIDADAS.
A69: DEV-CTANJZ04650 | B69: DEVIATION | C69: D604195 | E69: D604195 NGFWBU: Risk Buy: GQR No: GQR000055149; AQR No:AQR002394490; CPN: 24-3133-01; MFR NAME: MAG LAYERS; MPN: MMD-10DZNR36MEX2-CS-RU | F69: Pending | G69: Expired | H69: Pending Review | I69: STBU | J69: CTANJZ04650 | M69: 45902 | T69: Y | U69: FUENTE: Deviation.csv, filas CSV 1457-1470; Workflow=Expired; Date Released=2025-07-01; Date Originated=2025-06-05; Site=FJZP, Plant=MCGA (sin convertir automaticamente a FJZ); 4 filas PN; APROBACION Y APLICABILIDAD NO VALIDADAS.
A70: DEV-CTANJZ04651 | B70: DEVIATION | C70: DP524724 | E70: DP524724 Please see PageThree for details | F70: Pending | G70: Expired | H70: Pending Review | I70: STBU | J70: CTANJZ04651 | M70: 45873 | T70: Y | U70: FUENTE: Deviation.csv, filas CSV 690-726; Workflow=Expired; Date Released=2025-06-26; Date Originated=2025-06-06; Site=FJZP, Plant=MCGA (sin convertir automaticamente a FJZ); 8 filas PN; APROBACION Y APLICABILIDAD NO VALIDADAS.
... A79: DEV-CTANJZ04678 | B79: DEVIATION | C79: D604665 | E79: D604665 CVEBU;HeliosCS-CAM-RVPTZ-C Cisco Room Vision PTZ Camera; Carbon Black 74-146086-01 CAMERA MODULE;4k;PTZ;HELIOS;CARBON BLACKSelectable option via Config sheet:CS-PWR-INJ-30W Power Injector 802.3at PoE+ 30W 341-100456-03 PWRSPLY-ADAPTER;ISOLATED;POE;AC;30.0 W...IPQ to Qualified: Microchip PD-9001GR/AT/AC-CSIQualified: Phihong POE29U-1AT(PL)C-R ZDue missing availability FCZ and FJZ is allowed to use instead:AIR-PWRINJ6 Power Injector (802.3at) for Aironet Access Points 341-100456-02 PWRSPLY-ADAPTER;ISOLATED;POE;AC;30.0 W..Qualified: Microchip PD-9001GR/AT/AC-WN ZQualified: Phihong POE29U-1AT(PL)C-R Z | F79: Pending | G79: Expired | H79: Pending Review | I79: CVEBU | J79: CTANJZ04678 | M79: 45917 | T79: Y | U79: FUENTE: Deviation.csv, filas CSV 877-877; Workflow=Expired; Date Released=2025-07-01; Date Originated=2025-06-20; Site=FJZP, Plant=MCGA (sin convertir automaticamente a FJZ); 1 filas PN; APROBACION Y APLICABILIDAD NO VALIDADAS.
A80: DEV-CTANJZ04679 | B80: DEVIATION | C80: DP525026 | E80: DP525026 CVEBU;Pictoris73-103103-04 PCA; PICTORIS MAIN BOARD 73-103103-05 PCA; PICTORIS MAIN BOARD 73-103603-04 PCA; PICTORIS MAIN BOARD NR 73-103603-05 PCA; PICTORIS MAIN BOARD NR In BOMs; refdes U41715-108939-01 IC-MP;Trusted Platform Module 2.0 I2C;33 MHz;VQFP;32 P;5x5 mm PKGSIZE;0.5P;3.3 V NOM;0.63 W;I2C;NO-JTAG;-40 to 105 'CIPQ: Infinion SLB 9673AU2.0 FW27.24Qualified: ST Micro ST33HF2X32AHE3C1Do not use Infinion TPM circuit until the Pictoris AVL 2nd source build is completed and concluded. This is likely to be settled by late August 2025 | F80: Pending | G80: Expired | H80: Pending Review | I80: CVEBU | J80: CTANJZ04679 | M80: 45888 | T80: Y | U80: FUENTE: Deviation.csv, filas CSV 366-367; Workflow=Expired; Date Released=2025-07-02; Date Originated=2025-06-21; Site=FJZP, Plant=MCGA (sin convertir automaticamente a FJZ); 2 filas PN; APROBACION Y APLICABILIDAD NO VALIDADAS. | V80: PICTORIS: restricción temporal en U417. El documento indica no utilizar el circuito TPM Infineon hasta completar y concluir la calificación de la segunda fuente AVL de Pictoris. | W80: DP525026: Pictoris PCBAs 73-103103-04, 73-103103-05, 73-103603-04 y 73-103603-05. En la BOM, referencia U417, CPN 15-108939-01: módulo de plataforma confiable TPM 2.0, interfaz I²C, 33 MHz, VQFP de 32 terminales, encapsulado 5 × 5 mm, 3.3 V nominal y temperatura de −40 a 105 °C. Se mencionan Infineon SLB 9673AU2.0 FW27.24 y ST Micro ST33HF2X32AHE3C1. Instrucción original: no utilizar el circuito TPM Infineon hasta que la corrida de calificación de segunda fuente AVL de Pictoris haya concluido. El texto de origen estimaba su resolución para finales de agosto de 2025; no se debe interpretar esa estimación como liberación. | X80: Traduccion para consulta
A81: DEV-CTANJZ04680 | B81: DEVIATION | C81: D604676 | E81: D604676 CVEBU;HeliosCS-CAM-RVPTZ-C Cisco Room Vision PTZ Camera; Carbon Black 74-146086-01 CAMERA MODULE;4k;PTZ;HELIOS;CARBON BLACKSelectable option via Config sheet:CS-PWR-INJ-30W Power Injector 802.3at PoE+ 30W 341-100456-03 PWRSPLY-ADAPTER;ISOLATED;POE;AC;30.0 W...IPQ: Microchip PD-9001GR/AT/AC-CSIQualified: Phihong POE29U-1AT(PL)C-R ZDue missing availability; FCZ and FJZ are allowed to use same Phihong MPN; but with previous version CPN:AIR-PWRINJ6 Power Injector (802.3at) for Aironet Access Points 341-100456-02 PWRSPLY-ADAPTER;ISOLATED;POE;AC;30.0 W..Qualified: Phihong POE29U-1AT(PL)C-R Z (100 pcs site balanced from FVE) | F81: Pending | G81: Expired | H81: Pending Review | I81: CVEBU | J81: CTANJZ04680 | M81: 45918 | T81: Y | U81: FUENTE: Deviation.csv, filas CSV 878-878; Workflow=Expired; Date Released=2025-07-08; Date Originated=2025-06-21; Site=FJZP, Plant=MCGA (sin convertir automaticamente a FJZ); 1 filas PN; APROBACION Y APLICABILIDAD NO VALIDADAS.
A82: DEV-CTANJZ04684 | B82: DEVIATION | C82: DP524972 | E82: DP524972 This Prototype deviation will be used for Woodside Park Pre-Pilot chassis material at Likom.1. 10 chassis from Likom will be using the Old front logo label without the "Secure" wording due to new labels being lost. Likom will cut in the new labels for the rest of the units that will be shipped to FJZ once they have been received. | F82: Pending | G82: Expired | H82: Pending Review | I82: STBU | J82: CTANJZ04684 | M82: 45892 | T82: Y | U82: FUENTE: Deviation.csv, filas CSV 806-806; Workflow=Expired; Date Released=2025-07-15; Date Originated=2025-06-25; Site=FJZP, Plant=MCGA (sin convertir automaticamente a FJZ); 1 filas PN; APROBACION Y APLICABILIDAD NO VALIDADAS.
A83: DEV-CTANJZ04691 | B83: DEVIATION | C83: D604637 | E83: D604637 Deviation created to allow FJZ to test Tufnell units from Bone Pile with old revision for temporary manufacturing process changes. | F83: Pending | G83: Expired | H83: Pending Review | I83: STBU | J83: CTANJZ04691 | M83: 45923 | T83: Y | U83: FUENTE: Deviation.csv, filas CSV 760-932; Workflow=Expired; Date Released=2025-07-15; Date Originated=2025-06-26; Site=FJZP, Plant=MCGA (sin convertir automaticamente a FJZ); 12 filas PN; APROBACION Y APLICABILIDAD NO VALIDADAS.
A84: DEV-CTANJZ04693 | B84: DEVIATION | C84: D603586 | E84: D603586 ---Remark:It is same as CTANJZ04618;just reload the D603586;please review and sign off it;Thank you all.NGFWBU: Risk Buy: GQR No: GQR000047935; AQR No: AQR002263531 ; CPN: 20-0405-01; MFR NAME: ROHM; MPN: US6K1To execute the above AQR at CM Site. | F84: Pending | G84: Expired | H84: Pending Review | I84: STBU | J84: CTANJZ04693 | M84: 45889 | T84: Y | U84: FUENTE: Deviation.csv, filas CSV 1436-1436; Workflow=Expired; Date Released=2025-07-15; Date Originated=2025-06-26; Site=FJZP, Plant=MCGA (sin convertir automaticamente a FJZ); 1 filas PN; APROBACION Y APLICABILIDAD NO VALIDADAS. | V84: Calificación / compra de riesgo: tramitar AQR002263531 para el CPN 20-0405-01, fabricante ROHM, MPN US6K1, en el sitio de manufactura. Se solicita revisar y firmar el documento recargado. | W84: D603586: observación: documento equivalente a CTANJZ04618; se volvió a cargar D603586 y se solicita revisión y aprobación. NGFWBU: compra de riesgo asociada al GQR000047935 y AQR002263531, CPN 20-0405-01, fabricante ROHM, MPN US6K1. La intención es ejecutar la calificación AQR mencionada en el sitio CM. Solicitar la evidencia de aprobación antes de tratarla como autorización. | X84: Traduccion para consulta
A85: DEV-CTANJZ04699 | B85: DEVIATION | C85: D604620 | E85: D604620 CVEBU;HeliosCS-PWR-INJ-30W Power Injector 802.3at PoE+ 30W CS-PWR-INJ-30W= Power Injector 802.3at PoE+ 30W - SPAREIn BOMs341-100456-03 PWRSPLY-ADAPTER;ISOLATED;POE;AC;30.0 W...IPQ: Microchip PD-9001GR/AT/AC-CSIQualified: Phihong POE29U-1AT(PL)C-R ZSince the Microchip alternate is not yet qualified; and the Phihong alternate is not yet on-hand at DF sites; the DF sites are temporarily allowed to use the previous version:341-100456-02 PWRSPLY-ADAPTER;ISOLATED;POE;AC;30.0 W..Qualified: Microchip PD-9001GR/AT/AC-WN ZQualified: Phihong POE29U-1AT(PL)C-R ZUsing Microchip PD-9001GR/AT/AC-WN Z together with Brooklyn and Helios; may cause an extra Helios re-boot at first start-up. This allows temporarily use of this alternate. | F85: Pending | G85: Expired | H85: Pending Review | I85: CVEBU | J85: CTANJZ04699 | M85: 45923 | T85: Y | U85: FUENTE: Deviation.csv, filas CSV 474-474; Workflow=Expired; Date Released=2025-07-15; Date Originated=2025-07-02; Site=FJZP, Plant=MCGA (sin convertir automaticamente a FJZ); 1 filas PN; APROBACION Y APLICABILIDAD NO VALIDADAS.
A86: DEV-CTANJZ04702 | B86: DEVIATION | C86: D604757 | E86: D604757 NGFWBU: Risk Buy: GQR No: GQR000046874; AQR No:AQR002261011; CPN: 20-0041-02; MFR NAME: NEXPERIA USA INC; MPN: PMBT2907ATo execute the above AQR at CM Site. | F86: Pending | G86: Expired | H86: Pending Review | I86: STBU | J86: CTANJZ04702 | M86: 45930 | T86: Y | U86: FUENTE: Deviation.csv, filas CSV 1432-1433; Workflow=Expired; Date Released=2025-07-18; Date Originated=2025-07-03; Site=FJZP, Plant=MCGA (sin convertir automaticamente a FJZ); 2 filas PN; APROBACION Y APLICABILIDAD NO VALIDADAS.
A87: DEV-CTANJZ04703 | B87: DEVIATION | C87: D604633 | E87: D604633 NGFWBU: Risk Buy: GQR No: GQR000046862; AQR No:AQR002450088; CPN: 20-0643-01; MFR NAME: NEXPERIA USA INC; MPN: MMBT3904.To execute the above AQR at CM Site. | F87: Pending | G87: Expired | H87: Pending Review | I87: STBU | J87: CTANJZ04703 | M87: 45930 | T87: Y | U87: FUENTE: Deviation.csv, filas CSV 1428-1429; Workflow=Expired; Date Released=2025-07-18; Date Originated=2025-07-03; Site=FJZP, Plant=MCGA (sin convertir automaticamente a FJZ); 2 filas PN; APROBACION Y APLICABILIDAD NO VALIDADAS.
A88: DEV-CTANJZ04705 | B88: DEVIATION | C88: D604634 | E88: D604634 NGFWBU: Risk Buy: GQR No: GQR000046862; AQR No:AQR002450087; CPN: 20-0643-01; MFR NAME: NEXPERIA USA INC; MPN: MMBT3904To execute the above AQR at CM Site. | F88: Pending | G88: Expired | H88: Pending Review | I88: STBU | J88: CTANJZ04705 | M88: 45930 | T88: Y | U88: FUENTE: Deviation.csv, filas CSV 1430-1431; Workflow=Expired; Date Released=2025-07-18; Date Originated=2025-07-03; Site=FJZP, Plant=MCGA (sin convertir automaticamente a FJZ); 2 filas PN; APROBACION Y APLICABILIDAD NO VALIDADAS.
A89: DEV-CTANJZ04706 | B89: DEVIATION | C89: DP525064 | E89: DP525064 This deviation allows FJZ to build 68-104855-01 with several deviations that are listed in attached Document. | F89: Pending | G89: Expired | H89: Pending Review | I89: CVEBU | J89: CTANJZ04706 | M89: 45900 | T89: Y | U89: FUENTE: Deviation.csv, filas CSV 372-392; Workflow=Expired; Date Released=2025-07-15; Date Originated=2025-07-03; Site=FJZP, Plant=MCGA (sin convertir automaticamente a FJZ); 13 filas PN; APROBACION Y APLICABILIDAD NO VALIDADAS.
A90: DEV-CTANJZ04707 | B90: DEVIATION | C90: D604653 | E90: D604653 NGFWBU: Risk Buy: GQR No: GQR000055333; AQR No: AQR002398314; CPN: 15-14278-01; MFR NAME:DIODES INC; MPN: LXS0102VEXTo execute the above AQR at CM Site. | F90: Pending | G90: Expired | H90: Pending Review | I90: STBU | J90: CTANJZ04707 | M90: 45930 | T90: Y | U90: FUENTE: Deviation.csv, filas CSV 1424-1425; Workflow=Expired; Date Released=2025-07-18; Date Originated=2025-07-03; Site=FJZP, Plant=MCGA (sin convertir automaticamente a FJZ); 2 filas PN; APROBACION Y APLICABILIDAD NO VALIDADAS.
A91: DEV-CTANJZ04709 | B91: DEVIATION | C91: D604651 | E91: D604651 NGFWBU: Risk Buy: GQR No: GQR000056533 ; AQR No: AQR002427706; CPN: 29-6281-01; MFR NAME: TE CONNECTIVITY CORP ; MPN: 2057159-1.To execute the above AQR at CM Site. | F91: Pending | G91: Expired | H91: Pending Review | I91: STBU | J91: CTANJZ04709 | M91: 45930 | T91: Y | U91: FUENTE: Deviation.csv, filas CSV 1426-1427; Workflow=Expired; Date Released=2025-07-18; Date Originated=2025-07-03; Site=FJZP, Plant=MCGA (sin convertir automaticamente a FJZ); 2 filas PN; APROBACION Y APLICABILIDAD NO VALIDADAS.
A92: DEV-CTANJZ04710 | B92: DEVIATION | C92: D604750 | E92: D604750 NGFWBU: Risk Buy: GQR No: GQR000046866; AQR No:AQR002294673; CPN: 20-0150-02; MFR NAME: NEXPERIA USA INC; MPN: MMBT3904.To execute the above AQR at CM Site. | F92: Pending | G92: Expired | H92: Pending Review | I92: STBU | J92: CTANJZ04710 | M92: 45930 | T92: Y | U92: FUENTE: Deviation.csv, filas CSV 1438-1439; Workflow=Expired; Date Released=2025-07-18; Date Originated=2025-07-03; Site=FJZP, Plant=MCGA (sin convertir automaticamente a FJZ); 2 filas PN; APROBACION Y APLICABILIDAD NO VALIDADAS.
A93: DEV-CTANJZ04711 | B93: DEVIATION | C93: D604652 | E93: D604652 NGFWBU: Risk Buy: GQR No: GQR000056634; AQR No:AQR002431749; CPN: 25-1289-01; MFR NAME: STANLEY ELECTRIC; MPN: FYYPY1211C-10-TRTo execute the above AQR at CM Site. | F93: Pending | G93: Expired | H93: Pending Review | I93: STBU | J93: CTANJZ04711 | M93: 45930 | T93: Y | U93: FUENTE: Deviation.csv, filas CSV 1434-1437; Workflow=Expired; Date Released=2025-07-18; Date Originated=2025-07-03; Site=FJZP, Plant=MCGA (sin convertir automaticamente a FJZ); 2 filas PN; APROBACION Y APLICABILIDAD NO VALIDADAS.
A94: DEV-CTANJZ04721 | B94: DEVIATION | C94: D605020 | E94: D605020 Build a control run with 10 units using all the new parts to confirm no issues found17-102040-06: BIOS_ROMMON17-102041-07: SYSTEM FPGA CONFIG; SPI17-102043-03: NIC SPI17-102050-07: POWER SEQUENCER17-16001-07: System FPGA Akido Secure JTAG17-102102-03: NIC SPINOTE: The parts 17-102041-07 (FPGA CONFIG; SPI) and 17-16001-07 (FPGA+Akido+Secure_JTAG) **must be used** together. No mixing new versions with old version. No exceptions. | F94: Pending | G94: Expired | H94: Pending Review | I94: STBU | J94: CTANJZ04721 | M94: 46027 | T94: Y | U94: FUENTE: Deviation.csv, filas CSV 45-51; Workflow=Expired; Date Released=2025-07-24; Date Originated=2025-07-10; Site=FJZP, Plant=MCGA (sin convertir automaticamente a FJZ); 7 filas PN; APROBACION Y APLICABILIDAD NO VALIDADAS.
A95: DEV-CTANJZ04726 | B95: DEVIATION | C95: D604890 | E95: D604890Allow FJZ the usage of the -06 parts either thru risk buy or site balance for the number 700-107696-06.The EA612121 changed version -05 to -06 without notice to NGFWBU and the TANs were not included on it. | F95: Pending | G95: Expired | H95: Pending Review | I95: STBU | J95: CTANJZ04726 | M95: 45939 | T95: Y | U95: FUENTE: Deviation.csv, filas CSV 1724-1732; Workflow=Expired; Date Released=2025-07-26; Date Originated=2025-07-14; Site=FJZP, Plant=MCGA (sin convertir automaticamente a FJZ); 9 filas PN; APROBACION Y APLICABILIDAD NO VALIDADAS.
